{
  "caves": [
    {
      "x": 31.471022669900744,
      "y": 10.40886158767761,
      "max_capacity": 8
    },
    {
      "x": 4.131477823409401,
      "y": 34.940061961325064,
      "max_capacity": 12
    },
    {
      "x": 37.57132887248764,
      "y": 3.124324793419697,
      "max_capacity": 10
    },
    {
      "x": 10.28990254054859,
      "y": 30.188345205887444,
      "max_capacity": 12
    },
    {
      "x": 12.600136913135728,
      "y": 42.90302466378523,
      "max_capacity": 11
    },
    {
      "x": 46.90045056088142,
      "y": 20.554716746200096,
      "max_capacity": 9
    },
    {
      "x": 31.920117977553904,
      "y": 25.548945166739344,
      "max_capacity": 8
    },
    {
      "x": 19.594739374873445,
      "y": 21.26746489218794,
      "max_capacity": 9
    },
    {
      "x": 12.012864967682301,
      "y": 1.2709896403565235,
      "max_capacity": 11
    },
    {
      "x": 29.47598584281049,
      "y": 2.8406803674775216,
      "max_capacity": 12
    },
    {
      "x": 13.10533313427097,
      "y": 44.64374881845543,
      "max_capacity": 9
    },
    {
      "x": 30.90065489070187,
      "y": 15.573988444555976,
      "max_capacity": 7
    },
    {
      "x": 46.62761376368258,
      "y": 45.41830981942817,
      "max_capacity": 7
    },
    {
      "x": 45.35525615975733,
      "y": 0.6405280340741892,
      "max_capacity": 7
    },
    {
      "x": 21.544198872188208,
      "y": 38.24322790959268,
      "max_capacity": 8
    },
    {
      "x": 47.79961548331478,
      "y": 2.6634543367754726,
      "max_capacity": 7
    },
    {
      "x": 35.261545320636806,
      "y": 21.395694726537677,
      "max_capacity": 11
    },
    {
      "x": 43.200031117733786,
      "y": 22.46975970329727,
      "max_capacity": 8
    },
    {
      "x": 44.53226455623813,
      "y": 47.49535680060512,
      "max_capacity": 11
    },
    {
      "x": 2.0539194460303225,
      "y": 34.08257210798028,
      "max_capacity": 9
    },
    {
      "x": 37.27215707617267,
      "y": 21.55422582101039,
      "max_capacity": 7
    },
    {
      "x": 16.211108535231112,
      "y": 14.541005310005122,
      "max_capacity": 11
    },
    {
      "x": 19.233465747097885,
      "y": 6.782858548770876,
      "max_capacity": 7
    },
    {
      "x": 7.686557891155038,
      "y": 13.272460227073129,
      "max_capacity": 9
    },
    {
      "x": 27.487091287229106,
      "y": 25.146608563571114,
      "max_capacity": 12
    },
    {
      "x": 49.008076061520164,
      "y": 31.35397667908741,
      "max_capacity": 7
    },
    {
      "x": 48.19184905224512,
      "y": 2.641671719483596,
      "max_capacity": 12
    },
    {
      "x": 9.446242819375867,
      "y": 38.41471680749223,
      "max_capacity": 12
    },
    {
      "x": 48.42335346758559,
      "y": 45.589694740311224,
      "max_capacity": 10
    },
    {
      "x": 49.00784537336096,
      "y": 45.86221422650372,
      "max_capacity": 10
    },
    {
      "x": 44.14941976492061,
      "y": 48.89415215189945,
      "max_capacity": 7
    },
    {
      "x": 5.655166135234612,
      "y": 11.09043114770915,
      "max_capacity": 12
    },
    {
      "x": 35.602301604074746,
      "y": 23.21281656376579,
      "max_capacity": 11
    },
    {
      "x": 23.161728814290672,
      "y": 10.873689809795339,
      "max_capacity": 8
    },
    {
      "x": 23.583504315434823,
      "y": 48.630736454364666,
      "max_capacity": 11
    },
    {
      "x": 25.743711235022747,
      "y": 20.90454231380357,
      "max_capacity": 12
    },
    {
      "x": 24.5924548578045,
      "y": 19.97316901865762,
      "max_capacity": 11
    },
    {
      "x": 12.0511961697513,
      "y": 2.9224588108463623,
      "max_capacity": 8
    },
    {
      "x": 34.58428257322168,
      "y": 35.10785923424493,
      "max_capacity": 7
    },
    {
      "x": 9.738756440200685,
      "y": 38.79888982948148,
      "max_capacity": 8
    },
    {
      "x": 34.73549784110217,
      "y": 36.21920223568153,
      "max_capacity": 8
    },
    {
      "x": 17.135852503438386,
      "y": 37.57447816495732,
      "max_capacity": 10
    },
    {
      "x": 10.674653644426845,
      "y": 17.631611485476682,
      "max_capacity": 10
    },
    {
      "x": 48.18944585339962,
      "y": 5.429758132849488,
      "max_capacity": 10
    },
    {
      "x": 39.06971749522225,
      "y": 42.90673595851455,
      "max_capacity": 12
    },
    {
      "x": 32.78334620291265,
      "y": 27.050122781203832,
      "max_capacity": 10
    },
    {
      "x": 7.363746724312553,
      "y": 5.279270829097293,
      "max_capacity": 9
    },
    {
      "x": 34.70624888920676,
      "y": 1.2411000915190928,
      "max_capacity": 9
    },
    {
      "x": 3.5954287671435328,
      "y": 15.247716466628003,
      "max_capacity": 12
    },
    {
      "x": 25.096159778058635,
      "y": 6.593661162312276,
      "max_capacity": 7
    }
  ],
  "bushes": [
    {
      "max_calories": 1050,
      "x": 37.77845157300747,
      "y": 47.474323712526015
    },
    {
      "max_calories": 1250,
      "x": 1.5779821200750221,
      "y": 33.68349934415463
    },
    {
      "max_calories": 1200,
      "x": 8.30489584759128,
      "y": 12.982037521676698
    },
    {
      "max_calories": 1300,
      "x": 23.525414565957668,
      "y": 20.91694199652637
    },
    {
      "max_calories": 1300,
      "x": 44.91812979399092,
      "y": 24.376136394720227
    },
    {
      "max_calories": 1250,
      "x": 49.94458679313376,
      "y": 48.61240488632623
    },
    {
      "max_calories": 1250,
      "x": 32.985722181654076,
      "y": 40.53425890470041
    },
    {
      "max_calories": 1350,
      "x": 19.471985960627148,
      "y": 5.800320084055005
    },
    {
      "max_calories": 1100,
      "x": 35.56281708296366,
      "y": 35.77903569806391
    },
    {
      "max_calories": 1200,
      "x": 21.30960222544524,
      "y": 21.361105097803783
    },
    {
      "max_calories": 1350,
      "x": 26.656030820895115,
      "y": 27.155215064578876
    },
    {
      "max_calories": 1250,
      "x": 24.319913482393236,
      "y": 46.067895657291935
    },
    {
      "max_calories": 1050,
      "x": 14.17443797090222,
      "y": 2.3583382204865777
    },
    {
      "max_calories": 1450,
      "x": 28.476616252210786,
      "y": 33.9752797260883
    },
    {
      "max_calories": 1050,
      "x": 28.403877379435755,
      "y": 2.178409344500504
    },
    {
      "max_calories": 1350,
      "x": 4.767355493414477,
      "y": 43.04773781670464
    },
    {
      "max_calories": 1450,
      "x": 3.953555382011542,
      "y": 46.60819056484685
    },
    {
      "max_calories": 1150,
      "x": 39.82899414547652,
      "y": 6.106352443083507
    },
    {
      "max_calories": 1400,
      "x": 13.18130559193379,
      "y": 0.5095080433809074
    },
    {
      "max_calories": 1000,
      "x": 41.20886128966858,
      "y": 14.471967073298082
    },
    {
      "max_calories": 1500,
      "x": 35.1555911878483,
      "y": 22.236846369423997
    },
    {
      "max_calories": 1450,
      "x": 30.343227128954315,
      "y": 49.32741343495791
    },
    {
      "max_calories": 1200,
      "x": 48.663091347214014,
      "y": 24.952398594885505
    },
    {
      "max_calories": 1100,
      "x": 33.23655976536503,
      "y": 21.096007998138568
    },
    {
      "max_calories": 1150,
      "x": 12.944967977842476,
      "y": 6.704100407953373
    },
    {
      "max_calories": 1150,
      "x": 26.37542166860054,
      "y": 21.979203147829107
    },
    {
      "max_calories": 1050,
      "x": 46.75566169864955,
      "y": 27.624970766785783
    },
    {
      "max_calories": 1100,
      "x": 34.45777003381258,
      "y": 15.018776669075628
    },
    {
      "max_calories": 1450,
      "x": 23.836393876064605,
      "y": 7.818722698654257
    },
    {
      "max_calories": 1300,
      "x": 10.247663649737476,
      "y": 6.50394709756108
    },
    {
      "max_calories": 1450,
      "x": 21.13670663175774,
      "y": 5.402999055670388
    },
    {
      "max_calories": 1450,
      "x": 43.84107854137307,
      "y": 33.784092972765976
    },
    {
      "max_calories": 1050,
      "x": 8.891215713298116,
      "y": 11.419665742704609
    },
    {
      "max_calories": 1100,
      "x": 35.06239283407411,
      "y": 40.78020355007715
    },
    {
      "max_calories": 1450,
      "x": 35.06568156185306,
      "y": 46.64178728960107
    },
    {
      "max_calories": 1350,
      "x": 33.754465782130055,
      "y": 45.709325811748194
    },
    {
      "max_calories": 1450,
      "x": 38.93669532044459,
      "y": 48.358825237739566
    },
    {
      "max_calories": 1250,
      "x": 24.926639523040244,
      "y": 19.11896799634555
    },
    {
      "max_calories": 1500,
      "x": 19.325165512502934,
      "y": 3.205961169231636
    },
    {
      "max_calories": 1100,
      "x": 35.856957921917655,
      "y": 17.038534607351117
    },
    {
      "max_calories": 1400,
      "x": 31.592793627961917,
      "y": 33.371264026958094
    },
    {
      "max_calories": 1350,
      "x": 14.987023257971632,
      "y": 2.3720859756270807
    },
    {
      "max_calories": 1250,
      "x": 21.538721122277792,
      "y": 43.14834743291305
    },
    {
      "max_calories": 1500,
      "x": 38.21823955312473,
      "y": 10.398307105175409
    },
    {
      "max_calories": 1400,
      "x": 41.81912046758664,
      "y": 23.48645005794315
    },
    {
      "max_calories": 1250,
      "x": 31.605236173258334,
      "y": 2.8684918793273284
    },
    {
      "max_calories": 1500,
      "x": 22.075656937426363,
      "y": 14.105530412323747
    },
    {
      "max_calories": 1500,
      "x": 19.32007803442489,
      "y": 11.017713973493299
    },
    {
      "max_calories": 1100,
      "x": 3.2008564326054367,
      "y": 9.990977323540552
    },
    {
      "max_calories": 1500,
      "x": 22.00329109972749,
      "y": 31.650420237632463
    },
    {
      "max_calories": 1200,
      "x": 43.20926533777164,
      "y": 2.6930385620693387
    },
    {
      "max_calories": 1000,
      "x": 38.83333203650686,
      "y": 44.88080026854727
    },
    {
      "max_calories": 1350,
      "x": 10.380700186049857,
      "y": 45.401068163281785
    },
    {
      "max_calories": 1250,
      "x": 47.12860033356689,
      "y": 40.597266399620324
    },
    {
      "max_calories": 1050,
      "x": 20.990887822433134,
      "y": 5.875773989550098
    },
    {
      "max_calories": 1300,
      "x": 6.801995613278539,
      "y": 4.7848129354270075
    },
    {
      "max_calories": 1100,
      "x": 19.445988892212014,
      "y": 47.70543594436097
    },
    {
      "max_calories": 1450,
      "x": 49.35015499047275,
      "y": 35.45214248029915
    },
    {
      "max_calories": 1350,
      "x": 36.60945299768233,
      "y": 39.551427141028114
    },
    {
      "max_calories": 1450,
      "x": 5.902204143856283,
      "y": 41.92342530101698
    },
    {
      "max_calories": 1250,
      "x": 32.788147311673924,
      "y": 9.846743058161877
    },
    {
      "max_calories": 1400,
      "x": 35.1049298262431,
      "y": 47.57216407885974
    },
    {
      "max_calories": 1300,
      "x": 36.79901037795103,
      "y": 49.29560613281045
    },
    {
      "max_calories": 1350,
      "x": 0.9326132757467409,
      "y": 36.67522338448051
    },
    {
      "max_calories": 1450,
      "x": 16.3162382631547,
      "y": 45.69660801319314
    },
    {
      "max_calories": 1400,
      "x": 36.78062129832172,
      "y": 10.65733566289649
    },
    {
      "max_calories": 1500,
      "x": 1.1606149136838328,
      "y": 32.07398711392473
    },
    {
      "max_calories": 1050,
      "x": 16.54150686640059,
      "y": 21.16002123081511
    },
    {
      "max_calories": 1300,
      "x": 44.75784459805309,
      "y": 41.6522264020158
    },
    {
      "max_calories": 1000,
      "x": 49.07227007621415,
      "y": 2.2530822658466896
    },
    {
      "max_calories": 1100,
      "x": 5.884224419638684,
      "y": 25.00827701372942
    },
    {
      "max_calories": 1200,
      "x": 1.692463322437765,
      "y": 35.22437942277102
    },
    {
      "max_calories": 1400,
      "x": 26.618227765662507,
      "y": 47.37721227642078
    },
    {
      "max_calories": 1000,
      "x": 36.35035829058629,
      "y": 17.299680811755152
    },
    {
      "max_calories": 1100,
      "x": 0.23338712601837508,
      "y": 19.068345633649354
    }
  ],
  "agents": [
    {
      "max_memory": 4,
      "aggressiveness": 0.4574165683196484,
      "harvest_percent": 0.9731958288579513,
      "x": 32.78334620291265,
      "y": 27.050122781203832
    },
    {
      "max_memory": 9,
      "aggressiveness": 0.43908018939903914,
      "harvest_percent": 0.22550563727884965,
      "x": 35.602301604074746,
      "y": 23.21281656376579
    },
    {
      "max_memory": 5,
      "aggressiveness": 0.20802536098677127,
      "harvest_percent": 0.33328753109222464,
      "x": 31.920117977553904,
      "y": 25.548945166739344
    },
    {
      "max_memory": 0,
      "aggressiveness": 0.10267040855999776,
      "harvest_percent": 0.6053350598806974,
      "x": 25.743711235022747,
      "y": 20.90454231380357
    },
    {
      "max_memory": 7,
      "aggressiveness": 0.31202566737435944,
      "harvest_percent": 0.21305604553284485,
      "x": 19.594739374873445,
      "y": 21.26746489218794
    },
    {
      "max_memory": 0,
      "aggressiveness": 0.7100989649512434,
      "harvest_percent": 0.7412679563235303,
      "x": 31.920117977553904,
      "y": 25.548945166739344
    },
    {
      "max_memory": 5,
      "aggressiveness": 0.5719187612778268,
      "harvest_percent": 0.6968194453072051,
      "x": 27.487091287229106,
      "y": 25.146608563571114
    },
    {
      "max_memory": 17,
      "aggressiveness": 0.10663352861828657,
      "harvest_percent": 0.8410936306776116,
      "x": 32.78334620291265,
      "y": 27.050122781203832
    },
    {
      "max_memory": 18,
      "aggressiveness": 0.9052400325227614,
      "harvest_percent": 0.7776889370149614,
      "x": 31.920117977553904,
      "y": 25.548945166739344
    },
    {
      "max_memory": 2,
      "aggressiveness": 0.19149356915717952,
      "harvest_percent": 0.3507775482097416,
      "x": 27.487091287229106,
      "y": 25.146608563571114
    },
    {
      "max_memory": 5,
      "aggressiveness": 0.04140466094424966,
      "harvest_percent": 0.3800566927944561,
      "x": 31.920117977553904,
      "y": 25.548945166739344
    },
    {
      "max_memory": 19,
      "aggressiveness": 0.6188917583146406,
      "harvest_percent": 0.13529826905902265,
      "x": 16.211108535231112,
      "y": 14.541005310005122
    },
    {
      "max_memory": 3,
      "aggressiveness": 0.799513814532173,
      "harvest_percent": 0.5470882649789837,
      "x": 35.602301604074746,
      "y": 23.21281656376579
    },
    {
      "max_memory": 11,
      "aggressiveness": 0.8648347826848739,
      "harvest_percent": 0.5269881277926508,
      "x": 27.487091287229106,
      "y": 25.146608563571114
    },
    {
      "max_memory": 10,
      "aggressiveness": 0.7560979644126672,
      "harvest_percent": 0.7519943385200328,
      "x": 32.78334620291265,
      "y": 27.050122781203832
    },
    {
      "max_memory": 16,
      "aggressiveness": 0.6623207659447732,
      "harvest_percent": 0.5709698067807576,
      "x": 30.90065489070187,
      "y": 15.573988444555976
    },
    {
      "max_memory": 4,
      "aggressiveness": 0.6365891683177183,
      "harvest_percent": 0.13317798970144523,
      "x": 34.73549784110217,
      "y": 36.21920223568153
    },
    {
      "max_memory": 5,
      "aggressiveness": 0.4927447251104905,
      "harvest_percent": 0.17932789778259695,
      "x": 24.5924548578045,
      "y": 19.97316901865762
    },
    {
      "max_memory": 10,
      "aggressiveness": 0.962251906127358,
      "harvest_percent": 0.3759740132335003,
      "x": 27.487091287229106,
      "y": 25.146608563571114
    },
    {
      "max_memory": 20,
      "aggressiveness": 0.6178209847196517,
      "harvest_percent": 0.544684289255706,
      "x": 27.487091287229106,
      "y": 25.146608563571114
    },
    {
      "max_memory": 9,
      "aggressiveness": 0.919667930189889,
      "harvest_percent": 0.9130870817911886,
      "x": 31.920117977553904,
      "y": 25.548945166739344
    },
    {
      "max_memory": 8,
      "aggressiveness": 0.5941043378070833,
      "harvest_percent": 0.7818768016162899,
      "x": 35.261545320636806,
      "y": 21.395694726537677
    },
    {
      "max_memory": 6,
      "aggressiveness": 0.36273866531004706,
      "harvest_percent": 0.009500438520214982,
      "x": 30.90065489070187,
      "y": 15.573988444555976
    },
    {
      "max_memory": 1,
      "aggressiveness": 0.7209950914641013,
      "harvest_percent": 0.3083638842318498,
      "x": 32.78334620291265,
      "y": 27.050122781203832
    },
    {
      "max_memory": 17,
      "aggressiveness": 0.9922199241401615,
      "harvest_percent": 0.01174251485324096,
      "x": 31.920117977553904,
      "y": 25.548945166739344
    },
    {
      "max_memory": 17,
      "aggressiveness": 0.8676296291063958,
      "harvest_percent": 0.8499396706072742,
      "x": 9.738756440200685,
      "y": 38.79888982948148
    },
    {
      "max_memory": 15,
      "aggressiveness": 0.9130600036993832,
      "harvest_percent": 0.7374254500183653,
      "x": 24.5924548578045,
      "y": 19.97316901865762
    },
    {
      "max_memory": 5,
      "aggressiveness": 0.7450720803414042,
      "harvest_percent": 0.9308145161618566,
      "x": 44.14941976492061,
      "y": 48.89415215189945
    },
    {
      "max_memory": 6,
      "aggressiveness": 0.743446424887111,
      "harvest_percent": 0.8972281142993307,
      "x": 32.78334620291265,
      "y": 27.050122781203832
    },
    {
      "max_memory": 4,
      "aggressiveness": 0.8561514622914791,
      "harvest_percent": 0.9126806037343083,
      "x": 31.920117977553904,
      "y": 25.548945166739344
    },
    {
      "max_memory": 4,
      "aggressiveness": 0.768769969784391,
      "harvest_percent": 1,
      "x": 32.78334620291265,
      "y": 27.050122781203832
    },
    {
      "max_memory": 10,
      "aggressiveness": 0.476721081542696,
      "harvest_percent": 0.41473522880386743,
      "x": 32.78334620291265,
      "y": 27.050122781203832
    },
    {
      "max_memory": 10,
      "aggressiveness": 0.42396604786992415,
      "harvest_percent": 0.286929056826314,
      "x": 12.012864967682301,
      "y": 1.2709896403565235
    },
    {
      "max_memory": 6,
      "aggressiveness": 0.5977697966791661,
      "harvest_percent": 0.5373711844652291,
      "x": 39.06971749522225,
      "y": 42.90673595851455
    },
    {
      "max_memory": 8,
      "aggressiveness": 0.559601264092752,
      "harvest_percent": 0.4982783483258452,
      "x": 46.62761376368258,
      "y": 45.41830981942817
    },
    {
      "max_memory": 8,
      "aggressiveness": 0.6546610060077358,
      "harvest_percent": 0.29276916345843707,
      "x": 34.73549784110217,
      "y": 36.21920223568153
    },
    {
      "max_memory": 6,
      "aggressiveness": 0.6988307733430822,
      "harvest_percent": 0.6877965794827231,
      "x": 35.602301604074746,
      "y": 23.21281656376579
    },
    {
      "max_memory": 9,
      "aggressiveness": 0.6316388986975167,
      "harvest_percent": 0.25431593180334106,
      "x": 32.78334620291265,
      "y": 27.050122781203832
    },
    {
      "max_memory": 6,
      "aggressiveness": 0.6156955319432793,
      "harvest_percent": 0.3317032386939379,
      "x": 5.655166135234612,
      "y": 11.09043114770915
    },
    {
      "max_memory": 12,
      "aggressiveness": 0.24751160982018583,
      "harvest_percent": 0.048040164358264636,
      "x": 27.487091287229106,
      "y": 25.146608563571114
    },
    {
      "max_memory": 10,
      "aggressiveness": 0.3255866041997256,
      "harvest_percent": 0.1602627377684031,
      "x": 19.233465747097885,
      "y": 6.782858548770876
    },
    {
      "max_memory": 12,
      "aggressiveness": 0.30858810862021663,
      "harvest_percent": 0.1530904868442993,
      "x": 7.363746724312553,
      "y": 5.279270829097293
    },
    {
      "max_memory": 2,
      "aggressiveness": 0.5268383203401148,
      "harvest_percent": 0.5258247436687524,
      "x": 19.233465747097885,
      "y": 6.782858548770876
    },
    {
      "max_memory": 4,
      "aggressiveness": 0.5194507767198849,
      "harvest_percent": 0.4983170512332777,
      "x": 10.674653644426845,
      "y": 17.631611485476682
    },
    {
      "max_memory": 10,
      "aggressiveness": 0.27063687126766683,
      "harvest_percent": 0.7364146885703293,
      "x": 31.471022669900744,
      "y": 10.40886158767761
    },
    {
      "max_memory": 12,
      "aggressiveness": 0.1569005426716777,
      "harvest_percent": 0.6838095089489602,
      "x": 19.233465747097885,
      "y": 6.782858548770876
    },
    {
      "max_memory": 9,
      "aggressiveness": 0.37219817217916373,
      "harvest_percent": 0.4801061999284241,
      "x": 43.200031117733786,
      "y": 22.46975970329727
    },
    {
      "max_memory": 7,
      "aggressiveness": 0.23984714041236888,
      "harvest_percent": 0.33847427878099834,
      "x": 27.487091287229106,
      "y": 25.146608563571114
    },
    {
      "max_memory": 11,
      "aggressiveness": 0.2808114146216311,
      "harvest_percent": 0.39592753286503524,
      "x": 25.743711235022747,
      "y": 20.90454231380357
    },
    {
      "max_memory": 7,
      "aggressiveness": 0.2239128233566729,
      "harvest_percent": 0.4666262418350633,
      "x": 27.487091287229106,
      "y": 25.146608563571114
    },
    {
      "max_memory": 7,
      "aggressiveness": 0.3532759793464949,
      "harvest_percent": 0.3369566396560115,
      "x": 35.261545320636806,
      "y": 21.395694726537677
    },
    {
      "max_memory": 10,
      "aggressiveness": 0.2132230568676997,
      "harvest_percent": 0.3937818058237024,
      "x": 7.363746724312553,
      "y": 5.279270829097293
    },
    {
      "max_memory": 11,
      "aggressiveness": 0.3112015455246446,
      "harvest_percent": 0.5047817420163223,
      "x": 31.471022669900744,
      "y": 10.40886158767761
    },
    {
      "max_memory": 7,
      "aggressiveness": 0.2985617206977387,
      "harvest_percent": 0.4578897698935101,
      "x": 35.602301604074746,
      "y": 23.21281656376579
    },
    {
      "max_memory": 10,
      "aggressiveness": 0.3888935181074598,
      "harvest_percent": 0.46121364934345194,
      "x": 34.73549784110217,
      "y": 36.21920223568153
    },
    {
      "max_memory": 16,
      "aggressiveness": 0.5782467807578988,
      "harvest_percent": 0.5564157907859735,
      "x": 44.53226455623813,
      "y": 47.49535680060512
    },
    {
      "max_memory": 6,
      "aggressiveness": 0.3599811647938296,
      "harvest_percent": 0.6701343349949571,
      "x": 34.58428257322168,
      "y": 35.10785923424493
    },
    {
      "max_memory": 3,
      "aggressiveness": 0.3822384506983951,
      "harvest_percent": 0.47086378467747375,
      "x": 35.602301604074746,
      "y": 23.21281656376579
    },
    {
      "max_memory": 9,
      "aggressiveness": 0.21854745781598287,
      "harvest_percent": 0.5788454330737595,
      "x": 31.471022669900744,
      "y": 10.40886158767761
    },
    {
      "max_memory": 10,
      "aggressiveness": 0.3876598094503082,
      "harvest_percent": 0.5419491156554052,
      "x": 31.471022669900744,
      "y": 10.40886158767761
    },
    {
      "max_memory": 11,
      "aggressiveness": 0.2114280995759744,
      "harvest_percent": 0.6591389494107578,
      "x": 31.471022669900744,
      "y": 10.40886158767761
    },
    {
      "max_memory": 10,
      "aggressiveness": 0.3388388535324417,
      "harvest_percent": 0.6427015731242172,
      "x": 31.471022669900744,
      "y": 10.40886158767761
    },
    {
      "max_memory": 9,
      "aggressiveness": 0.24923397278368878,
      "harvest_percent": 0.6695322403720859,
      "x": 31.471022669900744,
      "y": 10.40886158767761
    },
    {
      "max_memory": 8,
      "aggressiveness": 0.3706466873029382,
      "harvest_percent": 0.6537440454083268,
      "x": 31.471022669900744,
      "y": 10.40886158767761
    },
    {
      "max_memory": 3,
      "aggressiveness": 0.4615389366072164,
      "harvest_percent": 0.47119603487420547,
      "x": 31.920117977553904,
      "y": 25.548945166739344
    },
    {
      "max_memory": 9,
      "aggressiveness": 0.5397359458363455,
      "harvest_percent": 0.19728311310247107,
      "x": 30.90065489070187,
      "y": 15.573988444555976
    },
    {
      "max_memory": 12,
      "aggressiveness": 0.4522484319488666,
      "harvest_percent": 0.32559279733868235,
      "x": 30.90065489070187,
      "y": 15.573988444555976
    },
    {
      "max_memory": 12,
      "aggressiveness": 0.427934579237081,
      "harvest_percent": 0.25877973034665597,
      "x": 30.90065489070187,
      "y": 15.573988444555976
    },
    {
      "max_memory": 9,
      "aggressiveness": 0.5393467739790011,
      "harvest_percent": 0.3733224072413335,
      "x": 30.90065489070187,
      "y": 15.573988444555976
    },
    {
      "max_memory": 10,
      "aggressiveness": 0.44219534446210107,
      "harvest_percent": 0.2989627015715941,
      "x": 30.90065489070187,
      "y": 15.573988444555976
    },
    {
      "max_memory": 5,
      "aggressiveness": 0.4690645351155607,
      "harvest_percent": 0.46122973229815994,
      "x": 35.261545320636806,
      "y": 21.395694726537677
    },
    {
      "max_memory": 7,
      "aggressiveness": 0.5143720300936996,
      "harvest_percent": 0.5692405676742291,
      "x": 35.261545320636806,
      "y": 21.395694726537677
    },
    {
      "max_memory": 5,
      "aggressiveness": 0.4382474193913277,
      "harvest_percent": 0.6117934372795244,
      "x": 35.261545320636806,
      "y": 21.395694726537677
    },
    {
      "max_memory": 8,
      "aggressiveness": 0.4655655525601342,
      "harvest_percent": 0.522198493844275,
      "x": 35.261545320636806,
      "y": 21.395694726537677
    },
    {
      "max_memory": 6,
      "aggressiveness": 0.4623155393404383,
      "harvest_percent": 0.6264788535219955,
      "x": 35.261545320636806,
      "y": 21.395694726537677
    },
    {
      "max_memory": 9,
      "aggressiveness": 0.46473016489795216,
      "harvest_percent": 0.47498137969437704,
      "x": 35.261545320636806,
      "y": 21.395694726537677
    },
    {
      "max_memory": 7,
      "aggressiveness": 0.509463987920914,
      "harvest_percent": 0.48919104236592426,
      "x": 35.261545320636806,
      "y": 21.395694726537677
    },
    {
      "max_memory": 8,
      "aggressiveness": 0.3966978508568574,
      "harvest_percent": 0.603616543316813,
      "x": 35.261545320636806,
      "y": 21.395694726537677
    },
    {
      "max_memory": 5,
      "aggressiveness": 0.4352131405761759,
      "harvest_percent": 0.543475156751935,
      "x": 35.261545320636806,
      "y": 21.395694726537677
    },
    {
      "max_memory": 10,
      "aggressiveness": 0.24697865861070126,
      "harvest_percent": 0.42161007061218875,
      "x": 19.233465747097885,
      "y": 6.782858548770876
    },
    {
      "max_memory": 7,
      "aggressiveness": 0.28535097865572556,
      "harvest_percent": 0.5056934201620522,
      "x": 19.233465747097885,
      "y": 6.782858548770876
    },
    {
      "max_memory": 9,
      "aggressiveness": 0.3380785850231458,
      "harvest_percent": 0.3959024794113535,
      "x": 19.233465747097885,
      "y": 6.782858548770876
    },
    {
      "max_memory": 5,
      "aggressiveness": 0.46559959293500186,
      "harvest_percent": 0.26737145592993405,
      "x": 19.233465747097885,
      "y": 6.782858548770876
    },
    {
      "max_memory": 4,
      "aggressiveness": 0.2960672543341377,
      "harvest_percent": 0.4296863436958479,
      "x": 27.487091287229106,
      "y": 25.146608563571114
    },
    {
      "max_memory": 7,
      "aggressiveness": 0.253832859941194,
      "harvest_percent": 0.10550182999248028,
      "x": 27.487091287229106,
      "y": 25.146608563571114
    },
    {
      "max_memory": 4,
      "aggressiveness": 0.5045751469939107,
      "harvest_percent": 0.5367743064845288,
      "x": 27.487091287229106,
      "y": 25.146608563571114
    },
    {
      "max_memory": 17,
      "aggressiveness": 0.4816348155042281,
      "harvest_percent": 0.2595917013564098,
      "x": 27.487091287229106,
      "y": 25.146608563571114
    },
    {
      "max_memory": 5,
      "aggressiveness": 0.40689115867346914,
      "harvest_percent": 0.4136713590971392,
      "x": 35.602301604074746,
      "y": 23.21281656376579
    },
    {
      "max_memory": 8,
      "aggressiveness": 0.6835637450518309,
      "harvest_percent": 0.48418161176605584,
      "x": 35.602301604074746,
      "y": 23.21281656376579
    },
    {
      "max_memory": 7,
      "aggressiveness": 0.5970231815861043,
      "harvest_percent": 0.5917526434226305,
      "x": 35.602301604074746,
      "y": 23.21281656376579
    },
    {
      "max_memory": 5,
      "aggressiveness": 0.6354712649560894,
      "harvest_percent": 0.4360179633617848,
      "x": 35.602301604074746,
      "y": 23.21281656376579
    },
    {
      "max_memory": 6,
      "aggressiveness": 0.7949558468095589,
      "harvest_percent": 0.5951283319086779,
      "x": 35.602301604074746,
      "y": 23.21281656376579
    },
    {
      "max_memory": 3,
      "aggressiveness": 0.6766322119131428,
      "harvest_percent": 0.4107939601873907,
      "x": 35.602301604074746,
      "y": 23.21281656376579
    },
    {
      "max_memory": 3,
      "aggressiveness": 0.2131516414364792,
      "harvest_percent": 0.5683524697216982,
      "x": 25.743711235022747,
      "y": 20.90454231380357
    },
    {
      "max_memory": 3,
      "aggressiveness": 0.27278032451560746,
      "harvest_percent": 0.470455544604758,
      "x": 25.743711235022747,
      "y": 20.90454231380357
    },
    {
      "max_memory": 7,
      "aggressiveness": 0.12443115716881126,
      "harvest_percent": 0.4023880919556064,
      "x": 25.743711235022747,
      "y": 20.90454231380357
    },
    {
      "max_memory": 3,
      "aggressiveness": 0.19882422237230615,
      "harvest_percent": 0.5228695659386753,
      "x": 25.743711235022747,
      "y": 20.90454231380357
    },
    {
      "max_memory": 4,
      "aggressiveness": 0.1920957240720672,
      "harvest_percent": 0.47786232886870594,
      "x": 25.743711235022747,
      "y": 20.90454231380357
    },
    {
      "max_memory": 3,
      "aggressiveness": 0.15072798504404938,
      "harvest_percent": 0.42561063087421214,
      "x": 25.743711235022747,
      "y": 20.90454231380357
    },
    {
      "max_memory": 6,
      "aggressiveness": 0.2430825296192343,
      "harvest_percent": 0.5396845131989411,
      "x": 25.743711235022747,
      "y": 20.90454231380357
    },
    {
      "max_memory": 5,
      "aggressiveness": 0.1163230562123145,
      "harvest_percent": 0.4674460933358966,
      "x": 25.743711235022747,
      "y": 20.90454231380357
    },
    {
      "max_memory": 5,
      "aggressiveness": 0.28049312002056803,
      "harvest_percent": 0.40579099350034464,
      "x": 25.743711235022747,
      "y": 20.90454231380357
    },
    {
      "max_memory": 5,
      "aggressiveness": 0.2279317935554145,
      "harvest_percent": 0.5163373560820657,
      "x": 25.743711235022747,
      "y": 20.90454231380357
    },
    {
      "max_memory": 12,
      "aggressiveness": 0.7373268965355068,
      "harvest_percent": 0.545832121058914,
      "x": 24.5924548578045,
      "y": 19.97316901865762
    },
    {
      "max_memory": 9,
      "aggressiveness": 0.7602234996709328,
      "harvest_percent": 0.4845067047231524,
      "x": 24.5924548578045,
      "y": 19.97316901865762
    },
    {
      "max_memory": 12,
      "aggressiveness": 0.6954919580519651,
      "harvest_percent": 0.5344440182444545,
      "x": 24.5924548578045,
      "y": 19.97316901865762
    },
    {
      "max_memory": 12,
      "aggressiveness": 0.6108164727564491,
      "harvest_percent": 0.4164321903958507,
      "x": 24.5924548578045,
      "y": 19.97316901865762
    },
    {
      "max_memory": 11,
      "aggressiveness": 0.6809255545340401,
      "harvest_percent": 0.3999869027172283,
      "x": 24.5924548578045,
      "y": 19.97316901865762
    },
    {
      "max_memory": 12,
      "aggressiveness": 0.6507667391080147,
      "harvest_percent": 0.3954380647981681,
      "x": 24.5924548578045,
      "y": 19.97316901865762
    },
    {
      "max_memory": 9,
      "aggressiveness": 0.7358889361023125,
      "harvest_percent": 0.4910515777268701,
      "x": 24.5924548578045,
      "y": 19.97316901865762
    },
    {
      "max_memory": 10,
      "aggressiveness": 0.7898593008564395,
      "harvest_percent": 0.36228085466119453,
      "x": 24.5924548578045,
      "y": 19.97316901865762
    },
    {
      "max_memory": 11,
      "aggressiveness": 0.7908946092058816,
      "harvest_percent": 0.5492910771218282,
      "x": 24.5924548578045,
      "y": 19.97316901865762
    },
    {
      "max_memory": 5,
      "aggressiveness": 0.4573985754507557,
      "harvest_percent": 0.24511591836921182,
      "x": 34.73549784110217,
      "y": 36.21920223568153
    },
    {
      "max_memory": 8,
      "aggressiveness": 0.5500343493157893,
      "harvest_percent": 0.33344508193468014,
      "x": 34.73549784110217,
      "y": 36.21920223568153
    },
    {
      "max_memory": 5,
      "aggressiveness": 0.5305862581415416,
      "harvest_percent": 0.3831453657640411,
      "x": 34.73549784110217,
      "y": 36.21920223568153
    },
    {
      "max_memory": 7,
      "aggressiveness": 0.6136766928223076,
      "harvest_percent": 0.21322566034696477,
      "x": 34.73549784110217,
      "y": 36.21920223568153
    },
    {
      "max_memory": 8,
      "aggressiveness": 0.5302082711741432,
      "harvest_percent": 0.27179027938053746,
      "x": 34.73549784110217,
      "y": 36.21920223568153
    },
    {
      "max_memory": 10,
      "aggressiveness": 0.5743253825332759,
      "harvest_percent": 0.5906294979745856,
      "x": 32.78334620291265,
      "y": 27.050122781203832
    },
    {
      "max_memory": 5,
      "aggressiveness": 0.5474664116671425,
      "harvest_percent": 0.7726815658916182,
      "x": 32.78334620291265,
      "y": 27.050122781203832
    },
    {
      "max_memory": 9,
      "aggressiveness": 0.31302185118587367,
      "harvest_percent": 0.3269308806915858,
      "x": 7.363746724312553,
      "y": 5.279270829097293
    },
    {
      "max_memory": 13,
      "aggressiveness": 0.2688115031869315,
      "harvest_percent": 0.33420533443019096,
      "x": 7.363746724312553,
      "y": 5.279270829097293
    },
    {
      "max_memory": 9,
      "aggressiveness": 0.3542673908065172,
      "harvest_percent": 0.3355449894938855,
      "x": 7.363746724312553,
      "y": 5.279270829097293
    },
    {
      "max_memory": 10,
      "aggressiveness": 0.275076561934813,
      "harvest_percent": 0.24418357571193355,
      "x": 7.363746724312553,
      "y": 5.279270829097293
    },
    {
      "max_memory": 9,
      "aggressiveness": 0.2529540672220416,
      "harvest_percent": 0.2167965403478115,
      "x": 7.363746724312553,
      "y": 5.279270829097293
    },
    {
      "max_memory": 11,
      "aggressiveness": 0.32166229219817605,
      "harvest_percent": 0.29146763236292234,
      "x": 7.363746724312553,
      "y": 5.279270829097293
    },
    {
      "max_memory": 11,
      "aggressiveness": 0.28613063690364793,
      "harvest_percent": 0.18448924566253344,
      "x": 7.363746724312553,
      "y": 5.279270829097293
    }
  ]
}