{
  "caves": [
    {
      "x": 20.52640290826823,
      "y": 21.16699613764489,
      "max_capacity": 3
    },
    {
      "x": 33.766630660222674,
      "y": 33.90118389171753,
      "max_capacity": 7
    },
    {
      "x": 5.2966242178564995,
      "y": 12.605520141362419,
      "max_capacity": 6
    },
    {
      "x": 5.69209511753917,
      "y": 13.997789505020775,
      "max_capacity": 4
    },
    {
      "x": 10.942108846011262,
      "y": 42.4879396956918,
      "max_capacity": 7
    },
    {
      "x": 11.677284795115794,
      "y": 46.99348170134856,
      "max_capacity": 6
    },
    {
      "x": 5.146920272074834,
      "y": 27.959640382352056,
      "max_capacity": 3
    },
    {
      "x": 21.896154748448925,
      "y": 3.771374048040582,
      "max_capacity": 3
    },
    {
      "x": 13.977255801846178,
      "y": 27.62375605132648,
      "max_capacity": 6
    },
    {
      "x": 46.503499655435945,
      "y": 23.412658031046995,
      "max_capacity": 7
    },
    {
      "x": 3.070285052901939,
      "y": 0.5626608050325776,
      "max_capacity": 4
    },
    {
      "x": 29.323626893404846,
      "y": 45.09400617039564,
      "max_capacity": 6
    },
    {
      "x": 6.719618095455459,
      "y": 1.486079709229593,
      "max_capacity": 5
    },
    {
      "x": 30.069339014963326,
      "y": 48.73043522516644,
      "max_capacity": 3
    },
    {
      "x": 23.937718940988923,
      "y": 27.98678456478687,
      "max_capacity": 7
    },
    {
      "x": 22.712440096565,
      "y": 26.14506248715611,
      "max_capacity": 6
    },
    {
      "x": 19.935931174199872,
      "y": 25.85059696265238,
      "max_capacity": 6
    },
    {
      "x": 15.773269219016777,
      "y": 8.578429964214351,
      "max_capacity": 6
    },
    {
      "x": 12.860900119219421,
      "y": 10.016124821329475,
      "max_capacity": 7
    },
    {
      "x": 37.79008627321713,
      "y": 10.196191585811626,
      "max_capacity": 5
    },
    {
      "x": 2.0653053392223395,
      "y": 7.607335119149106,
      "max_capacity": 7
    },
    {
      "x": 38.15942886183754,
      "y": 10.132813390100704,
      "max_capacity": 7
    },
    {
      "x": 43.33137024061182,
      "y": 5.59439380549348,
      "max_capacity": 4
    },
    {
      "x": 33.61358852200279,
      "y": 35.76878244258877,
      "max_capacity": 7
    },
    {
      "x": 44.90862263325064,
      "y": 49.9910254677252,
      "max_capacity": 7
    },
    {
      "x": 29.96170020807028,
      "y": 20.47709975343238,
      "max_capacity": 4
    },
    {
      "x": 9.208621382913373,
      "y": 1.6040155327261219,
      "max_capacity": 6
    },
    {
      "x": 47.38211060367122,
      "y": 0.14145000322353662,
      "max_capacity": 7
    },
    {
      "x": 25.961949846587228,
      "y": 25.101038584325046,
      "max_capacity": 5
    },
    {
      "x": 28.329900693984023,
      "y": 38.83864167552341,
      "max_capacity": 7
    },
    {
      "x": 9.30640007952933,
      "y": 44.28451444478173,
      "max_capacity": 6
    },
    {
      "x": 15.950226796625094,
      "y": 39.308928389373634,
      "max_capacity": 4
    },
    {
      "x": 19.62612853105434,
      "y": 29.756668607316566,
      "max_capacity": 4
    },
    {
      "x": 22.19761071348902,
      "y": 36.6510024029399,
      "max_capacity": 3
    },
    {
      "x": 17.999840858514414,
      "y": 23.989015523426293,
      "max_capacity": 5
    },
    {
      "x": 46.50010742897414,
      "y": 2.9260499759116154,
      "max_capacity": 5
    },
    {
      "x": 4.829990026093201,
      "y": 13.486351475483987,
      "max_capacity": 5
    },
    {
      "x": 1.0802634137206724,
      "y": 3.952692865091245,
      "max_capacity": 5
    },
    {
      "x": 0.23597151477383616,
      "y": 19.373523525068485,
      "max_capacity": 4
    },
    {
      "x": 39.62392986896302,
      "y": 30.034085205618013,
      "max_capacity": 5
    },
    {
      "x": 24.95745353376821,
      "y": 33.14793810146956,
      "max_capacity": 4
    },
    {
      "x": 32.72003226298622,
      "y": 7.387771573958702,
      "max_capacity": 6
    },
    {
      "x": 44.38722029481967,
      "y": 3.6592677125430075,
      "max_capacity": 4
    },
    {
      "x": 20.47435766053431,
      "y": 38.095985781171684,
      "max_capacity": 4
    },
    {
      "x": 34.00579959038977,
      "y": 40.83738387905448,
      "max_capacity": 3
    },
    {
      "x": 4.8793948810314625,
      "y": 19.143569867871378,
      "max_capacity": 3
    },
    {
      "x": 27.152176398670573,
      "y": 29.34014300153054,
      "max_capacity": 3
    },
    {
      "x": 6.831213358044525,
      "y": 27.780272938661476,
      "max_capacity": 4
    },
    {
      "x": 17.564036584444825,
      "y": 22.515031482305282,
      "max_capacity": 3
    },
    {
      "x": 19.620619109759012,
      "y": 38.73105759057739,
      "max_capacity": 3
    },
    {
      "x": 13.599425095278772,
      "y": 32.375982224743524,
      "max_capacity": 5
    },
    {
      "x": 22.333584394580175,
      "y": 3.2722989274073857,
      "max_capacity": 7
    },
    {
      "x": 37.546390057309196,
      "y": 25.20854606586193,
      "max_capacity": 5
    },
    {
      "x": 17.783935869628408,
      "y": 19.075512290327403,
      "max_capacity": 5
    },
    {
      "x": 8.061689062848748,
      "y": 30.970470256584083,
      "max_capacity": 4
    },
    {
      "x": 37.237538316018,
      "y": 11.330120403514254,
      "max_capacity": 7
    },
    {
      "x": 24.46579941232964,
      "y": 6.877769254462524,
      "max_capacity": 6
    },
    {
      "x": 21.62772502446752,
      "y": 8.066425974333463,
      "max_capacity": 5
    },
    {
      "x": 7.403017488290775,
      "y": 9.233144832370888,
      "max_capacity": 6
    },
    {
      "x": 48.67053878228935,
      "y": 36.16888251042341,
      "max_capacity": 7
    },
    {
      "x": 35.48071659805811,
      "y": 14.604281048469032,
      "max_capacity": 6
    },
    {
      "x": 8.518408452193965,
      "y": 30.464312714179737,
      "max_capacity": 3
    },
    {
      "x": 25.414680222313972,
      "y": 41.10851723785762,
      "max_capacity": 6
    },
    {
      "x": 22.037605399258787,
      "y": 6.65868295476097,
      "max_capacity": 6
    },
    {
      "x": 3.4442625268090055,
      "y": 34.170448500517026,
      "max_capacity": 6
    },
    {
      "x": 39.09082402460171,
      "y": 35.01809507918676,
      "max_capacity": 3
    },
    {
      "x": 4.301779732742089,
      "y": 15.324165103777526,
      "max_capacity": 4
    },
    {
      "x": 6.454200461978498,
      "y": 14.398358187651123,
      "max_capacity": 4
    },
    {
      "x": 38.30100530709079,
      "y": 26.857932314991473,
      "max_capacity": 3
    },
    {
      "x": 14.789947384290103,
      "y": 24.68938159819788,
      "max_capacity": 6
    }
  ],
  "bushes": [
    {
      "max_calories": 700,
      "x": 38.658222484322884,
      "y": 42.0926796151058
    },
    {
      "max_calories": 450,
      "x": 6.431520823583304,
      "y": 34.61431205783169
    },
    {
      "max_calories": 650,
      "x": 14.476356691658044,
      "y": 26.93130511834838
    },
    {
      "max_calories": 800,
      "x": 41.599211344614865,
      "y": 27.408943942043873
    },
    {
      "max_calories": 550,
      "x": 40.05827024579893,
      "y": 31.161111188900065
    },
    {
      "max_calories": 800,
      "x": 33.75004525182971,
      "y": 4.42184968799883
    },
    {
      "max_calories": 600,
      "x": 49.57450190918634,
      "y": 30.239958296180404
    },
    {
      "max_calories": 450,
      "x": 14.014652364214609,
      "y": 21.632930217768447
    },
    {
      "max_calories": 650,
      "x": 4.87188483928847,
      "y": 5.275830314477431
    },
    {
      "max_calories": 650,
      "x": 10.91028568758018,
      "y": 38.99496208315982
    },
    {
      "max_calories": 450,
      "x": 18.082482026828377,
      "y": 20.36432276389022
    },
    {
      "max_calories": 600,
      "x": 0.8807625321499868,
      "y": 12.63458524501343
    },
    {
      "max_calories": 750,
      "x": 14.366089517830948,
      "y": 3.9950698889560043
    },
    {
      "max_calories": 600,
      "x": 14.882738894730835,
      "y": 41.085076888411685
    },
    {
      "max_calories": 450,
      "x": 42.600126094839815,
      "y": 34.363712648922764
    },
    {
      "max_calories": 750,
      "x": 38.25513548852995,
      "y": 33.95759454595855
    },
    {
      "max_calories": 750,
      "x": 1.7147480552220817,
      "y": 37.20317550238803
    },
    {
      "max_calories": 600,
      "x": 0.8168648480586738,
      "y": 3.148904214990178
    },
    {
      "max_calories": 450,
      "x": 12.14603765799877,
      "y": 35.76594675293123
    },
    {
      "max_calories": 650,
      "x": 46.4119669056035,
      "y": 18.601213717665427
    },
    {
      "max_calories": 600,
      "x": 35.011565160253106,
      "y": 18.646763137612727
    },
    {
      "max_calories": 500,
      "x": 39.11412241778971,
      "y": 9.052986748189873
    },
    {
      "max_calories": 550,
      "x": 3.6390844456565317,
      "y": 34.22363054617092
    },
    {
      "max_calories": 750,
      "x": 7.645274769445032,
      "y": 4.47747881773174
    },
    {
      "max_calories": 700,
      "x": 47.93143885262624,
      "y": 14.60212018396797
    },
    {
      "max_calories": 400,
      "x": 45.854666714764214,
      "y": 11.328267470065345
    },
    {
      "max_calories": 500,
      "x": 28.861315493480895,
      "y": 28.502579404110417
    },
    {
      "max_calories": 600,
      "x": 15.511557064728876,
      "y": 36.79232788555465
    },
    {
      "max_calories": 600,
      "x": 44.99584691612772,
      "y": 6.1761851987778895
    },
    {
      "max_calories": 750,
      "x": 42.90917601634221,
      "y": 8.563726595756533
    },
    {
      "max_calories": 650,
      "x": 9.985063245370467,
      "y": 5.250763827234289
    },
    {
      "max_calories": 700,
      "x": 24.813918210520875,
      "y": 26.47057035935476
    },
    {
      "max_calories": 450,
      "x": 10.00069524682109,
      "y": 37.02538289802481
    },
    {
      "max_calories": 450,
      "x": 29.196079968257276,
      "y": 31.059562430383693
    },
    {
      "max_calories": 600,
      "x": 39.20958171196716,
      "y": 17.740523514368334
    },
    {
      "max_calories": 600,
      "x": 22.874432867288846,
      "y": 31.864769017843898
    },
    {
      "max_calories": 650,
      "x": 24.953374195099276,
      "y": 2.175560842993274
    },
    {
      "max_calories": 700,
      "x": 45.44571882474911,
      "y": 21.539466066745728
    },
    {
      "max_calories": 650,
      "x": 32.39886533435411,
      "y": 13.21115340053064
    },
    {
      "max_calories": 500,
      "x": 18.421860493752817,
      "y": 41.615028168430506
    },
    {
      "max_calories": 500,
      "x": 30.528784716998235,
      "y": 0.49135368306757465
    },
    {
      "max_calories": 750,
      "x": 2.687991759388159,
      "y": 8.824828172051241
    },
    {
      "max_calories": 800,
      "x": 41.570944398742974,
      "y": 17.01841590462616
    },
    {
      "max_calories": 550,
      "x": 46.333708977699686,
      "y": 3.2012050293136642
    },
    {
      "max_calories": 750,
      "x": 15.814029408569846,
      "y": 46.832820733776934
    },
    {
      "max_calories": 750,
      "x": 7.923421953756243,
      "y": 16.231449501643976
    },
    {
      "max_calories": 600,
      "x": 23.78423170432894,
      "y": 13.875924692526992
    },
    {
      "max_calories": 750,
      "x": 23.77317206202592,
      "y": 36.43856603465066
    },
    {
      "max_calories": 750,
      "x": 32.22504291831794,
      "y": 38.573044740709946
    },
    {
      "max_calories": 550,
      "x": 43.48052626534773,
      "y": 1.4442356008822044
    },
    {
      "max_calories": 750,
      "x": 0.10408276458075405,
      "y": 31.756588643329003
    },
    {
      "max_calories": 750,
      "x": 16.383201115493133,
      "y": 16.9937915319507
    },
    {
      "max_calories": 450,
      "x": 19.245367210666537,
      "y": 7.320747001278599
    },
    {
      "max_calories": 550,
      "x": 13.861370958702047,
      "y": 13.66419275619749
    },
    {
      "max_calories": 650,
      "x": 4.820337649176149,
      "y": 7.3078383338742725
    },
    {
      "max_calories": 550,
      "x": 25.899584841097507,
      "y": 8.878087572842214
    },
    {
      "max_calories": 400,
      "x": 21.109220845049826,
      "y": 35.74296329480895
    },
    {
      "max_calories": 800,
      "x": 38.309995099872594,
      "y": 2.3770340582015272
    },
    {
      "max_calories": 450,
      "x": 33.40585079080349,
      "y": 5.7498548603603155
    },
    {
      "max_calories": 500,
      "x": 26.943446185539067,
      "y": 21.0143266669668
    },
    {
      "max_calories": 800,
      "x": 40.513107732633564,
      "y": 34.979469905930586
    },
    {
      "max_calories": 400,
      "x": 14.158854224695771,
      "y": 18.51568387794694
    },
    {
      "max_calories": 400,
      "x": 37.73502863265386,
      "y": 15.3561485969462
    },
    {
      "max_calories": 400,
      "x": 3.0138137704680656,
      "y": 31.404911725879437
    },
    {
      "max_calories": 750,
      "x": 4.1391021494225635,
      "y": 43.22299201717353
    },
    {
      "max_calories": 500,
      "x": 14.63960225291348,
      "y": 49.719569629178835
    },
    {
      "max_calories": 650,
      "x": 35.246153774960014,
      "y": 41.922058379764785
    },
    {
      "max_calories": 600,
      "x": 38.68184716985159,
      "y": 24.94411097967575
    },
    {
      "max_calories": 500,
      "x": 13.826807399307567,
      "y": 20.070437715295974
    },
    {
      "max_calories": 750,
      "x": 15.609102862206093,
      "y": 20.261078516696124
    },
    {
      "max_calories": 600,
      "x": 39.04479756914078,
      "y": 22.433492144613954
    },
    {
      "max_calories": 450,
      "x": 29.068266852091245,
      "y": 5.070418299318807
    },
    {
      "max_calories": 400,
      "x": 23.048526827240178,
      "y": 11.449653600411047
    },
    {
      "max_calories": 500,
      "x": 26.159256473658616,
      "y": 39.3686893741721
    },
    {
      "max_calories": 650,
      "x": 6.778509579576886,
      "y": 39.63385082613839
    },
    {
      "max_calories": 450,
      "x": 26.23657882029474,
      "y": 39.986041307606975
    },
    {
      "max_calories": 550,
      "x": 26.790125920862458,
      "y": 22.357546031453733
    },
    {
      "max_calories": 800,
      "x": 11.57702532195673,
      "y": 20.144893500284677
    },
    {
      "max_calories": 800,
      "x": 31.85004217392639,
      "y": 4.547132545987564
    },
    {
      "max_calories": 650,
      "x": 29.86180465167207,
      "y": 22.694526116616164
    },
    {
      "max_calories": 550,
      "x": 18.34552739094005,
      "y": 32.41245863628382
    },
    {
      "max_calories": 800,
      "x": 49.742271742532694,
      "y": 27.793742248789332
    },
    {
      "max_calories": 800,
      "x": 5.419584192778815,
      "y": 39.61320767312328
    },
    {
      "max_calories": 750,
      "x": 14.45838996452234,
      "y": 4.412466550495653
    },
    {
      "max_calories": 800,
      "x": 38.2009229961453,
      "y": 41.63416106942663
    },
    {
      "max_calories": 650,
      "x": 11.495029075937257,
      "y": 46.21802029912816
    },
    {
      "max_calories": 400,
      "x": 37.59476450493124,
      "y": 5.571587747311135
    },
    {
      "max_calories": 800,
      "x": 45.043997372538065,
      "y": 2.999141328393823
    },
    {
      "max_calories": 400,
      "x": 3.9634404316853997,
      "y": 6.401908639394999
    },
    {
      "max_calories": 500,
      "x": 10.58423949488021,
      "y": 6.822367287839054
    },
    {
      "max_calories": 450,
      "x": 8.821720807103173,
      "y": 40.868035707229616
    },
    {
      "max_calories": 500,
      "x": 10.885041766096387,
      "y": 9.75839022246246
    },
    {
      "max_calories": 500,
      "x": 18.9129746845208,
      "y": 32.955828412941464
    },
    {
      "max_calories": 400,
      "x": 23.086972580782778,
      "y": 23.31146440260457
    },
    {
      "max_calories": 600,
      "x": 28.282207278487252,
      "y": 28.97640039569973
    },
    {
      "max_calories": 650,
      "x": 2.5876984880029097,
      "y": 27.47014765232243
    },
    {
      "max_calories": 750,
      "x": 34.42763472842522,
      "y": 16.892348188721506
    },
    {
      "max_calories": 550,
      "x": 42.26289860243428,
      "y": 31.742692672988554
    },
    {
      "max_calories": 750,
      "x": 10.250560956211146,
      "y": 45.8293411634642
    },
    {
      "max_calories": 450,
      "x": 17.04244222384284,
      "y": 38.5780840180917
    }
  ],
  "agents": [
    {
      "max_memory": 0,
      "aggressiveness": 0,
      "harvest_percent": 0.43705979898241515,
      "x": 12.860900119219421,
      "y": 10.016124821329475
    },
    {
      "max_memory": 2,
      "aggressiveness": 0,
      "harvest_percent": 0.47476240607671993,
      "x": 22.333584394580175,
      "y": 3.2722989274073857
    },
    {
      "max_memory": 0,
      "aggressiveness": 0,
      "harvest_percent": 0.48003884932167734,
      "x": 10.942108846011262,
      "y": 42.4879396956918
    },
    {
      "max_memory": 0,
      "aggressiveness": 0.10719613888643384,
      "harvest_percent": 0.3131585303997489,
      "x": 15.950226796625094,
      "y": 39.308928389373634
    },
    {
      "max_memory": 0,
      "aggressiveness": 0,
      "harvest_percent": 0.4178039029264421,
      "x": 15.773269219016777,
      "y": 8.578429964214351
    },
    {
      "max_memory": 0,
      "aggressiveness": 0.026527812709406046,
      "harvest_percent": 0.5371079826487524,
      "x": 28.329900693984023,
      "y": 38.83864167552341
    },
    {
      "max_memory": 0,
      "aggressiveness": 0.04131595610756857,
      "harvest_percent": 0.3641399382042635,
      "x": 37.546390057309196,
      "y": 25.20854606586193
    },
    {
      "max_memory": 1,
      "aggressiveness": 0.08478593983814045,
      "harvest_percent": 0.31639288428378043,
      "x": 8.518408452193965,
      "y": 30.464312714179737
    },
    {
      "max_memory": 2,
      "aggressiveness": 0.009106857518047067,
      "harvest_percent": 0.5483627076724769,
      "x": 15.950226796625094,
      "y": 39.308928389373634
    },
    {
      "max_memory": 0,
      "aggressiveness": 0.022019663227014125,
      "harvest_percent": 0.4674715691901063,
      "x": 32.72003226298622,
      "y": 7.387771573958702
    },
    {
      "max_memory": 1,
      "aggressiveness": 0.08155259389495108,
      "harvest_percent": 0.4800097873018685,
      "x": 9.30640007952933,
      "y": 44.28451444478173
    },
    {
      "max_memory": 0,
      "aggressiveness": 0,
      "harvest_percent": 0.48322757675420935,
      "x": 3.4442625268090055,
      "y": 34.170448500517026
    },
    {
      "max_memory": 0,
      "aggressiveness": 0,
      "harvest_percent": 0.3784400717727228,
      "x": 33.61358852200279,
      "y": 35.76878244258877
    },
    {
      "max_memory": 0,
      "aggressiveness": 0,
      "harvest_percent": 0.5455593888834267,
      "x": 3.4442625268090055,
      "y": 34.170448500517026
    },
    {
      "max_memory": 1,
      "aggressiveness": 0,
      "harvest_percent": 0.4949124116223821,
      "x": 37.79008627321713,
      "y": 10.196191585811626
    },
    {
      "max_memory": 0,
      "aggressiveness": 0.0003862482105401188,
      "harvest_percent": 0.5793569842327178,
      "x": 24.95745353376821,
      "y": 33.14793810146956
    },
    {
      "max_memory": 0,
      "aggressiveness": 0.031128238602670243,
      "harvest_percent": 0.4502481043382645,
      "x": 23.937718940988923,
      "y": 27.98678456478687
    },
    {
      "max_memory": 3,
      "aggressiveness": 0,
      "harvest_percent": 0.45610856175181264,
      "x": 39.09082402460171,
      "y": 35.01809507918676
    },
    {
      "max_memory": 0,
      "aggressiveness": 0,
      "harvest_percent": 0.7018926344006359,
      "x": 15.950226796625094,
      "y": 39.308928389373634
    },
    {
      "max_memory": 1,
      "aggressiveness": 0.15509790429983888,
      "harvest_percent": 0.5949214658794897,
      "x": 32.72003226298622,
      "y": 7.387771573958702
    },
    {
      "max_memory": 0,
      "aggressiveness": 0.19431768428472856,
      "harvest_percent": 0.25796812664880153,
      "x": 48.67053878228935,
      "y": 36.16888251042341
    },
    {
      "max_memory": 0,
      "aggressiveness": 0.031802123809855726,
      "harvest_percent": 0.47773969890953555,
      "x": 22.712440096565,
      "y": 26.14506248715611
    },
    {
      "max_memory": 0,
      "aggressiveness": 0.10084924459184186,
      "harvest_percent": 0.5456023926857144,
      "x": 15.773269219016777,
      "y": 8.578429964214351
    },
    {
      "max_memory": 1,
      "aggressiveness": 0.11536859984739287,
      "harvest_percent": 0.4644651479875821,
      "x": 13.599425095278772,
      "y": 32.375982224743524
    },
    {
      "max_memory": 0,
      "aggressiveness": 0.0038477058797716374,
      "harvest_percent": 0.49994240903642834,
      "x": 38.15942886183754,
      "y": 10.132813390100704
    },
    {
      "max_memory": 0,
      "aggressiveness": 0.0646637408483781,
      "harvest_percent": 0.2936064483337061,
      "x": 24.95745353376821,
      "y": 33.14793810146956
    },
    {
      "max_memory": 2,
      "aggressiveness": 0,
      "harvest_percent": 0.33646904175545717,
      "x": 7.403017488290775,
      "y": 9.233144832370888
    },
    {
      "max_memory": 0,
      "aggressiveness": 0.049138808058142594,
      "harvest_percent": 0.36563643509929433,
      "x": 9.30640007952933,
      "y": 44.28451444478173
    },
    {
      "max_memory": 0,
      "aggressiveness": 0.13964733067846133,
      "harvest_percent": 0.382977072345755,
      "x": 21.896154748448925,
      "y": 3.771374048040582
    },
    {
      "max_memory": 0,
      "aggressiveness": 0,
      "harvest_percent": 0.43715907844486346,
      "x": 38.15942886183754,
      "y": 10.132813390100704
    },
    {
      "max_memory": 0,
      "aggressiveness": 0.06396265984467685,
      "harvest_percent": 0.3743809597704912,
      "x": 24.46579941232964,
      "y": 6.877769254462524
    },
    {
      "max_memory": 0,
      "aggressiveness": 0,
      "harvest_percent": 0.4518208890959854,
      "x": 22.333584394580175,
      "y": 3.2722989274073857
    },
    {
      "max_memory": 1,
      "aggressiveness": 0,
      "harvest_percent": 0.4446903633305958,
      "x": 6.831213358044525,
      "y": 27.780272938661476
    },
    {
      "max_memory": 0,
      "aggressiveness": 0.20796182443291472,
      "harvest_percent": 0.5121364239052614,
      "x": 13.599425095278772,
      "y": 32.375982224743524
    },
    {
      "max_memory": 0,
      "aggressiveness": 0,
      "harvest_percent": 0.5093586162068529,
      "x": 12.860900119219421,
      "y": 10.016124821329475
    },
    {
      "max_memory": 0,
      "aggressiveness": 0,
      "harvest_percent": 0.5870557309736897,
      "x": 12.860900119219421,
      "y": 10.016124821329475
    },
    {
      "max_memory": 0,
      "aggressiveness": 0,
      "harvest_percent": 0.323245292746501,
      "x": 21.62772502446752,
      "y": 8.066425974333463
    },
    {
      "max_memory": 0,
      "aggressiveness": 0,
      "harvest_percent": 0.6122196979126975,
      "x": 38.15942886183754,
      "y": 10.132813390100704
    },
    {
      "max_memory": 0,
      "aggressiveness": 0.03346130907527973,
      "harvest_percent": 0.4834451382282804,
      "x": 12.860900119219421,
      "y": 10.016124821329475
    },
    {
      "max_memory": 0,
      "aggressiveness": 0.21107987789133892,
      "harvest_percent": 0.4340821323520518,
      "x": 38.15942886183754,
      "y": 10.132813390100704
    },
    {
      "max_memory": 2,
      "aggressiveness": 0.06278632026268421,
      "harvest_percent": 0.3988408499008086,
      "x": 39.62392986896302,
      "y": 30.034085205618013
    },
    {
      "max_memory": 1,
      "aggressiveness": 0.14712906807766923,
      "harvest_percent": 0.5334528864640179,
      "x": 13.599425095278772,
      "y": 32.375982224743524
    },
    {
      "max_memory": 0,
      "aggressiveness": 0.030586109595569417,
      "harvest_percent": 0.5717236935326828,
      "x": 21.62772502446752,
      "y": 8.066425974333463
    },
    {
      "max_memory": 0,
      "aggressiveness": 0.03903967868476668,
      "harvest_percent": 0.4068335966540058,
      "x": 11.677284795115794,
      "y": 46.99348170134856
    },
    {
      "max_memory": 1,
      "aggressiveness": 0.0034786581334169953,
      "harvest_percent": 0.424193438786018,
      "x": 37.237538316018,
      "y": 11.330120403514254
    },
    {
      "max_memory": 1,
      "aggressiveness": 0,
      "harvest_percent": 0.4267147521715484,
      "x": 13.599425095278772,
      "y": 32.375982224743524
    },
    {
      "max_memory": 2,
      "aggressiveness": 0,
      "harvest_percent": 0.39077582741751,
      "x": 15.773269219016777,
      "y": 8.578429964214351
    },
    {
      "max_memory": 0,
      "aggressiveness": 0,
      "harvest_percent": 0.4201658412523057,
      "x": 7.403017488290775,
      "y": 9.233144832370888
    },
    {
      "max_memory": 0,
      "aggressiveness": 0.0738617280904132,
      "harvest_percent": 0.5184065094020273,
      "x": 47.38211060367122,
      "y": 0.14145000322353662
    },
    {
      "max_memory": 1,
      "aggressiveness": 0.1994373459902382,
      "harvest_percent": 0.49766095467265925,
      "x": 38.15942886183754,
      "y": 10.132813390100704
    },
    {
      "max_memory": 2,
      "aggressiveness": 0.02518974929732118,
      "harvest_percent": 0.345107264551675,
      "x": 46.50010742897414,
      "y": 2.9260499759116154
    },
    {
      "max_memory": 1,
      "aggressiveness": 0.04021490987256869,
      "harvest_percent": 0.6062528775492462,
      "x": 20.52640290826823,
      "y": 21.16699613764489
    },
    {
      "max_memory": 1,
      "aggressiveness": 0.1128512460304229,
      "harvest_percent": 0.42559677469062746,
      "x": 15.773269219016777,
      "y": 8.578429964214351
    },
    {
      "max_memory": 0,
      "aggressiveness": 0.01985563362939211,
      "harvest_percent": 0.5265557984504142,
      "x": 10.942108846011262,
      "y": 42.4879396956918
    },
    {
      "max_memory": 0,
      "aggressiveness": 0.08916945987881071,
      "harvest_percent": 0.34427102615300176,
      "x": 7.403017488290775,
      "y": 9.233144832370888
    },
    {
      "max_memory": 2,
      "aggressiveness": 0.057549020894727104,
      "harvest_percent": 0.44462279281236566,
      "x": 22.333584394580175,
      "y": 3.2722989274073857
    },
    {
      "max_memory": 1,
      "aggressiveness": 0.08862007814904709,
      "harvest_percent": 0.547271386323335,
      "x": 29.96170020807028,
      "y": 20.47709975343238
    },
    {
      "max_memory": 0,
      "aggressiveness": 0.1865371557449224,
      "harvest_percent": 0.44025460242004416,
      "x": 37.79008627321713,
      "y": 10.196191585811626
    },
    {
      "max_memory": 0,
      "aggressiveness": 0.04659392039738755,
      "harvest_percent": 0.6331348678400514,
      "x": 35.48071659805811,
      "y": 14.604281048469032
    },
    {
      "max_memory": 0,
      "aggressiveness": 0,
      "harvest_percent": 0.6212889544278294,
      "x": 38.15942886183754,
      "y": 10.132813390100704
    },
    {
      "max_memory": 0,
      "aggressiveness": 0,
      "harvest_percent": 0.4507474349430806,
      "x": 2.0653053392223395,
      "y": 7.607335119149106
    },
    {
      "max_memory": 2,
      "aggressiveness": 0.13439346111697859,
      "harvest_percent": 0.45478265382531574,
      "x": 15.950226796625094,
      "y": 39.308928389373634
    },
    {
      "max_memory": 3,
      "aggressiveness": 0,
      "harvest_percent": 0.4486782967364158,
      "x": 10.942108846011262,
      "y": 42.4879396956918
    },
    {
      "max_memory": 0,
      "aggressiveness": 0.11704435804182747,
      "harvest_percent": 0.5161685401217141,
      "x": 3.4442625268090055,
      "y": 34.170448500517026
    },
    {
      "max_memory": 0,
      "aggressiveness": 0.17312622195864363,
      "harvest_percent": 0.41077679305893267,
      "x": 8.061689062848748,
      "y": 30.970470256584083
    },
    {
      "max_memory": 1,
      "aggressiveness": 0.08752919827993125,
      "harvest_percent": 0.44386616397956347,
      "x": 48.67053878228935,
      "y": 36.16888251042341
    },
    {
      "max_memory": 0,
      "aggressiveness": 0.18612892570426784,
      "harvest_percent": 0.5623876018591878,
      "x": 8.518408452193965,
      "y": 30.464312714179737
    },
    {
      "max_memory": 0,
      "aggressiveness": 0.1097817150520281,
      "harvest_percent": 0.4981535070743192,
      "x": 35.48071659805811,
      "y": 14.604281048469032
    },
    {
      "max_memory": 0,
      "aggressiveness": 0,
      "harvest_percent": 0.3687783660342176,
      "x": 24.46579941232964,
      "y": 6.877769254462524
    },
    {
      "max_memory": 3,
      "aggressiveness": 0,
      "harvest_percent": 0.42907871587716245,
      "x": 23.937718940988923,
      "y": 27.98678456478687
    },
    {
      "max_memory": 1,
      "aggressiveness": 0.05528011458070751,
      "harvest_percent": 0.4595088827048596,
      "x": 22.19761071348902,
      "y": 36.6510024029399
    },
    {
      "max_memory": 0,
      "aggressiveness": 0.02770570805026524,
      "harvest_percent": 0.46595229321010967,
      "x": 9.30640007952933,
      "y": 44.28451444478173
    },
    {
      "max_memory": 0,
      "aggressiveness": 0,
      "harvest_percent": 0.482302380896432,
      "x": 39.62392986896302,
      "y": 30.034085205618013
    },
    {
      "max_memory": 3,
      "aggressiveness": 0.06231519840089867,
      "harvest_percent": 0.539237987577559,
      "x": 28.329900693984023,
      "y": 38.83864167552341
    },
    {
      "max_memory": 0,
      "aggressiveness": 0,
      "harvest_percent": 0.5348311474028077,
      "x": 37.237538316018,
      "y": 11.330120403514254
    },
    {
      "max_memory": 0,
      "aggressiveness": 0.08089379778360418,
      "harvest_percent": 0.49985389138490144,
      "x": 15.773269219016777,
      "y": 8.578429964214351
    },
    {
      "max_memory": 0,
      "aggressiveness": 0.13142241242653793,
      "harvest_percent": 0.4767249079630816,
      "x": 12.860900119219421,
      "y": 10.016124821329475
    },
    {
      "max_memory": 0,
      "aggressiveness": 0.15053196473889469,
      "harvest_percent": 0.36728879110931395,
      "x": 46.50010742897414,
      "y": 2.9260499759116154
    },
    {
      "max_memory": 1,
      "aggressiveness": 0.020156743575958445,
      "harvest_percent": 0.24621940226813926,
      "x": 19.620619109759012,
      "y": 38.73105759057739
    },
    {
      "max_memory": 2,
      "aggressiveness": 0.017065968591495673,
      "harvest_percent": 0.24034258492649652,
      "x": 5.2966242178564995,
      "y": 12.605520141362419
    },
    {
      "max_memory": 2,
      "aggressiveness": 0.03143604651472076,
      "harvest_percent": 0.6421701968878272,
      "x": 20.47435766053431,
      "y": 38.095985781171684
    },
    {
      "max_memory": 0,
      "aggressiveness": 0.06223518634443553,
      "harvest_percent": 0.4359072492179969,
      "x": 19.935931174199872,
      "y": 25.85059696265238
    },
    {
      "max_memory": 0,
      "aggressiveness": 0.0335840196874799,
      "harvest_percent": 0.33808727743935335,
      "x": 6.719618095455459,
      "y": 1.486079709229593
    },
    {
      "max_memory": 1,
      "aggressiveness": 0,
      "harvest_percent": 0.45408128000578185,
      "x": 46.503499655435945,
      "y": 23.412658031046995
    },
    {
      "max_memory": 2,
      "aggressiveness": 0.004703046093097102,
      "harvest_percent": 0.47152689608080717,
      "x": 39.62392986896302,
      "y": 30.034085205618013
    },
    {
      "max_memory": 0,
      "aggressiveness": 0.03648244257601976,
      "harvest_percent": 0.38734444664674694,
      "x": 19.620619109759012,
      "y": 38.73105759057739
    },
    {
      "max_memory": 0,
      "aggressiveness": 0.15496706556372117,
      "harvest_percent": 0.5893825728553631,
      "x": 33.61358852200279,
      "y": 35.76878244258877
    },
    {
      "max_memory": 2,
      "aggressiveness": 0.13286392105773628,
      "harvest_percent": 0.4148960191927752,
      "x": 7.403017488290775,
      "y": 9.233144832370888
    },
    {
      "max_memory": 0,
      "aggressiveness": 0.08384112610090089,
      "harvest_percent": 0.4055445793120225,
      "x": 44.38722029481967,
      "y": 3.6592677125430075
    },
    {
      "max_memory": 1,
      "aggressiveness": 0.08585778572085057,
      "harvest_percent": 0.5711942632299986,
      "x": 17.783935869628408,
      "y": 19.075512290327403
    },
    {
      "max_memory": 2,
      "aggressiveness": 0.15159757320404943,
      "harvest_percent": 0.3982338592195658,
      "x": 8.518408452193965,
      "y": 30.464312714179737
    },
    {
      "max_memory": 2,
      "aggressiveness": 0.16823783681141624,
      "harvest_percent": 0.4191585803421198,
      "x": 9.30640007952933,
      "y": 44.28451444478173
    },
    {
      "max_memory": 0,
      "aggressiveness": 0,
      "harvest_percent": 0.3351770149571356,
      "x": 25.414680222313972,
      "y": 41.10851723785762
    },
    {
      "max_memory": 0,
      "aggressiveness": 0.0624147021835506,
      "harvest_percent": 0.36233933355581494,
      "x": 17.999840858514414,
      "y": 23.989015523426293
    },
    {
      "max_memory": 0,
      "aggressiveness": 0,
      "harvest_percent": 0.33437811995383954,
      "x": 22.333584394580175,
      "y": 3.2722989274073857
    },
    {
      "max_memory": 0,
      "aggressiveness": 0.12732879161809424,
      "harvest_percent": 0.3850381555888842,
      "x": 37.237538316018,
      "y": 11.330120403514254
    },
    {
      "max_memory": 0,
      "aggressiveness": 0.06001296582656033,
      "harvest_percent": 0.47662678170668255,
      "x": 35.48071659805811,
      "y": 14.604281048469032
    },
    {
      "max_memory": 2,
      "aggressiveness": 0.09363181152694625,
      "harvest_percent": 0.36650011256051873,
      "x": 15.773269219016777,
      "y": 8.578429964214351
    },
    {
      "max_memory": 1,
      "aggressiveness": 0.13628541055953672,
      "harvest_percent": 0.43945104062441664,
      "x": 12.860900119219421,
      "y": 10.016124821329475
    },
    {
      "max_memory": 0,
      "aggressiveness": 0,
      "harvest_percent": 0.43903535507942815,
      "x": 14.789947384290103,
      "y": 24.68938159819788
    },
    {
      "max_memory": 0,
      "aggressiveness": 0.009984614872224682,
      "harvest_percent": 0.5200214721869658,
      "x": 21.896154748448925,
      "y": 3.771374048040582
    },
    {
      "max_memory": 0,
      "aggressiveness": 0.07711338183796516,
      "harvest_percent": 0.5546366577853613,
      "x": 24.46579941232964,
      "y": 6.877769254462524
    },
    {
      "max_memory": 0,
      "aggressiveness": 0.14342209813973375,
      "harvest_percent": 0.5560422485970631,
      "x": 21.896154748448925,
      "y": 3.771374048040582
    },
    {
      "max_memory": 0,
      "aggressiveness": 0.11625191316977568,
      "harvest_percent": 0.4561254459264661,
      "x": 22.037605399258787,
      "y": 6.65868295476097
    },
    {
      "max_memory": 0,
      "aggressiveness": 0.09465795937521758,
      "harvest_percent": 0.34591030012578217,
      "x": 13.599425095278772,
      "y": 32.375982224743524
    },
    {
      "max_memory": 2,
      "aggressiveness": 0,
      "harvest_percent": 0.3466417918060278,
      "x": 21.62772502446752,
      "y": 8.066425974333463
    },
    {
      "max_memory": 0,
      "aggressiveness": 0.18037816181116412,
      "harvest_percent": 0.3939541489581927,
      "x": 17.783935869628408,
      "y": 19.075512290327403
    },
    {
      "max_memory": 2,
      "aggressiveness": 0.06492842953610899,
      "harvest_percent": 0.5339166702541487,
      "x": 39.62392986896302,
      "y": 30.034085205618013
    },
    {
      "max_memory": 0,
      "aggressiveness": 0.016061058547399018,
      "harvest_percent": 0.4737757264014006,
      "x": 3.070285052901939,
      "y": 0.5626608050325776
    },
    {
      "max_memory": 1,
      "aggressiveness": 0.0653889051873962,
      "harvest_percent": 0.3372672381594272,
      "x": 17.783935869628408,
      "y": 19.075512290327403
    },
    {
      "max_memory": 0,
      "aggressiveness": 0.08135168867563193,
      "harvest_percent": 0.4846779392699746,
      "x": 38.30100530709079,
      "y": 26.857932314991473
    },
    {
      "max_memory": 2,
      "aggressiveness": 0.006573682706653969,
      "harvest_percent": 0.33307923818707436,
      "x": 33.766630660222674,
      "y": 33.90118389171753
    },
    {
      "max_memory": 0,
      "aggressiveness": 0.05445380102287189,
      "harvest_percent": 0.581351881831685,
      "x": 11.677284795115794,
      "y": 46.99348170134856
    },
    {
      "max_memory": 0,
      "aggressiveness": 0.013031058112926895,
      "harvest_percent": 0.4505589028997008,
      "x": 3.4442625268090055,
      "y": 34.170448500517026
    },
    {
      "max_memory": 1,
      "aggressiveness": 0.100594975417837,
      "harvest_percent": 0.47037732316738035,
      "x": 19.935931174199872,
      "y": 25.85059696265238
    },
    {
      "max_memory": 0,
      "aggressiveness": 0.10519635802421302,
      "harvest_percent": 0.40888807686021084,
      "x": 7.403017488290775,
      "y": 9.233144832370888
    },
    {
      "max_memory": 2,
      "aggressiveness": 0.05157057359148688,
      "harvest_percent": 0.4527787436782913,
      "x": 37.546390057309196,
      "y": 25.20854606586193
    },
    {
      "max_memory": 1,
      "aggressiveness": 0.14721104640748817,
      "harvest_percent": 0.2827017072514515,
      "x": 29.96170020807028,
      "y": 20.47709975343238
    },
    {
      "max_memory": 0,
      "aggressiveness": 0.13777544513752674,
      "harvest_percent": 0.4443427575224745,
      "x": 20.52640290826823,
      "y": 21.16699613764489
    },
    {
      "max_memory": 0,
      "aggressiveness": 0.06855007585281665,
      "harvest_percent": 0.5030952956773558,
      "x": 44.38722029481967,
      "y": 3.6592677125430075
    },
    {
      "max_memory": 1,
      "aggressiveness": 0.12826759816423872,
      "harvest_percent": 0.4736790494507203,
      "x": 33.766630660222674,
      "y": 33.90118389171753
    },
    {
      "max_memory": 2,
      "aggressiveness": 0.12313481388689407,
      "harvest_percent": 0.5523676865199365,
      "x": 10.942108846011262,
      "y": 42.4879396956918
    },
    {
      "max_memory": 4,
      "aggressiveness": 0,
      "harvest_percent": 0.48549405945004,
      "x": 17.783935869628408,
      "y": 19.075512290327403
    },
    {
      "max_memory": 2,
      "aggressiveness": 0.06545497044202728,
      "harvest_percent": 0.24683383668506886,
      "x": 9.30640007952933,
      "y": 44.28451444478173
    },
    {
      "max_memory": 0,
      "aggressiveness": 0,
      "harvest_percent": 0.517749167493439,
      "x": 22.333584394580175,
      "y": 3.2722989274073857
    },
    {
      "max_memory": 1,
      "aggressiveness": 0.057389347946712174,
      "harvest_percent": 0.5866526666900772,
      "x": 39.09082402460171,
      "y": 35.01809507918676
    },
    {
      "max_memory": 0,
      "aggressiveness": 0.12833834721499146,
      "harvest_percent": 0.5270044424160835,
      "x": 46.503499655435945,
      "y": 23.412658031046995
    },
    {
      "max_memory": 3,
      "aggressiveness": 0.014322679603028174,
      "harvest_percent": 0.4967295544715,
      "x": 38.15942886183754,
      "y": 10.132813390100704
    },
    {
      "max_memory": 2,
      "aggressiveness": 0.07917098284660724,
      "harvest_percent": 0.49794794717110324,
      "x": 43.33137024061182,
      "y": 5.59439380549348
    },
    {
      "max_memory": 0,
      "aggressiveness": 0.03209815469253063,
      "harvest_percent": 0.5084207908339,
      "x": 19.935931174199872,
      "y": 25.85059696265238
    },
    {
      "max_memory": 0,
      "aggressiveness": 0,
      "harvest_percent": 0.3828679775388809,
      "x": 10.942108846011262,
      "y": 42.4879396956918
    },
    {
      "max_memory": 0,
      "aggressiveness": 0.10840982429659968,
      "harvest_percent": 0.4466284472348656,
      "x": 3.4442625268090055,
      "y": 34.170448500517026
    },
    {
      "max_memory": 0,
      "aggressiveness": 0.20901110261767764,
      "harvest_percent": 0.4788798437350951,
      "x": 43.33137024061182,
      "y": 5.59439380549348
    },
    {
      "max_memory": 0,
      "aggressiveness": 0.11316615819456946,
      "harvest_percent": 0.6610269563695925,
      "x": 32.72003226298622,
      "y": 7.387771573958702
    },
    {
      "max_memory": 1,
      "aggressiveness": 0.03394903021787836,
      "harvest_percent": 0.44692168573350277,
      "x": 2.0653053392223395,
      "y": 7.607335119149106
    },
    {
      "max_memory": 0,
      "aggressiveness": 0,
      "harvest_percent": 0.45647185039792293,
      "x": 6.454200461978498,
      "y": 14.398358187651123
    },
    {
      "max_memory": 0,
      "aggressiveness": 0.17320590473282904,
      "harvest_percent": 0.37845883589383633,
      "x": 37.237538316018,
      "y": 11.330120403514254
    },
    {
      "max_memory": 1,
      "aggressiveness": 0.08300254176924708,
      "harvest_percent": 0.4054106476281595,
      "x": 21.62772502446752,
      "y": 8.066425974333463
    },
    {
      "max_memory": 0,
      "aggressiveness": 0.052137578784866606,
      "harvest_percent": 0.3571434721336884,
      "x": 21.62772502446752,
      "y": 8.066425974333463
    },
    {
      "max_memory": 0,
      "aggressiveness": 0.24149156095299867,
      "harvest_percent": 0.3569377831845286,
      "x": 46.503499655435945,
      "y": 23.412658031046995
    },
    {
      "max_memory": 0,
      "aggressiveness": 0.20670691307961764,
      "harvest_percent": 0.45627968948807435,
      "x": 37.237538316018,
      "y": 11.330120403514254
    },
    {
      "max_memory": 0,
      "aggressiveness": 0.06228020136706692,
      "harvest_percent": 0.48022627138133067,
      "x": 38.30100530709079,
      "y": 26.857932314991473
    },
    {
      "max_memory": 0,
      "aggressiveness": 0.07931854648684636,
      "harvest_percent": 0.4415778618880965,
      "x": 35.48071659805811,
      "y": 14.604281048469032
    },
    {
      "max_memory": 2,
      "aggressiveness": 0.005055281397885523,
      "harvest_percent": 0.3355975232554813,
      "x": 24.95745353376821,
      "y": 33.14793810146956
    },
    {
      "max_memory": 1,
      "aggressiveness": 0,
      "harvest_percent": 0.46949563564227714,
      "x": 48.67053878228935,
      "y": 36.16888251042341
    },
    {
      "max_memory": 2,
      "aggressiveness": 0.0402667727896067,
      "harvest_percent": 0.44978197562961325,
      "x": 48.67053878228935,
      "y": 36.16888251042341
    },
    {
      "max_memory": 2,
      "aggressiveness": 0.10355363410415107,
      "harvest_percent": 0.3849910490103674,
      "x": 12.860900119219421,
      "y": 10.016124821329475
    },
    {
      "max_memory": 0,
      "aggressiveness": 0.21808193428775685,
      "harvest_percent": 0.38137987330668743,
      "x": 20.47435766053431,
      "y": 38.095985781171684
    },
    {
      "max_memory": 0,
      "aggressiveness": 0.22478816856146158,
      "harvest_percent": 0.41294825894427994,
      "x": 39.09082402460171,
      "y": 35.01809507918676
    },
    {
      "max_memory": 0,
      "aggressiveness": 0,
      "harvest_percent": 0.4547410472996118,
      "x": 22.19761071348902,
      "y": 36.6510024029399
    },
    {
      "max_memory": 0,
      "aggressiveness": 0.1542884707727656,
      "harvest_percent": 0.3665578159217758,
      "x": 10.942108846011262,
      "y": 42.4879396956918
    },
    {
      "max_memory": 1,
      "aggressiveness": 0.06015438802472787,
      "harvest_percent": 0.4694852237934025,
      "x": 35.48071659805811,
      "y": 14.604281048469032
    },
    {
      "max_memory": 1,
      "aggressiveness": 0,
      "harvest_percent": 0.3620720179377677,
      "x": 3.4442625268090055,
      "y": 34.170448500517026
    },
    {
      "max_memory": 2,
      "aggressiveness": 0,
      "harvest_percent": 0.42162345621143094,
      "x": 19.620619109759012,
      "y": 38.73105759057739
    },
    {
      "max_memory": 0,
      "aggressiveness": 0.05618799271671655,
      "harvest_percent": 0.2917254333842884,
      "x": 9.208621382913373,
      "y": 1.6040155327261219
    },
    {
      "max_memory": 0,
      "aggressiveness": 0.1760055398646882,
      "harvest_percent": 0.32909451688987135,
      "x": 23.937718940988923,
      "y": 27.98678456478687
    },
    {
      "max_memory": 0,
      "aggressiveness": 0,
      "harvest_percent": 0.4750902755058709,
      "x": 44.38722029481967,
      "y": 3.6592677125430075
    },
    {
      "max_memory": 0,
      "aggressiveness": 0,
      "harvest_percent": 0.43047031226163457,
      "x": 22.333584394580175,
      "y": 3.2722989274073857
    },
    {
      "max_memory": 1,
      "aggressiveness": 0.14708195390907416,
      "harvest_percent": 0.47786385082050475,
      "x": 37.79008627321713,
      "y": 10.196191585811626
    },
    {
      "max_memory": 2,
      "aggressiveness": 0.11909893425445313,
      "harvest_percent": 0.3164651119972246,
      "x": 37.79008627321713,
      "y": 10.196191585811626
    },
    {
      "max_memory": 0,
      "aggressiveness": 0.1240789721145615,
      "harvest_percent": 0.417057310851039,
      "x": 43.33137024061182,
      "y": 5.59439380549348
    },
    {
      "max_memory": 2,
      "aggressiveness": 0.17331610114770402,
      "harvest_percent": 0.3206098503633642,
      "x": 32.72003226298622,
      "y": 7.387771573958702
    },
    {
      "max_memory": 1,
      "aggressiveness": 0.0744324778035376,
      "harvest_percent": 0.37098798210855954,
      "x": 48.67053878228935,
      "y": 36.16888251042341
    },
    {
      "max_memory": 0,
      "aggressiveness": 0.11904250944731104,
      "harvest_percent": 0.5315001065377837,
      "x": 37.237538316018,
      "y": 11.330120403514254
    },
    {
      "max_memory": 0,
      "aggressiveness": 0.056256555985391664,
      "harvest_percent": 0.5287673457864728,
      "x": 22.333584394580175,
      "y": 3.2722989274073857
    },
    {
      "max_memory": 1,
      "aggressiveness": 0,
      "harvest_percent": 0.4347992188177789,
      "x": 43.33137024061182,
      "y": 5.59439380549348
    },
    {
      "max_memory": 2,
      "aggressiveness": 0.03694311344750003,
      "harvest_percent": 0.5517117047408311,
      "x": 38.30100530709079,
      "y": 26.857932314991473
    },
    {
      "max_memory": 0,
      "aggressiveness": 0,
      "harvest_percent": 0.4625041306876094,
      "x": 32.72003226298622,
      "y": 7.387771573958702
    },
    {
      "max_memory": 0,
      "aggressiveness": 0,
      "harvest_percent": 0.5230080162282124,
      "x": 39.62392986896302,
      "y": 30.034085205618013
    },
    {
      "max_memory": 0,
      "aggressiveness": 0.022283066996537922,
      "harvest_percent": 0.44755423209227246,
      "x": 37.79008627321713,
      "y": 10.196191585811626
    },
    {
      "max_memory": 0,
      "aggressiveness": 0.12479723608396787,
      "harvest_percent": 0.5168053148702937,
      "x": 2.0653053392223395,
      "y": 7.607335119149106
    },
    {
      "max_memory": 2,
      "aggressiveness": 0,
      "harvest_percent": 0.4884989629209565,
      "x": 7.403017488290775,
      "y": 9.233144832370888
    },
    {
      "max_memory": 1,
      "aggressiveness": 0.03340930751200064,
      "harvest_percent": 0.5435423285345699,
      "x": 20.52640290826823,
      "y": 21.16699613764489
    },
    {
      "max_memory": 3,
      "aggressiveness": 0.12999244082782646,
      "harvest_percent": 0.31265150867691616,
      "x": 33.766630660222674,
      "y": 33.90118389171753
    },
    {
      "max_memory": 1,
      "aggressiveness": 0.14160286666354938,
      "harvest_percent": 0.401199597063964,
      "x": 33.766630660222674,
      "y": 33.90118389171753
    },
    {
      "max_memory": 2,
      "aggressiveness": 0.08948865447176202,
      "harvest_percent": 0.36891809743684456,
      "x": 33.766630660222674,
      "y": 33.90118389171753
    },
    {
      "max_memory": 0,
      "aggressiveness": 0.15219594860377822,
      "harvest_percent": 0.4672832933884531,
      "x": 33.766630660222674,
      "y": 33.90118389171753
    },
    {
      "max_memory": 2,
      "aggressiveness": 0.028131342355897954,
      "harvest_percent": 0.4199771334715849,
      "x": 33.766630660222674,
      "y": 33.90118389171753
    },
    {
      "max_memory": 2,
      "aggressiveness": 0.02277246608167007,
      "harvest_percent": 0.5043978620806682,
      "x": 10.942108846011262,
      "y": 42.4879396956918
    },
    {
      "max_memory": 0,
      "aggressiveness": 0.0939614224577831,
      "harvest_percent": 0.5245308611081018,
      "x": 11.677284795115794,
      "y": 46.99348170134856
    },
    {
      "max_memory": 2,
      "aggressiveness": 0.07709516093178737,
      "harvest_percent": 0.44723634015658137,
      "x": 11.677284795115794,
      "y": 46.99348170134856
    },
    {
      "max_memory": 0,
      "aggressiveness": 0.055779646923224985,
      "harvest_percent": 0.5606699692144508,
      "x": 11.677284795115794,
      "y": 46.99348170134856
    },
    {
      "max_memory": 0,
      "aggressiveness": 0.05553286708977413,
      "harvest_percent": 0.43246808353660704,
      "x": 11.677284795115794,
      "y": 46.99348170134856
    },
    {
      "max_memory": 1,
      "aggressiveness": 0.04722595038317012,
      "harvest_percent": 0.395900620894942,
      "x": 46.503499655435945,
      "y": 23.412658031046995
    },
    {
      "max_memory": 1,
      "aggressiveness": 0.1775347212214045,
      "harvest_percent": 0.4832430935576309,
      "x": 46.503499655435945,
      "y": 23.412658031046995
    },
    {
      "max_memory": 1,
      "aggressiveness": 0.16651996656657145,
      "harvest_percent": 0.4567544367682672,
      "x": 46.503499655435945,
      "y": 23.412658031046995
    },
    {
      "max_memory": 0,
      "aggressiveness": 0,
      "harvest_percent": 0.46402942592130686,
      "x": 46.503499655435945,
      "y": 23.412658031046995
    },
    {
      "max_memory": 3,
      "aggressiveness": 0,
      "harvest_percent": 0.3655097319874415,
      "x": 23.937718940988923,
      "y": 27.98678456478687
    },
    {
      "max_memory": 0,
      "aggressiveness": 0.03296235308709039,
      "harvest_percent": 0.45281076786293006,
      "x": 23.937718940988923,
      "y": 27.98678456478687
    },
    {
      "max_memory": 0,
      "aggressiveness": 0.047371887584914105,
      "harvest_percent": 0.5166335626576453,
      "x": 23.937718940988923,
      "y": 27.98678456478687
    },
    {
      "max_memory": 3,
      "aggressiveness": 0.11311275775677293,
      "harvest_percent": 0.3645057484787848,
      "x": 23.937718940988923,
      "y": 27.98678456478687
    },
    {
      "max_memory": 0,
      "aggressiveness": 0.038673516947752264,
      "harvest_percent": 0.40402239085778924,
      "x": 19.935931174199872,
      "y": 25.85059696265238
    },
    {
      "max_memory": 1,
      "aggressiveness": 0.09669911937171355,
      "harvest_percent": 0.5011802476230205,
      "x": 19.935931174199872,
      "y": 25.85059696265238
    },
    {
      "max_memory": 0,
      "aggressiveness": 0.08547050788640945,
      "harvest_percent": 0.45657938789678437,
      "x": 19.935931174199872,
      "y": 25.85059696265238
    },
    {
      "max_memory": 0,
      "aggressiveness": 0.011629236665192513,
      "harvest_percent": 0.3873680736037819,
      "x": 2.0653053392223395,
      "y": 7.607335119149106
    },
    {
      "max_memory": 2,
      "aggressiveness": 0.0693801870784006,
      "harvest_percent": 0.4741232349490454,
      "x": 2.0653053392223395,
      "y": 7.607335119149106
    },
    {
      "max_memory": 1,
      "aggressiveness": 0.13419740875794264,
      "harvest_percent": 0.5137322430365043,
      "x": 2.0653053392223395,
      "y": 7.607335119149106
    },
    {
      "max_memory": 1,
      "aggressiveness": 0,
      "harvest_percent": 0.4893347332651494,
      "x": 2.0653053392223395,
      "y": 7.607335119149106
    },
    {
      "max_memory": 0,
      "aggressiveness": 0.1660229536510223,
      "harvest_percent": 0.5644659441256258,
      "x": 33.61358852200279,
      "y": 35.76878244258877
    },
    {
      "max_memory": 0,
      "aggressiveness": 0.008600434340498828,
      "harvest_percent": 0.5133072920029581,
      "x": 33.61358852200279,
      "y": 35.76878244258877
    },
    {
      "max_memory": 2,
      "aggressiveness": 0.06544594192476368,
      "harvest_percent": 0.41720648977956076,
      "x": 33.61358852200279,
      "y": 35.76878244258877
    },
    {
      "max_memory": 1,
      "aggressiveness": 0.1097844904983891,
      "harvest_percent": 0.531471954132471,
      "x": 33.61358852200279,
      "y": 35.76878244258877
    },
    {
      "max_memory": 0,
      "aggressiveness": 0.04512074082184799,
      "harvest_percent": 0.5655989803758673,
      "x": 33.61358852200279,
      "y": 35.76878244258877
    },
    {
      "max_memory": 3,
      "aggressiveness": 0.03675873024469463,
      "harvest_percent": 0.44255603745550526,
      "x": 29.96170020807028,
      "y": 20.47709975343238
    },
    {
      "max_memory": 0,
      "aggressiveness": 0.19098012552181304,
      "harvest_percent": 0.46901995597161933,
      "x": 29.96170020807028,
      "y": 20.47709975343238
    },
    {
      "max_memory": 1,
      "aggressiveness": 0.06476381845259913,
      "harvest_percent": 0.6323061966459605,
      "x": 28.329900693984023,
      "y": 38.83864167552341
    },
    {
      "max_memory": 3,
      "aggressiveness": 0.008742129853657576,
      "harvest_percent": 0.5832966282793255,
      "x": 28.329900693984023,
      "y": 38.83864167552341
    },
    {
      "max_memory": 1,
      "aggressiveness": 0.005300851135133136,
      "harvest_percent": 0.6268394705568842,
      "x": 28.329900693984023,
      "y": 38.83864167552341
    },
    {
      "max_memory": 1,
      "aggressiveness": 0.10372373093226417,
      "harvest_percent": 0.5179534489516787,
      "x": 28.329900693984023,
      "y": 38.83864167552341
    },
    {
      "max_memory": 0,
      "aggressiveness": 0.01619772795410323,
      "harvest_percent": 0.5477801286698977,
      "x": 28.329900693984023,
      "y": 38.83864167552341
    },
    {
      "max_memory": 1,
      "aggressiveness": 0.010525614369666453,
      "harvest_percent": 0.46208350156261324,
      "x": 9.30640007952933,
      "y": 44.28451444478173
    },
    {
      "max_memory": 0,
      "aggressiveness": 0.05564876738515226,
      "harvest_percent": 0.5497012627509709,
      "x": 22.19761071348902,
      "y": 36.6510024029399
    },
    {
      "max_memory": 2,
      "aggressiveness": 0.011215725297352638,
      "harvest_percent": 0.3189426233428348,
      "x": 46.50010742897414,
      "y": 2.9260499759116154
    },
    {
      "max_memory": 1,
      "aggressiveness": 0.17761306771107002,
      "harvest_percent": 0.365843979332906,
      "x": 46.50010742897414,
      "y": 2.9260499759116154
    },
    {
      "max_memory": 0,
      "aggressiveness": 0.10091058361759178,
      "harvest_percent": 0.287882293122397,
      "x": 46.50010742897414,
      "y": 2.9260499759116154
    },
    {
      "max_memory": 0,
      "aggressiveness": 0.06362045810671131,
      "harvest_percent": 0.3712020299902082,
      "x": 24.95745353376821,
      "y": 33.14793810146956
    },
    {
      "max_memory": 0,
      "aggressiveness": 0.1306393762877084,
      "harvest_percent": 0.5145081660312057,
      "x": 32.72003226298622,
      "y": 7.387771573958702
    },
    {
      "max_memory": 0,
      "aggressiveness": 0,
      "harvest_percent": 0.5412092729432992,
      "x": 44.38722029481967,
      "y": 3.6592677125430075
    },
    {
      "max_memory": 2,
      "aggressiveness": 0.036872945788621034,
      "harvest_percent": 0.43668230983689743,
      "x": 20.47435766053431,
      "y": 38.095985781171684
    },
    {
      "max_memory": 1,
      "aggressiveness": 0.03510325180627588,
      "harvest_percent": 0.5866486142341326,
      "x": 20.47435766053431,
      "y": 38.095985781171684
    },
    {
      "max_memory": 3,
      "aggressiveness": 0.03819396731552136,
      "harvest_percent": 0.4120097672779888,
      "x": 37.546390057309196,
      "y": 25.20854606586193
    },
    {
      "max_memory": 0,
      "aggressiveness": 0.13018249079313338,
      "harvest_percent": 0.47598970609392277,
      "x": 37.546390057309196,
      "y": 25.20854606586193
    },
    {
      "max_memory": 3,
      "aggressiveness": 0.10350938984847977,
      "harvest_percent": 0.5076851507418536,
      "x": 37.546390057309196,
      "y": 25.20854606586193
    },
    {
      "max_memory": 0,
      "aggressiveness": 0.09180172452261462,
      "harvest_percent": 0.49508039287976635,
      "x": 17.783935869628408,
      "y": 19.075512290327403
    },
    {
      "max_memory": 2,
      "aggressiveness": 0.24538717644900881,
      "harvest_percent": 0.49927267729173713,
      "x": 37.237538316018,
      "y": 11.330120403514254
    },
    {
      "max_memory": 2,
      "aggressiveness": 0.042065545088728444,
      "harvest_percent": 0.2914448343136038,
      "x": 24.46579941232964,
      "y": 6.877769254462524
    },
    {
      "max_memory": 1,
      "aggressiveness": 0.01694254944839141,
      "harvest_percent": 0.38421092365681375,
      "x": 24.46579941232964,
      "y": 6.877769254462524
    },
    {
      "max_memory": 1,
      "aggressiveness": 0.07681982424927897,
      "harvest_percent": 0.5571383430488532,
      "x": 24.46579941232964,
      "y": 6.877769254462524
    },
    {
      "max_memory": 1,
      "aggressiveness": 0.149341303082774,
      "harvest_percent": 0.42407803558817997,
      "x": 48.67053878228935,
      "y": 36.16888251042341
    },
    {
      "max_memory": 0,
      "aggressiveness": 0.0895915146495026,
      "harvest_percent": 0.48405798603075,
      "x": 48.67053878228935,
      "y": 36.16888251042341
    },
    {
      "max_memory": 0,
      "aggressiveness": 0.11576595050577987,
      "harvest_percent": 0.4486000177375145,
      "x": 35.48071659805811,
      "y": 14.604281048469032
    }
  ]
}