{
    "caves": [
        {
            "x": 2.242251418672503,
            "y": 38.08967163607256,
            "max_capacity": 5
        },
        {
            "x": 32.25653600601761,
            "y": 36.384066399933644,
            "max_capacity": 7
        },
        {
            "x": 32.7416532773555,
            "y": 13.348522536089991,
            "max_capacity": 3
        },
        {
            "x": 35.61855605123129,
            "y": 16.94495409230228,
            "max_capacity": 4
        },
        {
            "x": 13.110411762892493,
            "y": 45.37018110659511,
            "max_capacity": 3
        },
        {
            "x": 9.66736948011005,
            "y": 49.887435688456826,
            "max_capacity": 7
        },
        {
            "x": 17.319673178177307,
            "y": 16.42836748914604,
            "max_capacity": 5
        },
        {
            "x": 9.292097693379569,
            "y": 39.74399629292607,
            "max_capacity": 3
        },
        {
            "x": 4.781133337721688,
            "y": 43.94900141105123,
            "max_capacity": 7
        },
        {
            "x": 8.23599922358037,
            "y": 6.0752586424899055,
            "max_capacity": 5
        },
        {
            "x": 4.40437529422843,
            "y": 22.80861531253232,
            "max_capacity": 5
        },
        {
            "x": 36.43084592776107,
            "y": 19.736814364911627,
            "max_capacity": 4
        },
        {
            "x": 23.595720233935992,
            "y": 11.438332591576527,
            "max_capacity": 5
        },
        {
            "x": 11.936626168169234,
            "y": 32.27656424383623,
            "max_capacity": 4
        },
        {
            "x": 21.98314145239927,
            "y": 5.737719306780681,
            "max_capacity": 3
        },
        {
            "x": 36.913164115468476,
            "y": 15.106417043466285,
            "max_capacity": 4
        },
        {
            "x": 30.052598649624642,
            "y": 5.979701889770212,
            "max_capacity": 4
        },
        {
            "x": 38.113495885507085,
            "y": 8.928315418765653,
            "max_capacity": 3
        },
        {
            "x": 33.77946933505194,
            "y": 23.77239496243818,
            "max_capacity": 5
        },
        {
            "x": 5.060339212662584,
            "y": 14.072284068413499,
            "max_capacity": 5
        },
        {
            "x": 23.06394208376502,
            "y": 42.16039648007055,
            "max_capacity": 7
        },
        {
            "x": 17.1960782824064,
            "y": 25.687165502892984,
            "max_capacity": 5
        },
        {
            "x": 10.508499410915201,
            "y": 28.423409044286068,
            "max_capacity": 4
        },
        {
            "x": 48.487780787638044,
            "y": 49.14919534617638,
            "max_capacity": 3
        },
        {
            "x": 39.45451509827305,
            "y": 25.914629758119002,
            "max_capacity": 3
        },
        {
            "x": 47.01934905646272,
            "y": 14.013988451429139,
            "max_capacity": 7
        },
        {
            "x": 31.84917674948319,
            "y": 11.213502143493475,
            "max_capacity": 7
        },
        {
            "x": 42.37685120684285,
            "y": 23.574809477386104,
            "max_capacity": 4
        },
        {
            "x": 20.49174376914969,
            "y": 19.32632168551854,
            "max_capacity": 5
        },
        {
            "x": 3.5473573140349157,
            "y": 36.193652319735655,
            "max_capacity": 6
        },
        {
            "x": 36.068742843261994,
            "y": 19.405007610666956,
            "max_capacity": 6
        },
        {
            "x": 43.502150036815394,
            "y": 18.713714365842115,
            "max_capacity": 5
        },
        {
            "x": 10.133089587470051,
            "y": 7.8116781650288845,
            "max_capacity": 4
        },
        {
            "x": 28.384140433806788,
            "y": 8.423319851586985,
            "max_capacity": 5
        },
        {
            "x": 40.64740646092353,
            "y": 4.340410371020026,
            "max_capacity": 5
        },
        {
            "x": 1.3922712406157056,
            "y": 20.47337759522833,
            "max_capacity": 7
        },
        {
            "x": 48.08292648518885,
            "y": 23.46617020259841,
            "max_capacity": 7
        },
        {
            "x": 9.43625105118997,
            "y": 11.541069774088403,
            "max_capacity": 7
        },
        {
            "x": 49.03239357742933,
            "y": 45.77884782427826,
            "max_capacity": 5
        },
        {
            "x": 12.894261658366258,
            "y": 8.376828244846873,
            "max_capacity": 6
        },
        {
            "x": 14.645408259801101,
            "y": 18.988795825670707,
            "max_capacity": 6
        },
        {
            "x": 23.363230871146868,
            "y": 49.79543521943789,
            "max_capacity": 3
        },
        {
            "x": 30.22424073468976,
            "y": 3.11314035373228,
            "max_capacity": 4
        },
        {
            "x": 22.731968180953217,
            "y": 28.847541492260405,
            "max_capacity": 7
        },
        {
            "x": 15.453465754778234,
            "y": 41.204263932504084,
            "max_capacity": 7
        },
        {
            "x": 17.224788740857,
            "y": 39.34617153549525,
            "max_capacity": 5
        },
        {
            "x": 14.11797392343635,
            "y": 36.2983463795417,
            "max_capacity": 6
        },
        {
            "x": 5.798183405497969,
            "y": 35.719707056339416,
            "max_capacity": 6
        },
        {
            "x": 31.166890783887713,
            "y": 17.623453549212588,
            "max_capacity": 5
        },
        {
            "x": 31.957188030851047,
            "y": 21.55160832522197,
            "max_capacity": 6
        },
        {
            "x": 37.072398132823174,
            "y": 47.63421220279792,
            "max_capacity": 7
        },
        {
            "x": 29.3870836820634,
            "y": 34.355896750882444,
            "max_capacity": 7
        },
        {
            "x": 32.00867141854521,
            "y": 35.75935454114226,
            "max_capacity": 7
        },
        {
            "x": 35.76041500407713,
            "y": 38.81852410131362,
            "max_capacity": 7
        },
        {
            "x": 17.766113660113202,
            "y": 12.697898431470932,
            "max_capacity": 6
        },
        {
            "x": 9.174208481186868,
            "y": 24.981769626688248,
            "max_capacity": 3
        },
        {
            "x": 4.3372954042662055,
            "y": 20.831387486829854,
            "max_capacity": 3
        },
        {
            "x": 5.915484643642599,
            "y": 43.35351976709039,
            "max_capacity": 5
        },
        {
            "x": 11.759366123943371,
            "y": 30.985377624546885,
            "max_capacity": 4
        },
        {
            "x": 42.97613115260236,
            "y": 44.757838903003474,
            "max_capacity": 7
        },
        {
            "x": 39.66087153150621,
            "y": 35.03309793230373,
            "max_capacity": 4
        },
        {
            "x": 19.555743260343384,
            "y": 39.30582091985564,
            "max_capacity": 5
        },
        {
            "x": 11.378064127347015,
            "y": 18.3552945919123,
            "max_capacity": 4
        },
        {
            "x": 36.14504218502239,
            "y": 5.6029520724299955,
            "max_capacity": 5
        },
        {
            "x": 14.42318629135466,
            "y": 43.16281248930383,
            "max_capacity": 4
        },
        {
            "x": 43.43390089966997,
            "y": 42.86750142086883,
            "max_capacity": 7
        },
        {
            "x": 20.897386891210445,
            "y": 4.653136532536023,
            "max_capacity": 6
        },
        {
            "x": 0.4629866347943379,
            "y": 3.405115664676117,
            "max_capacity": 6
        },
        {
            "x": 13.04634205291989,
            "y": 12.608476190645558,
            "max_capacity": 6
        },
        {
            "x": 41.12030516350206,
            "y": 26.955455099333143,
            "max_capacity": 5
        },
        {
            "x": 30.98110503897026,
            "y": 5.921904211235302,
            "max_capacity": 7
        },
        {
            "x": 7.0477156737619335,
            "y": 0.4045440503168074,
            "max_capacity": 4
        },
        {
            "x": 48.25539938458045,
            "y": 1.2400358577732862,
            "max_capacity": 3
        },
        {
            "x": 20.590832858243964,
            "y": 18.044828738723528,
            "max_capacity": 3
        },
        {
            "x": 11.676292493509594,
            "y": 16.10892169232145,
            "max_capacity": 3
        }
    ],
    "bushes": [
        {
            "max_calories": 700,
            "x": 25.10792484037622,
            "y": 23.936309373819913
        },
        {
            "max_calories": 550,
            "x": 33.353739848458446,
            "y": 10.625526269602908
        },
        {
            "max_calories": 600,
            "x": 34.11794334570178,
            "y": 14.851600579153946
        },
        {
            "max_calories": 700,
            "x": 14.814347197004501,
            "y": 40.49035126189619
        },
        {
            "max_calories": 550,
            "x": 12.179636425020707,
            "y": 48.632999477375435
        },
        {
            "max_calories": 500,
            "x": 30.808532382692842,
            "y": 33.552679009366734
        },
        {
            "max_calories": 550,
            "x": 42.98284467638559,
            "y": 5.3796521722388855
        },
        {
            "max_calories": 750,
            "x": 21.06864459845474,
            "y": 43.426528919801534
        },
        {
            "max_calories": 700,
            "x": 38.69480595821762,
            "y": 1.7701994633019968
        },
        {
            "max_calories": 750,
            "x": 25.8572627277681,
            "y": 0.6422065803646959
        },
        {
            "max_calories": 550,
            "x": 28.239634597380135,
            "y": 35.924189462201625
        },
        {
            "max_calories": 400,
            "x": 20.719426389521384,
            "y": 22.215612113214263
        },
        {
            "max_calories": 550,
            "x": 24.896157632889665,
            "y": 41.93659671159855
        },
        {
            "max_calories": 700,
            "x": 33.712648258220305,
            "y": 20.927525765112843
        },
        {
            "max_calories": 550,
            "x": 39.335073679303726,
            "y": 10.663847174535269
        },
        {
            "max_calories": 750,
            "x": 39.58340009817967,
            "y": 15.708202329991472
        },
        {
            "max_calories": 500,
            "x": 21.97431871342855,
            "y": 14.43801170403949
        },
        {
            "max_calories": 700,
            "x": 24.87076757116935,
            "y": 1.5102625404676606
        },
        {
            "max_calories": 550,
            "x": 0.3859532949110678,
            "y": 35.410518675943294
        },
        {
            "max_calories": 700,
            "x": 49.97939377725052,
            "y": 23.934867990101168
        },
        {
            "max_calories": 500,
            "x": 29.60165309253834,
            "y": 38.36117880664078
        },
        {
            "max_calories": 600,
            "x": 2.7663649042847185,
            "y": 29.968505913929878
        },
        {
            "max_calories": 400,
            "x": 37.68528911508837,
            "y": 13.19701831249755
        },
        {
            "max_calories": 400,
            "x": 33.8628729628803,
            "y": 20.63962460132131
        },
        {
            "max_calories": 700,
            "x": 28.892660035814,
            "y": 8.143208653577583
        },
        {
            "max_calories": 650,
            "x": 25.643940806766835,
            "y": 7.494062012011632
        },
        {
            "max_calories": 500,
            "x": 13.62887903279808,
            "y": 11.271188685995265
        },
        {
            "max_calories": 800,
            "x": 33.42528282939664,
            "y": 3.894364297133529
        },
        {
            "max_calories": 550,
            "x": 28.993918332384805,
            "y": 12.636371671512354
        },
        {
            "max_calories": 650,
            "x": 5.160711645787785,
            "y": 37.41901646815096
        },
        {
            "max_calories": 550,
            "x": 7.227204924985308,
            "y": 36.03579146289518
        },
        {
            "max_calories": 550,
            "x": 3.8003378008597375,
            "y": 40.4971885406642
        },
        {
            "max_calories": 500,
            "x": 17.76927187182643,
            "y": 34.70118455176101
        },
        {
            "max_calories": 450,
            "x": 42.36311814994977,
            "y": 41.563268626706844
        },
        {
            "max_calories": 700,
            "x": 33.47284441573004,
            "y": 15.327846701684095
        },
        {
            "max_calories": 550,
            "x": 30.35723534021027,
            "y": 18.23446193120679
        },
        {
            "max_calories": 550,
            "x": 2.1995341777492516,
            "y": 49.54170820912548
        },
        {
            "max_calories": 650,
            "x": 39.34165224437813,
            "y": 7.734514938155951
        },
        {
            "max_calories": 450,
            "x": 40.81748140652641,
            "y": 39.14253762992864
        },
        {
            "max_calories": 650,
            "x": 7.9448940129801855,
            "y": 5.568974202963228
        },
        {
            "max_calories": 600,
            "x": 31.35109496269404,
            "y": 23.099330151265075
        },
        {
            "max_calories": 650,
            "x": 39.02580172909425,
            "y": 48.96166509460515
        },
        {
            "max_calories": 550,
            "x": 38.01866624312043,
            "y": 24.9526585358544
        },
        {
            "max_calories": 550,
            "x": 21.83294166482495,
            "y": 15.994029139305098
        },
        {
            "max_calories": 700,
            "x": 9.559347280814517,
            "y": 42.87978499836613
        },
        {
            "max_calories": 650,
            "x": 38.206107558241335,
            "y": 38.75087699248477
        },
        {
            "max_calories": 500,
            "x": 0.07390022868822843,
            "y": 16.237640850906875
        },
        {
            "max_calories": 600,
            "x": 49.416772250383794,
            "y": 4.399615683059604
        },
        {
            "max_calories": 750,
            "x": 38.000979720053564,
            "y": 25.99068726131412
        },
        {
            "max_calories": 450,
            "x": 28.49713131878936,
            "y": 14.077888229739106
        },
        {
            "max_calories": 700,
            "x": 46.629743177311425,
            "y": 28.608855739699717
        },
        {
            "max_calories": 400,
            "x": 4.903098240296789,
            "y": 30.84346913302145
        },
        {
            "max_calories": 700,
            "x": 16.02481439195126,
            "y": 16.792324676630262
        },
        {
            "max_calories": 750,
            "x": 48.105440593325774,
            "y": 46.312357900203224
        },
        {
            "max_calories": 750,
            "x": 40.26030759016605,
            "y": 40.45148577790661
        },
        {
            "max_calories": 600,
            "x": 22.096668843923624,
            "y": 49.976303790279395
        },
        {
            "max_calories": 600,
            "x": 14.286021981528046,
            "y": 13.260514891883417
        },
        {
            "max_calories": 450,
            "x": 15.885419061811962,
            "y": 25.181177964568068
        },
        {
            "max_calories": 400,
            "x": 3.2813841490856257,
            "y": 31.298466503133938
        },
        {
            "max_calories": 800,
            "x": 14.771085890846619,
            "y": 41.23065746162358
        },
        {
            "max_calories": 750,
            "x": 6.874426496023572,
            "y": 21.95793551864619
        },
        {
            "max_calories": 550,
            "x": 14.357994474477954,
            "y": 35.29123028109521
        },
        {
            "max_calories": 400,
            "x": 23.446049491490072,
            "y": 29.91690868624579
        },
        {
            "max_calories": 600,
            "x": 11.461077717177337,
            "y": 20.408252184753295
        },
        {
            "max_calories": 600,
            "x": 17.914815665156457,
            "y": 31.68624219563049
        },
        {
            "max_calories": 400,
            "x": 44.08803334666006,
            "y": 37.25069476364807
        },
        {
            "max_calories": 550,
            "x": 34.60260144716771,
            "y": 17.15031348354456
        },
        {
            "max_calories": 550,
            "x": 20.612566841572814,
            "y": 42.27215363876316
        },
        {
            "max_calories": 750,
            "x": 2.8866631165500922,
            "y": 37.324478206748616
        },
        {
            "max_calories": 450,
            "x": 2.673756718836373,
            "y": 25.873624702734
        },
        {
            "max_calories": 700,
            "x": 18.589428065707576,
            "y": 21.546166224041674
        },
        {
            "max_calories": 500,
            "x": 9.75411897260557,
            "y": 26.696231225852586
        },
        {
            "max_calories": 600,
            "x": 36.40706869113875,
            "y": 8.162783181502803
        },
        {
            "max_calories": 750,
            "x": 42.47781200805299,
            "y": 36.82661151514877
        },
        {
            "max_calories": 550,
            "x": 22.76084626705633,
            "y": 14.36535813174129
        },
        {
            "max_calories": 550,
            "x": 41.52124990643967,
            "y": 5.465759890262511
        },
        {
            "max_calories": 500,
            "x": 30.882136772159498,
            "y": 39.213333481335255
        },
        {
            "max_calories": 800,
            "x": 48.03620314463975,
            "y": 16.579648136039992
        },
        {
            "max_calories": 400,
            "x": 19.842211700680775,
            "y": 23.913264014596873
        },
        {
            "max_calories": 550,
            "x": 33.55612205983138,
            "y": 1.0707038678685221
        },
        {
            "max_calories": 650,
            "x": 14.990551829699255,
            "y": 14.15563647853652
        },
        {
            "max_calories": 750,
            "x": 47.11220110624583,
            "y": 41.07808553022439
        },
        {
            "max_calories": 650,
            "x": 43.14798292962839,
            "y": 38.31782486713464
        },
        {
            "max_calories": 500,
            "x": 7.687838653096346,
            "y": 39.983144225143995
        },
        {
            "max_calories": 500,
            "x": 26.044160590579896,
            "y": 29.329826799296434
        },
        {
            "max_calories": 800,
            "x": 26.45973004514797,
            "y": 41.14984155056395
        },
        {
            "max_calories": 600,
            "x": 11.512191670744908,
            "y": 16.47380982456033
        },
        {
            "max_calories": 600,
            "x": 6.90573808917968,
            "y": 46.63051450256683
        },
        {
            "max_calories": 550,
            "x": 16.81393124604396,
            "y": 6.194680848312684
        },
        {
            "max_calories": 700,
            "x": 11.766060475049816,
            "y": 28.782590576780077
        },
        {
            "max_calories": 600,
            "x": 44.08855136824131,
            "y": 35.073575039411615
        },
        {
            "max_calories": 400,
            "x": 34.000686872591466,
            "y": 6.687100428775262
        },
        {
            "max_calories": 700,
            "x": 13.089830013489461,
            "y": 43.43647686630897
        },
        {
            "max_calories": 550,
            "x": 41.86276201637685,
            "y": 23.482229884485267
        },
        {
            "max_calories": 650,
            "x": 49.093964519755076,
            "y": 1.9887183187010882
        },
        {
            "max_calories": 400,
            "x": 1.6300229715380143,
            "y": 26.51537841856842
        },
        {
            "max_calories": 500,
            "x": 30.958525039727856,
            "y": 45.8351566087791
        },
        {
            "max_calories": 500,
            "x": 16.793622876883862,
            "y": 31.72002981248974
        },
        {
            "max_calories": 450,
            "x": 34.46237279443154,
            "y": 29.09648300311772
        },
        {
            "max_calories": 500,
            "x": 4.121434290564335,
            "y": 8.779442474847926
        }
    ],
    "agents": [
        {
            "max_memory": 0,
            "aggressiveness": 0.3942067280236873,
            "harvest_percent": 0.6054554624163717,
            "x": 4.40437529422843,
            "y": 22.80861531253232
        },
        {
            "max_memory": 0,
            "aggressiveness": 0.3281515119351769,
            "harvest_percent": 0.49236266725580186,
            "x": 30.98110503897026,
            "y": 5.921904211235302
        },
        {
            "max_memory": 0,
            "aggressiveness": 0.15388364270687646,
            "harvest_percent": 0.3711183005302746,
            "x": 35.76041500407713,
            "y": 38.81852410131362
        },
        {
            "max_memory": 0,
            "aggressiveness": 0.2606988883271784,
            "harvest_percent": 0.6750108071037946,
            "x": 17.224788740857,
            "y": 39.34617153549525
        },
        {
            "max_memory": 0,
            "aggressiveness": 0.19610324103588586,
            "harvest_percent": 0.5976228892011506,
            "x": 13.110411762892493,
            "y": 45.37018110659511
        },
        {
            "max_memory": 0,
            "aggressiveness": 0.17769009893896837,
            "harvest_percent": 0.6460665482046458,
            "x": 9.174208481186868,
            "y": 24.981769626688248
        },
        {
            "max_memory": 0,
            "aggressiveness": 0.2627030848997344,
            "harvest_percent": 0.6869917112546162,
            "x": 14.42318629135466,
            "y": 43.16281248930383
        },
        {
            "max_memory": 0,
            "aggressiveness": 0.21946544468473422,
            "harvest_percent": 0.5258875258156946,
            "x": 17.766113660113202,
            "y": 12.697898431470932
        },
        {
            "max_memory": 0,
            "aggressiveness": 0.3081171325271125,
            "harvest_percent": 0.7005042544715614,
            "x": 32.7416532773555,
            "y": 13.348522536089991
        },
        {
            "max_memory": 1,
            "aggressiveness": 0.32051153606912886,
            "harvest_percent": 0.6206779867342332,
            "x": 38.113495885507085,
            "y": 8.928315418765653
        },
        {
            "max_memory": 0,
            "aggressiveness": 0.29194103771193053,
            "harvest_percent": 0.627499166579153,
            "x": 17.1960782824064,
            "y": 25.687165502892984
        },
        {
            "max_memory": 2,
            "aggressiveness": 0.2612405855164978,
            "harvest_percent": 0.586805559174587,
            "x": 31.957188030851047,
            "y": 21.55160832522197
        },
        {
            "max_memory": 0,
            "aggressiveness": 0.2863334813135027,
            "harvest_percent": 0.7210791459931325,
            "x": 30.052598649624642,
            "y": 5.979701889770212
        },
        {
            "max_memory": 1,
            "aggressiveness": 0.2752973995404633,
            "harvest_percent": 0.6448297029196774,
            "x": 10.508499410915201,
            "y": 28.423409044286068
        },
        {
            "max_memory": 1,
            "aggressiveness": 0.20623135747445234,
            "harvest_percent": 0.6268915740173161,
            "x": 36.14504218502239,
            "y": 5.6029520724299955
        },
        {
            "max_memory": 0,
            "aggressiveness": 0.18607484795144918,
            "harvest_percent": 0.47602136053074245,
            "x": 9.66736948011005,
            "y": 49.887435688456826
        },
        {
            "max_memory": 0,
            "aggressiveness": 0.3467330560571191,
            "harvest_percent": 0.6827698864895102,
            "x": 11.378064127347015,
            "y": 18.3552945919123
        },
        {
            "max_memory": 0,
            "aggressiveness": 0.161586850824962,
            "harvest_percent": 0.4603621400022066,
            "x": 40.64740646092353,
            "y": 4.340410371020026
        },
        {
            "max_memory": 0,
            "aggressiveness": 0.1477237866244774,
            "harvest_percent": 0.47797782391185983,
            "x": 39.66087153150621,
            "y": 35.03309793230373
        },
        {
            "max_memory": 0,
            "aggressiveness": 0.24286902938766117,
            "harvest_percent": 0.6069858267105864,
            "x": 32.00867141854521,
            "y": 35.75935454114226
        },
        {
            "max_memory": 0,
            "aggressiveness": 0.16832111693144808,
            "harvest_percent": 0.6623722530480493,
            "x": 11.936626168169234,
            "y": 32.27656424383623
        },
        {
            "max_memory": 0,
            "aggressiveness": 0.246123923953939,
            "harvest_percent": 0.6440081812097435,
            "x": 43.43390089966997,
            "y": 42.86750142086883
        },
        {
            "max_memory": 0,
            "aggressiveness": 0.24043496514558083,
            "harvest_percent": 0.6033896173025318,
            "x": 36.068742843261994,
            "y": 19.405007610666956
        },
        {
            "max_memory": 0,
            "aggressiveness": 0.2818664982579188,
            "harvest_percent": 0.6759250238637888,
            "x": 19.555743260343384,
            "y": 39.30582091985564
        },
        {
            "max_memory": 0,
            "aggressiveness": 0.22136089205050463,
            "harvest_percent": 0.5064334608574621,
            "x": 22.731968180953217,
            "y": 28.847541492260405
        },
        {
            "max_memory": 0,
            "aggressiveness": 0.16625310538073984,
            "harvest_percent": 0.5814544103757808,
            "x": 11.759366123943371,
            "y": 30.985377624546885
        },
        {
            "max_memory": 1,
            "aggressiveness": 0.13679468966443176,
            "harvest_percent": 0.6323315456519297,
            "x": 17.766113660113202,
            "y": 12.697898431470932
        },
        {
            "max_memory": 1,
            "aggressiveness": 0.3137193855617664,
            "harvest_percent": 0.5154696745236889,
            "x": 32.00867141854521,
            "y": 35.75935454114226
        },
        {
            "max_memory": 2,
            "aggressiveness": 0.1971656663628979,
            "harvest_percent": 0.5361659323045844,
            "x": 10.508499410915201,
            "y": 28.423409044286068
        },
        {
            "max_memory": 1,
            "aggressiveness": 0.24973344411293172,
            "harvest_percent": 0.6383845541657506,
            "x": 35.76041500407713,
            "y": 38.81852410131362
        },
        {
            "max_memory": 0,
            "aggressiveness": 0.4230059005107508,
            "harvest_percent": 0.6005614663516159,
            "x": 11.378064127347015,
            "y": 18.3552945919123
        },
        {
            "max_memory": 1,
            "aggressiveness": 0.36194555459578953,
            "harvest_percent": 0.7042303899798039,
            "x": 17.319673178177307,
            "y": 16.42836748914604
        },
        {
            "max_memory": 1,
            "aggressiveness": 0.24712954244136776,
            "harvest_percent": 0.6677856615114324,
            "x": 40.64740646092353,
            "y": 4.340410371020026
        },
        {
            "max_memory": 0,
            "aggressiveness": 0.20666283582888645,
            "harvest_percent": 0.6058410536630403,
            "x": 9.66736948011005,
            "y": 49.887435688456826
        },
        {
            "max_memory": 0,
            "aggressiveness": 0.37732881797945983,
            "harvest_percent": 0.5406870694428044,
            "x": 20.49174376914969,
            "y": 19.32632168551854
        },
        {
            "max_memory": 0,
            "aggressiveness": 0.37828432609027596,
            "harvest_percent": 0.48506206945901004,
            "x": 11.378064127347015,
            "y": 18.3552945919123
        },
        {
            "max_memory": 2,
            "aggressiveness": 0.31727631653007154,
            "harvest_percent": 0.495523050201998,
            "x": 20.49174376914969,
            "y": 19.32632168551854
        },
        {
            "max_memory": 0,
            "aggressiveness": 0.07777616328752922,
            "harvest_percent": 0.4754797008065688,
            "x": 28.384140433806788,
            "y": 8.423319851586985
        },
        {
            "max_memory": 0,
            "aggressiveness": 0.22237859657285142,
            "harvest_percent": 0.5488565450461365,
            "x": 39.66087153150621,
            "y": 35.03309793230373
        },
        {
            "max_memory": 0,
            "aggressiveness": 0.10978734701680443,
            "harvest_percent": 0.4925748283820805,
            "x": 43.43390089966997,
            "y": 42.86750142086883
        },
        {
            "max_memory": 0,
            "aggressiveness": 0.31496410956139653,
            "harvest_percent": 0.5559234933877013,
            "x": 22.731968180953217,
            "y": 28.847541492260405
        },
        {
            "max_memory": 0,
            "aggressiveness": 0.3717203036057969,
            "harvest_percent": 0.6641115529469035,
            "x": 3.5473573140349157,
            "y": 36.193652319735655
        },
        {
            "max_memory": 0,
            "aggressiveness": 0.1358553012089681,
            "harvest_percent": 0.535011825181513,
            "x": 23.06394208376502,
            "y": 42.16039648007055
        },
        {
            "max_memory": 1,
            "aggressiveness": 0.26167003381167414,
            "harvest_percent": 0.6316507285880868,
            "x": 2.242251418672503,
            "y": 38.08967163607256
        },
        {
            "max_memory": 1,
            "aggressiveness": 0.21921944203471075,
            "harvest_percent": 0.5673834663736136,
            "x": 40.64740646092353,
            "y": 4.340410371020026
        },
        {
            "max_memory": 0,
            "aggressiveness": 0.27161879568550723,
            "harvest_percent": 0.6133560606286445,
            "x": 23.595720233935992,
            "y": 11.438332591576527
        },
        {
            "max_memory": 1,
            "aggressiveness": 0.3104363593940267,
            "harvest_percent": 0.5337697705703995,
            "x": 19.555743260343384,
            "y": 39.30582091985564
        },
        {
            "max_memory": 0,
            "aggressiveness": 0.25371444071613675,
            "harvest_percent": 0.6315136875792642,
            "x": 2.242251418672503,
            "y": 38.08967163607256
        },
        {
            "max_memory": 1,
            "aggressiveness": 0.26667211586776224,
            "harvest_percent": 0.6568405580719217,
            "x": 30.98110503897026,
            "y": 5.921904211235302
        },
        {
            "max_memory": 0,
            "aggressiveness": 0.12893044512429738,
            "harvest_percent": 0.54516722534221,
            "x": 11.759366123943371,
            "y": 30.985377624546885
        },
        {
            "max_memory": 0,
            "aggressiveness": 0.35403234061833844,
            "harvest_percent": 0.5336701793651292,
            "x": 22.731968180953217,
            "y": 28.847541492260405
        },
        {
            "max_memory": 0,
            "aggressiveness": 0.31717759875135126,
            "harvest_percent": 0.3775098979595627,
            "x": 17.319673178177307,
            "y": 16.42836748914604
        },
        {
            "max_memory": 0,
            "aggressiveness": 0.35146120093458255,
            "harvest_percent": 0.5022464802464847,
            "x": 23.595720233935992,
            "y": 11.438332591576527
        },
        {
            "max_memory": 1,
            "aggressiveness": 0.1945314134348955,
            "harvest_percent": 0.5783091712760159,
            "x": 22.731968180953217,
            "y": 28.847541492260405
        },
        {
            "max_memory": 0,
            "aggressiveness": 0.18892707856922808,
            "harvest_percent": 0.6080931300367955,
            "x": 17.224788740857,
            "y": 39.34617153549525
        },
        {
            "max_memory": 0,
            "aggressiveness": 0.1756103819649234,
            "harvest_percent": 0.5205132874244218,
            "x": 11.936626168169234,
            "y": 32.27656424383623
        },
        {
            "max_memory": 1,
            "aggressiveness": 0.2938733107876536,
            "harvest_percent": 0.5047231371130587,
            "x": 48.25539938458045,
            "y": 1.2400358577732862
        },
        {
            "max_memory": 0,
            "aggressiveness": 0.28035666659770897,
            "harvest_percent": 0.5774851047716862,
            "x": 31.957188030851047,
            "y": 21.55160832522197
        },
        {
            "max_memory": 0,
            "aggressiveness": 0.1603637839539348,
            "harvest_percent": 0.5290936123296727,
            "x": 15.453465754778234,
            "y": 41.204263932504084
        },
        {
            "max_memory": 0,
            "aggressiveness": 0.18272496792752985,
            "harvest_percent": 0.5930218724129012,
            "x": 32.7416532773555,
            "y": 13.348522536089991
        },
        {
            "max_memory": 0,
            "aggressiveness": 0.2453972360243727,
            "harvest_percent": 0.6303864156912743,
            "x": 2.242251418672503,
            "y": 38.08967163607256
        },
        {
            "max_memory": 1,
            "aggressiveness": 0.23520306950015019,
            "harvest_percent": 0.585367383844674,
            "x": 23.06394208376502,
            "y": 42.16039648007055
        },
        {
            "max_memory": 0,
            "aggressiveness": 0.2789241571100161,
            "harvest_percent": 0.4922956816960341,
            "x": 11.936626168169234,
            "y": 32.27656424383623
        },
        {
            "max_memory": 0,
            "aggressiveness": 0.15126381900993477,
            "harvest_percent": 0.6259636607431177,
            "x": 19.555743260343384,
            "y": 39.30582091985564
        },
        {
            "max_memory": 2,
            "aggressiveness": 0.2884992429325766,
            "harvest_percent": 0.40170525788250194,
            "x": 31.957188030851047,
            "y": 21.55160832522197
        },
        {
            "max_memory": 0,
            "aggressiveness": 0.3324977635253963,
            "harvest_percent": 0.6232150048887849,
            "x": 10.508499410915201,
            "y": 28.423409044286068
        },
        {
            "max_memory": 0,
            "aggressiveness": 0.15826170246023782,
            "harvest_percent": 0.4510285609151976,
            "x": 32.00867141854521,
            "y": 35.75935454114226
        },
        {
            "max_memory": 0,
            "aggressiveness": 0.28203279161562,
            "harvest_percent": 0.6019467000934895,
            "x": 17.1960782824064,
            "y": 25.687165502892984
        },
        {
            "max_memory": 0,
            "aggressiveness": 0.32778755092436807,
            "harvest_percent": 0.4807558384641952,
            "x": 11.936626168169234,
            "y": 32.27656424383623
        },
        {
            "max_memory": 1,
            "aggressiveness": 0.24362623696230223,
            "harvest_percent": 0.5155747591457648,
            "x": 36.068742843261994,
            "y": 19.405007610666956
        },
        {
            "max_memory": 0,
            "aggressiveness": 0.258985218927188,
            "harvest_percent": 0.5045171171237597,
            "x": 22.731968180953217,
            "y": 28.847541492260405
        },
        {
            "max_memory": 0,
            "aggressiveness": 0.2614100645994489,
            "harvest_percent": 0.46243653852782,
            "x": 5.798183405497969,
            "y": 35.719707056339416
        },
        {
            "max_memory": 0,
            "aggressiveness": 0.15644508240352029,
            "harvest_percent": 0.5576342972927069,
            "x": 32.00867141854521,
            "y": 35.75935454114226
        },
        {
            "max_memory": 0,
            "aggressiveness": 0.15861983662722962,
            "harvest_percent": 0.6689225203831405,
            "x": 11.759366123943371,
            "y": 30.985377624546885
        },
        {
            "max_memory": 0,
            "aggressiveness": 0.20027587864486882,
            "harvest_percent": 0.5983912416195847,
            "x": 23.06394208376502,
            "y": 42.16039648007055
        },
        {
            "max_memory": 0,
            "aggressiveness": 0.21713288509968404,
            "harvest_percent": 0.6816194110877897,
            "x": 20.49174376914969,
            "y": 19.32632168551854
        },
        {
            "max_memory": 2,
            "aggressiveness": 0.2726693952628707,
            "harvest_percent": 0.40334691247151866,
            "x": 9.292097693379569,
            "y": 39.74399629292607
        },
        {
            "max_memory": 2,
            "aggressiveness": 0.273494386711237,
            "harvest_percent": 0.4135984031900215,
            "x": 4.3372954042662055,
            "y": 20.831387486829854
        },
        {
            "max_memory": 1,
            "aggressiveness": 0.2547830220145839,
            "harvest_percent": 0.4776071635415952,
            "x": 39.66087153150621,
            "y": 35.03309793230373
        },
        {
            "max_memory": 1,
            "aggressiveness": 0.16324342179502724,
            "harvest_percent": 0.6133570336488273,
            "x": 17.766113660113202,
            "y": 12.697898431470932
        },
        {
            "max_memory": 2,
            "aggressiveness": 0.33079665071296727,
            "harvest_percent": 0.5201061076864417,
            "x": 36.14504218502239,
            "y": 5.6029520724299955
        },
        {
            "max_memory": 0,
            "aggressiveness": 0.14306789646832996,
            "harvest_percent": 0.61805563585941,
            "x": 5.798183405497969,
            "y": 35.719707056339416
        },
        {
            "max_memory": 0,
            "aggressiveness": 0.24741125787933335,
            "harvest_percent": 0.5640696883559616,
            "x": 17.766113660113202,
            "y": 12.697898431470932
        },
        {
            "max_memory": 0,
            "aggressiveness": 0.4301599679477943,
            "harvest_percent": 0.6244491518159705,
            "x": 38.113495885507085,
            "y": 8.928315418765653
        },
        {
            "max_memory": 1,
            "aggressiveness": 0.2758019988273221,
            "harvest_percent": 0.5893598540926496,
            "x": 17.319673178177307,
            "y": 16.42836748914604
        },
        {
            "max_memory": 0,
            "aggressiveness": 0.3716455658200964,
            "harvest_percent": 0.583232578579326,
            "x": 19.555743260343384,
            "y": 39.30582091985564
        },
        {
            "max_memory": 1,
            "aggressiveness": 0.3735863529818501,
            "harvest_percent": 0.5769262441125832,
            "x": 9.174208481186868,
            "y": 24.981769626688248
        },
        {
            "max_memory": 2,
            "aggressiveness": 0.16815923355837933,
            "harvest_percent": 0.5697601263541056,
            "x": 3.5473573140349157,
            "y": 36.193652319735655
        },
        {
            "max_memory": 1,
            "aggressiveness": 0.2349847695583635,
            "harvest_percent": 0.5407123456193634,
            "x": 28.384140433806788,
            "y": 8.423319851586985
        },
        {
            "max_memory": 0,
            "aggressiveness": 0.35115945369675655,
            "harvest_percent": 0.6478603148416124,
            "x": 5.798183405497969,
            "y": 35.719707056339416
        },
        {
            "max_memory": 0,
            "aggressiveness": 0.16657480911896533,
            "harvest_percent": 0.5355608171598146,
            "x": 23.595720233935992,
            "y": 11.438332591576527
        },
        {
            "max_memory": 1,
            "aggressiveness": 0.2817924119461736,
            "harvest_percent": 0.5990219511895042,
            "x": 36.14504218502239,
            "y": 5.6029520724299955
        },
        {
            "max_memory": 0,
            "aggressiveness": 0.3004217077521616,
            "harvest_percent": 0.5528664756913517,
            "x": 20.590832858243964,
            "y": 18.044828738723528
        },
        {
            "max_memory": 0,
            "aggressiveness": 0.3233098825701697,
            "harvest_percent": 0.5316135864878231,
            "x": 20.49174376914969,
            "y": 19.32632168551854
        },
        {
            "max_memory": 0,
            "aggressiveness": 0.2583601245809499,
            "harvest_percent": 0.6133713047926171,
            "x": 42.97613115260236,
            "y": 44.757838903003474
        },
        {
            "max_memory": 2,
            "aggressiveness": 0.34100321693013835,
            "harvest_percent": 0.5249148438183804,
            "x": 40.64740646092353,
            "y": 4.340410371020026
        },
        {
            "max_memory": 0,
            "aggressiveness": 0.25506826808358357,
            "harvest_percent": 0.6932028404518499,
            "x": 1.3922712406157056,
            "y": 20.47337759522833
        },
        {
            "max_memory": 1,
            "aggressiveness": 0.22056250134587108,
            "harvest_percent": 0.4559083293390724,
            "x": 14.42318629135466,
            "y": 43.16281248930383
        },
        {
            "max_memory": 0,
            "aggressiveness": 0.30448049711838987,
            "harvest_percent": 0.41829921656325586,
            "x": 22.731968180953217,
            "y": 28.847541492260405
        },
        {
            "max_memory": 0,
            "aggressiveness": 0.23510950425567329,
            "harvest_percent": 0.5465992871481089,
            "x": 23.595720233935992,
            "y": 11.438332591576527
        },
        {
            "max_memory": 1,
            "aggressiveness": 0.31237038225433156,
            "harvest_percent": 0.4355397052778566,
            "x": 35.76041500407713,
            "y": 38.81852410131362
        },
        {
            "max_memory": 1,
            "aggressiveness": 0.12886759159815586,
            "harvest_percent": 0.5262401349298526,
            "x": 17.1960782824064,
            "y": 25.687165502892984
        },
        {
            "max_memory": 0,
            "aggressiveness": 0.1692757751583345,
            "harvest_percent": 0.6152674610791851,
            "x": 40.64740646092353,
            "y": 4.340410371020026
        },
        {
            "max_memory": 0,
            "aggressiveness": 0.17565486807135294,
            "harvest_percent": 0.5636572099007026,
            "x": 13.04634205291989,
            "y": 12.608476190645558
        },
        {
            "max_memory": 1,
            "aggressiveness": 0.2379049195362338,
            "harvest_percent": 0.7987007494168854,
            "x": 17.319673178177307,
            "y": 16.42836748914604
        },
        {
            "max_memory": 0,
            "aggressiveness": 0.31249128249945296,
            "harvest_percent": 0.5604730936507616,
            "x": 22.731968180953217,
            "y": 28.847541492260405
        },
        {
            "max_memory": 0,
            "aggressiveness": 0.09221654443197233,
            "harvest_percent": 0.6029725522216298,
            "x": 29.3870836820634,
            "y": 34.355896750882444
        },
        {
            "max_memory": 2,
            "aggressiveness": 0.13024137681590697,
            "harvest_percent": 0.5867575367591215,
            "x": 14.645408259801101,
            "y": 18.988795825670707
        },
        {
            "max_memory": 2,
            "aggressiveness": 0.2184318356117762,
            "harvest_percent": 0.5889705271543109,
            "x": 23.06394208376502,
            "y": 42.16039648007055
        },
        {
            "max_memory": 0,
            "aggressiveness": 0.2823186629284688,
            "harvest_percent": 0.5262015744436642,
            "x": 3.5473573140349157,
            "y": 36.193652319735655
        },
        {
            "max_memory": 0,
            "aggressiveness": 0.2804147555942381,
            "harvest_percent": 0.45798062406547585,
            "x": 9.292097693379569,
            "y": 39.74399629292607
        },
        {
            "max_memory": 3,
            "aggressiveness": 0.3151319137084624,
            "harvest_percent": 0.5202557515325165,
            "x": 31.84917674948319,
            "y": 11.213502143493475
        },
        {
            "max_memory": 2,
            "aggressiveness": 0.1456307911688175,
            "harvest_percent": 0.4199924170459456,
            "x": 20.897386891210445,
            "y": 4.653136532536023
        },
        {
            "max_memory": 0,
            "aggressiveness": 0.10685615832819544,
            "harvest_percent": 0.6058537105766896,
            "x": 20.590832858243964,
            "y": 18.044828738723528
        },
        {
            "max_memory": 1,
            "aggressiveness": 0.1363277727495848,
            "harvest_percent": 0.6333914494022874,
            "x": 9.292097693379569,
            "y": 39.74399629292607
        },
        {
            "max_memory": 0,
            "aggressiveness": 0.12083560013425435,
            "harvest_percent": 0.46638474254424267,
            "x": 32.7416532773555,
            "y": 13.348522536089991
        },
        {
            "max_memory": 1,
            "aggressiveness": 0.20882886460093755,
            "harvest_percent": 0.5031109577675622,
            "x": 3.5473573140349157,
            "y": 36.193652319735655
        },
        {
            "max_memory": 2,
            "aggressiveness": 0.34633353655287136,
            "harvest_percent": 0.4946386475752588,
            "x": 48.08292648518885,
            "y": 23.46617020259841
        },
        {
            "max_memory": 0,
            "aggressiveness": 0.29198996154705026,
            "harvest_percent": 0.5208096944732021,
            "x": 4.3372954042662055,
            "y": 20.831387486829854
        },
        {
            "max_memory": 2,
            "aggressiveness": 0.4068390861671114,
            "harvest_percent": 0.42299008660444304,
            "x": 35.76041500407713,
            "y": 38.81852410131362
        },
        {
            "max_memory": 0,
            "aggressiveness": 0.2756863852479066,
            "harvest_percent": 0.6767176069927121,
            "x": 36.14504218502239,
            "y": 5.6029520724299955
        },
        {
            "max_memory": 0,
            "aggressiveness": 0.3885384723647148,
            "harvest_percent": 0.6240479870555038,
            "x": 13.04634205291989,
            "y": 12.608476190645558
        },
        {
            "max_memory": 0,
            "aggressiveness": 0.1963222367008214,
            "harvest_percent": 0.510129723008798,
            "x": 17.766113660113202,
            "y": 12.697898431470932
        },
        {
            "max_memory": 0,
            "aggressiveness": 0.16285561742858415,
            "harvest_percent": 0.5312909846370107,
            "x": 17.1960782824064,
            "y": 25.687165502892984
        },
        {
            "max_memory": 0,
            "aggressiveness": 0.2528688289060536,
            "harvest_percent": 0.6117792333273132,
            "x": 21.98314145239927,
            "y": 5.737719306780681
        },
        {
            "max_memory": 0,
            "aggressiveness": 0.20170994424022967,
            "harvest_percent": 0.5243771636227701,
            "x": 10.508499410915201,
            "y": 28.423409044286068
        },
        {
            "max_memory": 0,
            "aggressiveness": 0.23513523788562926,
            "harvest_percent": 0.5308873900699485,
            "x": 5.798183405497969,
            "y": 35.719707056339416
        },
        {
            "max_memory": 2,
            "aggressiveness": 0.28520747502333593,
            "harvest_percent": 0.5912720639807897,
            "x": 31.166890783887713,
            "y": 17.623453549212588
        },
        {
            "max_memory": 0,
            "aggressiveness": 0.35239388462300764,
            "harvest_percent": 0.4295491418412214,
            "x": 20.590832858243964,
            "y": 18.044828738723528
        },
        {
            "max_memory": 1,
            "aggressiveness": 0.2745607673472577,
            "harvest_percent": 0.6091931783133168,
            "x": 1.3922712406157056,
            "y": 20.47337759522833
        },
        {
            "max_memory": 0,
            "aggressiveness": 0.3189716042532444,
            "harvest_percent": 0.6127288206284285,
            "x": 29.3870836820634,
            "y": 34.355896750882444
        },
        {
            "max_memory": 0,
            "aggressiveness": 0.353830872518866,
            "harvest_percent": 0.627854088794521,
            "x": 17.224788740857,
            "y": 39.34617153549525
        },
        {
            "max_memory": 0,
            "aggressiveness": 0.2805930185888412,
            "harvest_percent": 0.6254253686974836,
            "x": 13.110411762892493,
            "y": 45.37018110659511
        },
        {
            "max_memory": 1,
            "aggressiveness": 0.03947168450113456,
            "harvest_percent": 0.6542647617868212,
            "x": 3.5473573140349157,
            "y": 36.193652319735655
        },
        {
            "max_memory": 1,
            "aggressiveness": 0.26461331024288376,
            "harvest_percent": 0.5983152353727951,
            "x": 23.06394208376502,
            "y": 42.16039648007055
        },
        {
            "max_memory": 0,
            "aggressiveness": 0.19607047610825035,
            "harvest_percent": 0.4430450585723756,
            "x": 42.97613115260236,
            "y": 44.757838903003474
        },
        {
            "max_memory": 3,
            "aggressiveness": 0.2089661653427778,
            "harvest_percent": 0.6183932436765666,
            "x": 39.66087153150621,
            "y": 35.03309793230373
        },
        {
            "max_memory": 0,
            "aggressiveness": 0.24204837194554585,
            "harvest_percent": 0.5047689843222762,
            "x": 11.759366123943371,
            "y": 30.985377624546885
        },
        {
            "max_memory": 0,
            "aggressiveness": 0.212679035773963,
            "harvest_percent": 0.4165154234522741,
            "x": 2.242251418672503,
            "y": 38.08967163607256
        },
        {
            "max_memory": 0,
            "aggressiveness": 0.2437872556188041,
            "harvest_percent": 0.5871678809113924,
            "x": 32.00867141854521,
            "y": 35.75935454114226
        },
        {
            "max_memory": 0,
            "aggressiveness": 0.2406918398585898,
            "harvest_percent": 0.6246126094972908,
            "x": 35.76041500407713,
            "y": 38.81852410131362
        },
        {
            "max_memory": 0,
            "aggressiveness": 0.22215344548961788,
            "harvest_percent": 0.6568413328669963,
            "x": 32.00867141854521,
            "y": 35.75935454114226
        },
        {
            "max_memory": 0,
            "aggressiveness": 0.33858840385767164,
            "harvest_percent": 0.5247356755158163,
            "x": 13.04634205291989,
            "y": 12.608476190645558
        },
        {
            "max_memory": 1,
            "aggressiveness": 0.286455644424657,
            "harvest_percent": 0.5321124263768015,
            "x": 17.766113660113202,
            "y": 12.697898431470932
        },
        {
            "max_memory": 0,
            "aggressiveness": 0.32416249643966477,
            "harvest_percent": 0.6336325248080537,
            "x": 48.25539938458045,
            "y": 1.2400358577732862
        },
        {
            "max_memory": 1,
            "aggressiveness": 0.23480154134489337,
            "harvest_percent": 0.5747396389446382,
            "x": 5.798183405497969,
            "y": 35.719707056339416
        },
        {
            "max_memory": 2,
            "aggressiveness": 0.3956278243250222,
            "harvest_percent": 0.5875639213763995,
            "x": 35.61855605123129,
            "y": 16.94495409230228
        },
        {
            "max_memory": 0,
            "aggressiveness": 0.12313207519151463,
            "harvest_percent": 0.5577692125926083,
            "x": 43.502150036815394,
            "y": 18.713714365842115
        },
        {
            "max_memory": 0,
            "aggressiveness": 0.2750470260818913,
            "harvest_percent": 0.5586339547536812,
            "x": 14.645408259801101,
            "y": 18.988795825670707
        },
        {
            "max_memory": 0,
            "aggressiveness": 0.22047698333379934,
            "harvest_percent": 0.7243951405444097,
            "x": 1.3922712406157056,
            "y": 20.47337759522833
        },
        {
            "max_memory": 0,
            "aggressiveness": 0.3229903268016699,
            "harvest_percent": 0.5766277530865337,
            "x": 31.957188030851047,
            "y": 21.55160832522197
        },
        {
            "max_memory": 2,
            "aggressiveness": 0.24250694736878314,
            "harvest_percent": 0.4931403852662564,
            "x": 36.14504218502239,
            "y": 5.6029520724299955
        },
        {
            "max_memory": 2,
            "aggressiveness": 0.32455008264778784,
            "harvest_percent": 0.4356048636287133,
            "x": 4.40437529422843,
            "y": 22.80861531253232
        },
        {
            "max_memory": 0,
            "aggressiveness": 0.2852952807535176,
            "harvest_percent": 0.5927820768306078,
            "x": 17.224788740857,
            "y": 39.34617153549525
        },
        {
            "max_memory": 0,
            "aggressiveness": 0.15247409879332505,
            "harvest_percent": 0.6030832426896728,
            "x": 38.113495885507085,
            "y": 8.928315418765653
        },
        {
            "max_memory": 0,
            "aggressiveness": 0.19814496973105647,
            "harvest_percent": 0.6855915197439719,
            "x": 32.25653600601761,
            "y": 36.384066399933644
        },
        {
            "max_memory": 0,
            "aggressiveness": 0.21156669188013244,
            "harvest_percent": 0.5001150797411371,
            "x": 29.3870836820634,
            "y": 34.355896750882444
        },
        {
            "max_memory": 2,
            "aggressiveness": 0.23846974924069053,
            "harvest_percent": 0.49710233500922607,
            "x": 33.77946933505194,
            "y": 23.77239496243818
        },
        {
            "max_memory": 3,
            "aggressiveness": 0.15679949439523275,
            "harvest_percent": 0.4562681115150367,
            "x": 14.645408259801101,
            "y": 18.988795825670707
        },
        {
            "max_memory": 1,
            "aggressiveness": 0.16569530886930287,
            "harvest_percent": 0.42711539719437197,
            "x": 30.98110503897026,
            "y": 5.921904211235302
        },
        {
            "max_memory": 3,
            "aggressiveness": 0.15151891764762895,
            "harvest_percent": 0.6616377892870272,
            "x": 35.76041500407713,
            "y": 38.81852410131362
        },
        {
            "max_memory": 1,
            "aggressiveness": 0.3405825364625772,
            "harvest_percent": 0.5106242880174304,
            "x": 2.242251418672503,
            "y": 38.08967163607256
        },
        {
            "max_memory": 1,
            "aggressiveness": 0.16772754140056026,
            "harvest_percent": 0.495791899961923,
            "x": 23.06394208376502,
            "y": 42.16039648007055
        },
        {
            "max_memory": 0,
            "aggressiveness": 0.17222308982242257,
            "harvest_percent": 0.4681748877563937,
            "x": 41.12030516350206,
            "y": 26.955455099333143
        },
        {
            "max_memory": 1,
            "aggressiveness": 0.21818467776358183,
            "harvest_percent": 0.5690317038836608,
            "x": 32.25653600601761,
            "y": 36.384066399933644
        },
        {
            "max_memory": 0,
            "aggressiveness": 0.21121326939711504,
            "harvest_percent": 0.5106362599398813,
            "x": 17.1960782824064,
            "y": 25.687165502892984
        },
        {
            "max_memory": 1,
            "aggressiveness": 0.2596897893162376,
            "harvest_percent": 0.5697130311209534,
            "x": 5.798183405497969,
            "y": 35.719707056339416
        },
        {
            "max_memory": 2,
            "aggressiveness": 0.40911889696237663,
            "harvest_percent": 0.6958263757284114,
            "x": 4.40437529422843,
            "y": 22.80861531253232
        },
        {
            "max_memory": 0,
            "aggressiveness": 0.14277482422038662,
            "harvest_percent": 0.6033501290079878,
            "x": 35.76041500407713,
            "y": 38.81852410131362
        },
        {
            "max_memory": 1,
            "aggressiveness": 0.14600483362561045,
            "harvest_percent": 0.5919937181185916,
            "x": 37.072398132823174,
            "y": 47.63421220279792
        },
        {
            "max_memory": 2,
            "aggressiveness": 0.21759776211440146,
            "harvest_percent": 0.5769956111102732,
            "x": 23.595720233935992,
            "y": 11.438332591576527
        },
        {
            "max_memory": 0,
            "aggressiveness": 0.2646662504132457,
            "harvest_percent": 0.5282448052047303,
            "x": 48.25539938458045,
            "y": 1.2400358577732862
        },
        {
            "max_memory": 0,
            "aggressiveness": 0.2804708976475532,
            "harvest_percent": 0.4765695056235077,
            "x": 4.3372954042662055,
            "y": 20.831387486829854
        },
        {
            "max_memory": 2,
            "aggressiveness": 0.2297501135541557,
            "harvest_percent": 0.4890518452871993,
            "x": 3.5473573140349157,
            "y": 36.193652319735655
        },
        {
            "max_memory": 0,
            "aggressiveness": 0.2650834866881046,
            "harvest_percent": 0.6678670907030867,
            "x": 9.174208481186868,
            "y": 24.981769626688248
        },
        {
            "max_memory": 0,
            "aggressiveness": 0.23097784831769252,
            "harvest_percent": 0.5161466583051313,
            "x": 31.84917674948319,
            "y": 11.213502143493475
        },
        {
            "max_memory": 1,
            "aggressiveness": 0.13906197385562724,
            "harvest_percent": 0.5221049561921278,
            "x": 30.22424073468976,
            "y": 3.11314035373228
        },
        {
            "max_memory": 2,
            "aggressiveness": 0.3166057262029266,
            "harvest_percent": 0.6069638308352673,
            "x": 17.319673178177307,
            "y": 16.42836748914604
        },
        {
            "max_memory": 0,
            "aggressiveness": 0.23735969587086866,
            "harvest_percent": 0.5694425207545527,
            "x": 32.25653600601761,
            "y": 36.384066399933644
        },
        {
            "max_memory": 0,
            "aggressiveness": 0.18246096136859066,
            "harvest_percent": 0.6248332926679254,
            "x": 32.25653600601761,
            "y": 36.384066399933644
        },
        {
            "max_memory": 0,
            "aggressiveness": 0.29862582266044385,
            "harvest_percent": 0.61896325275995,
            "x": 32.25653600601761,
            "y": 36.384066399933644
        },
        {
            "max_memory": 0,
            "aggressiveness": 0.23890710799385068,
            "harvest_percent": 0.5445324831112962,
            "x": 32.25653600601761,
            "y": 36.384066399933644
        },
        {
            "max_memory": 0,
            "aggressiveness": 0.27722062023490457,
            "harvest_percent": 0.7024649806054023,
            "x": 32.25653600601761,
            "y": 36.384066399933644
        },
        {
            "max_memory": 0,
            "aggressiveness": 0.28381331212009453,
            "harvest_percent": 0.565558503521464,
            "x": 13.110411762892493,
            "y": 45.37018110659511
        },
        {
            "max_memory": 0,
            "aggressiveness": 0.24725786751058343,
            "harvest_percent": 0.5854699025890006,
            "x": 9.66736948011005,
            "y": 49.887435688456826
        },
        {
            "max_memory": 0,
            "aggressiveness": 0.18812987185296365,
            "harvest_percent": 0.5265129259466197,
            "x": 9.66736948011005,
            "y": 49.887435688456826
        },
        {
            "max_memory": 0,
            "aggressiveness": 0.2534869518548857,
            "harvest_percent": 0.44701542240540026,
            "x": 9.66736948011005,
            "y": 49.887435688456826
        },
        {
            "max_memory": 0,
            "aggressiveness": 0.22872250641126451,
            "harvest_percent": 0.614496621000899,
            "x": 9.66736948011005,
            "y": 49.887435688456826
        },
        {
            "max_memory": 1,
            "aggressiveness": 0.1433408715523279,
            "harvest_percent": 0.5484999756795974,
            "x": 9.66736948011005,
            "y": 49.887435688456826
        },
        {
            "max_memory": 3,
            "aggressiveness": 0.2740007579403478,
            "harvest_percent": 0.5992980118258764,
            "x": 4.40437529422843,
            "y": 22.80861531253232
        },
        {
            "max_memory": 0,
            "aggressiveness": 0.3139971068676327,
            "harvest_percent": 0.6318182124910573,
            "x": 4.40437529422843,
            "y": 22.80861531253232
        },
        {
            "max_memory": 0,
            "aggressiveness": 0.24595797650170145,
            "harvest_percent": 0.5065084468407158,
            "x": 23.06394208376502,
            "y": 42.16039648007055
        },
        {
            "max_memory": 0,
            "aggressiveness": 0.18372470951592246,
            "harvest_percent": 0.4272223719406161,
            "x": 31.84917674948319,
            "y": 11.213502143493475
        },
        {
            "max_memory": 2,
            "aggressiveness": 0.31443188448483733,
            "harvest_percent": 0.5677731584937764,
            "x": 31.84917674948319,
            "y": 11.213502143493475
        },
        {
            "max_memory": 0,
            "aggressiveness": 0.20606998925378606,
            "harvest_percent": 0.5297824479488864,
            "x": 31.84917674948319,
            "y": 11.213502143493475
        },
        {
            "max_memory": 1,
            "aggressiveness": 0.22046265117436117,
            "harvest_percent": 0.46016925115057267,
            "x": 31.84917674948319,
            "y": 11.213502143493475
        },
        {
            "max_memory": 0,
            "aggressiveness": 0.18657903141014645,
            "harvest_percent": 0.5777679086519644,
            "x": 31.84917674948319,
            "y": 11.213502143493475
        },
        {
            "max_memory": 3,
            "aggressiveness": 0.2217010987434562,
            "harvest_percent": 0.62445791325096,
            "x": 20.49174376914969,
            "y": 19.32632168551854
        },
        {
            "max_memory": 0,
            "aggressiveness": 0.16719240899561136,
            "harvest_percent": 0.5790027331266012,
            "x": 36.068742843261994,
            "y": 19.405007610666956
        },
        {
            "max_memory": 0,
            "aggressiveness": 0.2311555302616492,
            "harvest_percent": 0.536117210203991,
            "x": 36.068742843261994,
            "y": 19.405007610666956
        },
        {
            "max_memory": 1,
            "aggressiveness": 0.17975651978496643,
            "harvest_percent": 0.5911250188221245,
            "x": 36.068742843261994,
            "y": 19.405007610666956
        },
        {
            "max_memory": 0,
            "aggressiveness": 0.14354837119915523,
            "harvest_percent": 0.5264861544048158,
            "x": 36.068742843261994,
            "y": 19.405007610666956
        },
        {
            "max_memory": 1,
            "aggressiveness": 0.16718155556436934,
            "harvest_percent": 0.5301720947608605,
            "x": 28.384140433806788,
            "y": 8.423319851586985
        },
        {
            "max_memory": 0,
            "aggressiveness": 0.2457767370697962,
            "harvest_percent": 0.5543741833589894,
            "x": 28.384140433806788,
            "y": 8.423319851586985
        },
        {
            "max_memory": 0,
            "aggressiveness": 0.09192004609568967,
            "harvest_percent": 0.4763997146514771,
            "x": 28.384140433806788,
            "y": 8.423319851586985
        },
        {
            "max_memory": 1,
            "aggressiveness": 0.2033406658240109,
            "harvest_percent": 0.5904527747195951,
            "x": 1.3922712406157056,
            "y": 20.47337759522833
        },
        {
            "max_memory": 0,
            "aggressiveness": 0.17600387274901336,
            "harvest_percent": 0.6285420213208127,
            "x": 1.3922712406157056,
            "y": 20.47337759522833
        },
        {
            "max_memory": 0,
            "aggressiveness": 0.36199209506718155,
            "harvest_percent": 0.5564169835668085,
            "x": 1.3922712406157056,
            "y": 20.47337759522833
        },
        {
            "max_memory": 0,
            "aggressiveness": 0.2238170715493896,
            "harvest_percent": 0.6595926931822882,
            "x": 1.3922712406157056,
            "y": 20.47337759522833
        },
        {
            "max_memory": 2,
            "aggressiveness": 0.1736058010033827,
            "harvest_percent": 0.5280586594681322,
            "x": 14.645408259801101,
            "y": 18.988795825670707
        },
        {
            "max_memory": 4,
            "aggressiveness": 0.2251775084777815,
            "harvest_percent": 0.4258855732804051,
            "x": 14.645408259801101,
            "y": 18.988795825670707
        },
        {
            "max_memory": 3,
            "aggressiveness": 0.24329541425156553,
            "harvest_percent": 0.5311520195157687,
            "x": 14.645408259801101,
            "y": 18.988795825670707
        },
        {
            "max_memory": 0,
            "aggressiveness": 0.26632855768374425,
            "harvest_percent": 0.584463154180792,
            "x": 17.224788740857,
            "y": 39.34617153549525
        },
        {
            "max_memory": 0,
            "aggressiveness": 0.19232970729918492,
            "harvest_percent": 0.47879956547786606,
            "x": 31.957188030851047,
            "y": 21.55160832522197
        },
        {
            "max_memory": 1,
            "aggressiveness": 0.35942600519289336,
            "harvest_percent": 0.543331557057702,
            "x": 31.957188030851047,
            "y": 21.55160832522197
        },
        {
            "max_memory": 2,
            "aggressiveness": 0.24164491192777868,
            "harvest_percent": 0.6450716857494309,
            "x": 29.3870836820634,
            "y": 34.355896750882444
        },
        {
            "max_memory": 1,
            "aggressiveness": 0.09791506570422445,
            "harvest_percent": 0.5342675629090851,
            "x": 29.3870836820634,
            "y": 34.355896750882444
        },
        {
            "max_memory": 0,
            "aggressiveness": 0.24047070984523566,
            "harvest_percent": 0.47708161737538063,
            "x": 29.3870836820634,
            "y": 34.355896750882444
        },
        {
            "max_memory": 1,
            "aggressiveness": 0.33492518738517396,
            "harvest_percent": 0.6312729767443184,
            "x": 29.3870836820634,
            "y": 34.355896750882444
        },
        {
            "max_memory": 1,
            "aggressiveness": 0.26755992972319453,
            "harvest_percent": 0.57629069625798,
            "x": 32.00867141854521,
            "y": 35.75935454114226
        },
        {
            "max_memory": 0,
            "aggressiveness": 0.18040269913980705,
            "harvest_percent": 0.5944529762729123,
            "x": 42.97613115260236,
            "y": 44.757838903003474
        },
        {
            "max_memory": 0,
            "aggressiveness": 0.2513061087276084,
            "harvest_percent": 0.4623479115971971,
            "x": 42.97613115260236,
            "y": 44.757838903003474
        },
        {
            "max_memory": 1,
            "aggressiveness": 0.21443226550436081,
            "harvest_percent": 0.524071106943284,
            "x": 42.97613115260236,
            "y": 44.757838903003474
        },
        {
            "max_memory": 2,
            "aggressiveness": 0.2507157505039397,
            "harvest_percent": 0.6258545820052576,
            "x": 42.97613115260236,
            "y": 44.757838903003474
        },
        {
            "max_memory": 1,
            "aggressiveness": 0.18488990030008612,
            "harvest_percent": 0.6535599364280298,
            "x": 19.555743260343384,
            "y": 39.30582091985564
        },
        {
            "max_memory": 2,
            "aggressiveness": 0.4993457586524532,
            "harvest_percent": 0.6083742206240186,
            "x": 11.378064127347015,
            "y": 18.3552945919123
        },
        {
            "max_memory": 0,
            "aggressiveness": 0.252805192758709,
            "harvest_percent": 0.5885061681094133,
            "x": 14.42318629135466,
            "y": 43.16281248930383
        },
        {
            "max_memory": 0,
            "aggressiveness": 0.1896960480227368,
            "harvest_percent": 0.6314085604355834,
            "x": 14.42318629135466,
            "y": 43.16281248930383
        },
        {
            "max_memory": 0,
            "aggressiveness": 0.18481010817352636,
            "harvest_percent": 0.5968945913095169,
            "x": 43.43390089966997,
            "y": 42.86750142086883
        },
        {
            "max_memory": 2,
            "aggressiveness": 0.09834382518208315,
            "harvest_percent": 0.5571447752427843,
            "x": 43.43390089966997,
            "y": 42.86750142086883
        },
        {
            "max_memory": 0,
            "aggressiveness": 0.2092167269666404,
            "harvest_percent": 0.6000498703275478,
            "x": 43.43390089966997,
            "y": 42.86750142086883
        },
        {
            "max_memory": 0,
            "aggressiveness": 0.19115982343468668,
            "harvest_percent": 0.6612220658172491,
            "x": 43.43390089966997,
            "y": 42.86750142086883
        },
        {
            "max_memory": 2,
            "aggressiveness": 0.26990056681690555,
            "harvest_percent": 0.5331746474045364,
            "x": 43.43390089966997,
            "y": 42.86750142086883
        },
        {
            "max_memory": 0,
            "aggressiveness": 0.2745036913672873,
            "harvest_percent": 0.6629420945365517,
            "x": 13.04634205291989,
            "y": 12.608476190645558
        },
        {
            "max_memory": 1,
            "aggressiveness": 0.37520417638873427,
            "harvest_percent": 0.5841189921914159,
            "x": 13.04634205291989,
            "y": 12.608476190645558
        },
        {
            "max_memory": 2,
            "aggressiveness": 0.42088875773695256,
            "harvest_percent": 0.48223057882851245,
            "x": 13.04634205291989,
            "y": 12.608476190645558
        },
        {
            "max_memory": 1,
            "aggressiveness": 0.22028337264040015,
            "harvest_percent": 0.4000742887442606,
            "x": 30.98110503897026,
            "y": 5.921904211235302
        },
        {
            "max_memory": 0,
            "aggressiveness": 0.17681448066690528,
            "harvest_percent": 0.4165548029965307,
            "x": 30.98110503897026,
            "y": 5.921904211235302
        },
        {
            "max_memory": 0,
            "aggressiveness": 0.1646660156784482,
            "harvest_percent": 0.4703671811088938,
            "x": 30.98110503897026,
            "y": 5.921904211235302
        },
        {
            "max_memory": 1,
            "aggressiveness": 0.2656294725099869,
            "harvest_percent": 0.40195690857685284,
            "x": 30.98110503897026,
            "y": 5.921904211235302
        }
    ]
}