{
    "caves": [
        {
            "x": 3.8514933235497537,
            "y": 12.382230017081364,
            "max_capacity": 3
        },
        {
            "x": 28.93617860226265,
            "y": 21.138933870731762,
            "max_capacity": 3
        },
        {
            "x": 36.72759307487947,
            "y": 42.67295911508505,
            "max_capacity": 5
        },
        {
            "x": 29.76808536046361,
            "y": 18.597677419821917,
            "max_capacity": 4
        },
        {
            "x": 27.11122243176336,
            "y": 3.275441957775038,
            "max_capacity": 6
        },
        {
            "x": 46.10839365903293,
            "y": 5.43078060004526,
            "max_capacity": 4
        },
        {
            "x": 15.401511984144244,
            "y": 17.741982267841017,
            "max_capacity": 6
        },
        {
            "x": 48.7841002434302,
            "y": 9.531916242621453,
            "max_capacity": 3
        },
        {
            "x": 43.64035184643906,
            "y": 24.261178956955693,
            "max_capacity": 4
        },
        {
            "x": 29.723674589910182,
            "y": 19.663245871507446,
            "max_capacity": 3
        },
        {
            "x": 28.795180096596635,
            "y": 8.286532042970245,
            "max_capacity": 4
        },
        {
            "x": 43.6756490782734,
            "y": 14.922298982840342,
            "max_capacity": 7
        },
        {
            "x": 12.961567794761065,
            "y": 23.326263663382896,
            "max_capacity": 5
        },
        {
            "x": 7.8793546719553245,
            "y": 16.057470346454334,
            "max_capacity": 4
        },
        {
            "x": 35.53086850725441,
            "y": 10.634573749093052,
            "max_capacity": 4
        },
        {
            "x": 31.134081508246535,
            "y": 20.412192977377767,
            "max_capacity": 7
        },
        {
            "x": 34.9001555101773,
            "y": 2.96919266345147,
            "max_capacity": 4
        },
        {
            "x": 7.001249249179647,
            "y": 44.73833777590003,
            "max_capacity": 3
        },
        {
            "x": 34.272134472174805,
            "y": 16.85900099542672,
            "max_capacity": 3
        },
        {
            "x": 19.580204348785475,
            "y": 2.076916978738269,
            "max_capacity": 6
        },
        {
            "x": 22.053616749419437,
            "y": 24.673516270877677,
            "max_capacity": 6
        },
        {
            "x": 34.75202648939769,
            "y": 37.85611239151132,
            "max_capacity": 7
        },
        {
            "x": 42.822902937565885,
            "y": 27.861791691835847,
            "max_capacity": 5
        },
        {
            "x": 4.475740525849381,
            "y": 47.676253662964314,
            "max_capacity": 5
        },
        {
            "x": 11.126203858640038,
            "y": 25.338584989545744,
            "max_capacity": 7
        },
        {
            "x": 14.781355581422256,
            "y": 16.718285916280205,
            "max_capacity": 6
        },
        {
            "x": 45.00591900637571,
            "y": 35.61216710497165,
            "max_capacity": 3
        },
        {
            "x": 28.255290231799762,
            "y": 0.198825731579233,
            "max_capacity": 5
        },
        {
            "x": 42.75320637474739,
            "y": 28.24062819533633,
            "max_capacity": 4
        },
        {
            "x": 22.07960506249138,
            "y": 8.570067701801998,
            "max_capacity": 5
        },
        {
            "x": 29.824392067254596,
            "y": 32.70849691454524,
            "max_capacity": 6
        },
        {
            "x": 23.60892845246609,
            "y": 43.244826782284036,
            "max_capacity": 3
        },
        {
            "x": 8.471465774354254,
            "y": 38.58298096339279,
            "max_capacity": 4
        },
        {
            "x": 45.24123960241435,
            "y": 27.81266806513528,
            "max_capacity": 3
        },
        {
            "x": 15.196480741650165,
            "y": 4.968793721019243,
            "max_capacity": 3
        },
        {
            "x": 32.32638608316476,
            "y": 10.602628903357791,
            "max_capacity": 3
        },
        {
            "x": 16.047190712372544,
            "y": 18.922292523644956,
            "max_capacity": 5
        },
        {
            "x": 31.222998429323024,
            "y": 4.520954437066971,
            "max_capacity": 7
        },
        {
            "x": 14.593962589819093,
            "y": 35.45531925057801,
            "max_capacity": 3
        },
        {
            "x": 7.834532508320829,
            "y": 7.066144572346106,
            "max_capacity": 7
        },
        {
            "x": 5.772753563811783,
            "y": 4.4248063741162635,
            "max_capacity": 6
        },
        {
            "x": 11.972058567113313,
            "y": 45.75366745493359,
            "max_capacity": 3
        },
        {
            "x": 27.75743603648499,
            "y": 33.64858906577326,
            "max_capacity": 3
        },
        {
            "x": 29.38835814797255,
            "y": 4.8116880125533115,
            "max_capacity": 4
        },
        {
            "x": 4.919731584983173,
            "y": 30.764576001042627,
            "max_capacity": 6
        },
        {
            "x": 9.67078045998348,
            "y": 18.919470760262275,
            "max_capacity": 7
        },
        {
            "x": 40.354558077737586,
            "y": 38.363743503669895,
            "max_capacity": 4
        },
        {
            "x": 26.22504542397248,
            "y": 11.013563055842447,
            "max_capacity": 3
        },
        {
            "x": 44.764285391725025,
            "y": 11.790594672873606,
            "max_capacity": 6
        },
        {
            "x": 10.358111512967765,
            "y": 31.43442765206815,
            "max_capacity": 4
        }
    ],
    "bushes": [
        {
            "max_calories": 650,
            "x": 33.074211485362156,
            "y": 6.255978379710747
        },
        {
            "max_calories": 400,
            "x": 8.239731344557665,
            "y": 47.20980617179406
        },
        {
            "max_calories": 550,
            "x": 11.129624683839722,
            "y": 37.04166214663001
        },
        {
            "max_calories": 450,
            "x": 34.9023320438522,
            "y": 37.70000814667808
        },
        {
            "max_calories": 550,
            "x": 33.87719430754907,
            "y": 0.826830790028471
        },
        {
            "max_calories": 800,
            "x": 9.201810997394139,
            "y": 0.07422702592624342
        },
        {
            "max_calories": 500,
            "x": 19.623700030541773,
            "y": 43.46625515426702
        },
        {
            "max_calories": 400,
            "x": 46.768701443879465,
            "y": 4.980073888497488
        },
        {
            "max_calories": 550,
            "x": 17.038239638281404,
            "y": 36.04485465306905
        },
        {
            "max_calories": 450,
            "x": 15.046213434312545,
            "y": 6.914874535617827
        },
        {
            "max_calories": 550,
            "x": 29.007134859126488,
            "y": 37.49118983617546
        },
        {
            "max_calories": 600,
            "x": 15.141929013967104,
            "y": 38.89894511820203
        },
        {
            "max_calories": 600,
            "x": 43.50397543022996,
            "y": 16.053249003438903
        },
        {
            "max_calories": 750,
            "x": 16.715931318363907,
            "y": 29.353020885947632
        },
        {
            "max_calories": 600,
            "x": 25.213697151812504,
            "y": 47.25921992141713
        },
        {
            "max_calories": 700,
            "x": 11.074424744215976,
            "y": 41.660990950481555
        },
        {
            "max_calories": 600,
            "x": 25.568724895137123,
            "y": 10.316001499167033
        },
        {
            "max_calories": 800,
            "x": 34.321211308252906,
            "y": 49.197759389874406
        },
        {
            "max_calories": 750,
            "x": 37.3162510233674,
            "y": 3.61403152328848
        },
        {
            "max_calories": 450,
            "x": 34.192543269624835,
            "y": 31.30676621630068
        },
        {
            "max_calories": 800,
            "x": 17.854995275446996,
            "y": 28.485050583877374
        },
        {
            "max_calories": 700,
            "x": 42.81631802274378,
            "y": 22.34192422232454
        },
        {
            "max_calories": 800,
            "x": 48.04973503395768,
            "y": 14.521310189184721
        },
        {
            "max_calories": 400,
            "x": 44.035693507157184,
            "y": 14.391849715971405
        },
        {
            "max_calories": 750,
            "x": 19.23001359899153,
            "y": 43.27314310484247
        },
        {
            "max_calories": 550,
            "x": 21.732559666877442,
            "y": 40.60187477419559
        },
        {
            "max_calories": 550,
            "x": 24.983380286318024,
            "y": 32.23342003950838
        },
        {
            "max_calories": 650,
            "x": 48.371440993282874,
            "y": 26.183414977073422
        },
        {
            "max_calories": 750,
            "x": 33.90989651237204,
            "y": 34.84778608092771
        },
        {
            "max_calories": 400,
            "x": 23.297264209221296,
            "y": 31.57631688656789
        },
        {
            "max_calories": 700,
            "x": 3.606301240804044,
            "y": 3.9682769739788517
        },
        {
            "max_calories": 650,
            "x": 17.950599803649624,
            "y": 0.5076245758999065
        },
        {
            "max_calories": 750,
            "x": 29.215271255888336,
            "y": 25.404262089782943
        },
        {
            "max_calories": 600,
            "x": 46.487618338954185,
            "y": 27.73630715473907
        },
        {
            "max_calories": 800,
            "x": 39.56088195953173,
            "y": 36.55714245260499
        },
        {
            "max_calories": 650,
            "x": 2.759211755464391,
            "y": 6.742233976549788
        },
        {
            "max_calories": 550,
            "x": 11.018121610534099,
            "y": 34.60551727161301
        },
        {
            "max_calories": 400,
            "x": 2.2481192712240192,
            "y": 0.32346167902277956
        },
        {
            "max_calories": 400,
            "x": 35.45701902465821,
            "y": 33.70987402322733
        },
        {
            "max_calories": 600,
            "x": 38.90166549286516,
            "y": 29.69008110814154
        },
        {
            "max_calories": 500,
            "x": 31.249036544450732,
            "y": 36.40068652989259
        },
        {
            "max_calories": 700,
            "x": 44.2453943056246,
            "y": 47.51285155472888
        },
        {
            "max_calories": 600,
            "x": 20.447059260858975,
            "y": 22.989820210483693
        },
        {
            "max_calories": 650,
            "x": 30.665056740109208,
            "y": 39.44516181555649
        },
        {
            "max_calories": 550,
            "x": 33.683991756391976,
            "y": 21.803553657374696
        },
        {
            "max_calories": 750,
            "x": 39.473341564330816,
            "y": 11.14806930606425
        },
        {
            "max_calories": 800,
            "x": 24.86499835861983,
            "y": 14.817171247472027
        },
        {
            "max_calories": 400,
            "x": 37.43945328030653,
            "y": 27.87287123783789
        },
        {
            "max_calories": 550,
            "x": 15.267912513327486,
            "y": 6.463012044817379
        },
        {
            "max_calories": 700,
            "x": 14.855711086479689,
            "y": 24.247066181914278
        },
        {
            "max_calories": 800,
            "x": 17.78736595071037,
            "y": 33.809981669009886
        },
        {
            "max_calories": 500,
            "x": 13.658725821682188,
            "y": 5.760305921550801
        },
        {
            "max_calories": 600,
            "x": 48.35896815163983,
            "y": 39.69432340964285
        },
        {
            "max_calories": 550,
            "x": 32.34396774445562,
            "y": 25.674186918349346
        },
        {
            "max_calories": 650,
            "x": 28.585825439650076,
            "y": 4.161989838553137
        },
        {
            "max_calories": 650,
            "x": 27.03932401631008,
            "y": 18.511656335884545
        },
        {
            "max_calories": 550,
            "x": 33.70143912353363,
            "y": 40.21070009689065
        },
        {
            "max_calories": 600,
            "x": 19.048135453235826,
            "y": 40.398240657318155
        },
        {
            "max_calories": 700,
            "x": 5.247596350359663,
            "y": 21.772991278220232
        },
        {
            "max_calories": 700,
            "x": 26.577331425410033,
            "y": 7.45578497827969
        },
        {
            "max_calories": 700,
            "x": 2.968293687444956,
            "y": 22.224643520159027
        },
        {
            "max_calories": 550,
            "x": 30.05370160800006,
            "y": 21.680656093900076
        },
        {
            "max_calories": 700,
            "x": 26.255508993920817,
            "y": 20.385968329238285
        },
        {
            "max_calories": 450,
            "x": 21.885047654621932,
            "y": 42.37648797835987
        },
        {
            "max_calories": 400,
            "x": 2.53526730996807,
            "y": 14.028393053856686
        },
        {
            "max_calories": 400,
            "x": 17.517780171595877,
            "y": 15.643455856078885
        },
        {
            "max_calories": 700,
            "x": 2.0282921264173304,
            "y": 22.168623979265924
        },
        {
            "max_calories": 750,
            "x": 31.986500522282135,
            "y": 6.156141884980065
        },
        {
            "max_calories": 550,
            "x": 3.164572126927373,
            "y": 11.53089791987889
        },
        {
            "max_calories": 700,
            "x": 6.064764685697965,
            "y": 26.586884776223513
        },
        {
            "max_calories": 750,
            "x": 44.642048267835165,
            "y": 44.049125022316076
        },
        {
            "max_calories": 750,
            "x": 5.3902950523306625,
            "y": 37.468784058813114
        },
        {
            "max_calories": 450,
            "x": 25.8652653874881,
            "y": 32.32994986591086
        },
        {
            "max_calories": 550,
            "x": 16.965321146584568,
            "y": 39.790665731193364
        },
        {
            "max_calories": 700,
            "x": 49.124066535357294,
            "y": 7.453611614822103
        }
    ],
    "agents": [
        {
            "max_memory": 0,
            "aggressiveness": 0.5959460739759006,
            "harvest_percent": 0.6091064688767404,
            "x": 4.919731584983173,
            "y": 30.764576001042627
        },
        {
            "max_memory": 4,
            "aggressiveness": 0.43056993199941856,
            "harvest_percent": 0.5652232572471443,
            "x": 19.580204348785475,
            "y": 2.076916978738269
        },
        {
            "max_memory": 3,
            "aggressiveness": 0.5760273606136364,
            "harvest_percent": 0.5322431224182397,
            "x": 14.593962589819093,
            "y": 35.45531925057801
        },
        {
            "max_memory": 0,
            "aggressiveness": 0.45694611849838307,
            "harvest_percent": 0.4583938529051012,
            "x": 27.75743603648499,
            "y": 33.64858906577326
        },
        {
            "max_memory": 1,
            "aggressiveness": 0.507918892876957,
            "harvest_percent": 0.7432110791703879,
            "x": 27.11122243176336,
            "y": 3.275441957775038
        },
        {
            "max_memory": 3,
            "aggressiveness": 0.568519419820745,
            "harvest_percent": 0.5741630270969778,
            "x": 29.723674589910182,
            "y": 19.663245871507446
        },
        {
            "max_memory": 0,
            "aggressiveness": 0.5153912004895981,
            "harvest_percent": 0.6665994583691924,
            "x": 42.822902937565885,
            "y": 27.861791691835847
        },
        {
            "max_memory": 3,
            "aggressiveness": 0.35935766723988327,
            "harvest_percent": 0.45755236080669537,
            "x": 29.824392067254596,
            "y": 32.70849691454524
        },
        {
            "max_memory": 2,
            "aggressiveness": 0.6088688428978868,
            "harvest_percent": 0.6277375490450999,
            "x": 14.781355581422256,
            "y": 16.718285916280205
        },
        {
            "max_memory": 2,
            "aggressiveness": 0.3102252151959166,
            "harvest_percent": 0.44804588311393295,
            "x": 27.11122243176336,
            "y": 3.275441957775038
        },
        {
            "max_memory": 0,
            "aggressiveness": 0.5216524376064909,
            "harvest_percent": 0.6695945378638533,
            "x": 34.9001555101773,
            "y": 2.96919266345147
        },
        {
            "max_memory": 3,
            "aggressiveness": 0.4607199597251491,
            "harvest_percent": 0.6812111786570404,
            "x": 45.24123960241435,
            "y": 27.81266806513528
        },
        {
            "max_memory": 1,
            "aggressiveness": 0.5683724875343702,
            "harvest_percent": 0.7426173301827865,
            "x": 4.919731584983173,
            "y": 30.764576001042627
        },
        {
            "max_memory": 1,
            "aggressiveness": 0.4693691655707617,
            "harvest_percent": 0.560630899089112,
            "x": 22.053616749419437,
            "y": 24.673516270877677
        },
        {
            "max_memory": 0,
            "aggressiveness": 0.41847284042980776,
            "harvest_percent": 0.47114680205996406,
            "x": 19.580204348785475,
            "y": 2.076916978738269
        },
        {
            "max_memory": 0,
            "aggressiveness": 0.4405446451629551,
            "harvest_percent": 0.5868429466300745,
            "x": 11.126203858640038,
            "y": 25.338584989545744
        },
        {
            "max_memory": 3,
            "aggressiveness": 0.38680408291080265,
            "harvest_percent": 0.5143595778442818,
            "x": 10.358111512967765,
            "y": 31.43442765206815
        },
        {
            "max_memory": 0,
            "aggressiveness": 0.3913816641440277,
            "harvest_percent": 0.5494075178290582,
            "x": 31.222998429323024,
            "y": 4.520954437066971
        },
        {
            "max_memory": 0,
            "aggressiveness": 0.5702396121410055,
            "harvest_percent": 0.5452162052736423,
            "x": 42.75320637474739,
            "y": 28.24062819533633
        },
        {
            "max_memory": 0,
            "aggressiveness": 0.3964526173620497,
            "harvest_percent": 0.5710988618808415,
            "x": 42.822902937565885,
            "y": 27.861791691835847
        },
        {
            "max_memory": 0,
            "aggressiveness": 0.45287242174190706,
            "harvest_percent": 0.7544632237912291,
            "x": 42.75320637474739,
            "y": 28.24062819533633
        },
        {
            "max_memory": 0,
            "aggressiveness": 0.5997320884800822,
            "harvest_percent": 0.5258911968600172,
            "x": 31.134081508246535,
            "y": 20.412192977377767
        },
        {
            "max_memory": 0,
            "aggressiveness": 0.3509391469644036,
            "harvest_percent": 0.5005448022422405,
            "x": 29.824392067254596,
            "y": 32.70849691454524
        },
        {
            "max_memory": 0,
            "aggressiveness": 0.5630010181857681,
            "harvest_percent": 0.5746823333200277,
            "x": 46.10839365903293,
            "y": 5.43078060004526
        },
        {
            "max_memory": 0,
            "aggressiveness": 0.515394742158949,
            "harvest_percent": 0.5720883298176888,
            "x": 14.593962589819093,
            "y": 35.45531925057801
        },
        {
            "max_memory": 1,
            "aggressiveness": 0.39559786227904403,
            "harvest_percent": 0.5039961553939503,
            "x": 11.126203858640038,
            "y": 25.338584989545744
        },
        {
            "max_memory": 0,
            "aggressiveness": 0.4398824034397156,
            "harvest_percent": 0.6434626783347734,
            "x": 27.75743603648499,
            "y": 33.64858906577326
        },
        {
            "max_memory": 0,
            "aggressiveness": 0.5178842030633043,
            "harvest_percent": 0.48554862802170945,
            "x": 42.822902937565885,
            "y": 27.861791691835847
        },
        {
            "max_memory": 0,
            "aggressiveness": 0.36088394496212917,
            "harvest_percent": 0.5874354575651023,
            "x": 43.64035184643906,
            "y": 24.261178956955693
        },
        {
            "max_memory": 0,
            "aggressiveness": 0.4616566776362967,
            "harvest_percent": 0.4959903437896752,
            "x": 34.9001555101773,
            "y": 2.96919266345147
        },
        {
            "max_memory": 2,
            "aggressiveness": 0.37441175378933284,
            "harvest_percent": 0.4270149658289608,
            "x": 22.07960506249138,
            "y": 8.570067701801998
        },
        {
            "max_memory": 0,
            "aggressiveness": 0.4777828770634292,
            "harvest_percent": 0.716874876231881,
            "x": 45.24123960241435,
            "y": 27.81266806513528
        },
        {
            "max_memory": 3,
            "aggressiveness": 0.5572337483255122,
            "harvest_percent": 0.6900447384546262,
            "x": 10.358111512967765,
            "y": 31.43442765206815
        },
        {
            "max_memory": 2,
            "aggressiveness": 0.49708476597311935,
            "harvest_percent": 0.5400280028090558,
            "x": 7.8793546719553245,
            "y": 16.057470346454334
        },
        {
            "max_memory": 0,
            "aggressiveness": 0.43278505438476944,
            "harvest_percent": 0.8248799235824384,
            "x": 32.32638608316476,
            "y": 10.602628903357791
        },
        {
            "max_memory": 0,
            "aggressiveness": 0.51933391003873,
            "harvest_percent": 0.4725268894424369,
            "x": 29.38835814797255,
            "y": 4.8116880125533115
        },
        {
            "max_memory": 1,
            "aggressiveness": 0.3908111768190094,
            "harvest_percent": 0.7188645310687762,
            "x": 3.8514933235497537,
            "y": 12.382230017081364
        },
        {
            "max_memory": 2,
            "aggressiveness": 0.47286860167367484,
            "harvest_percent": 0.5314788538833916,
            "x": 22.07960506249138,
            "y": 8.570067701801998
        },
        {
            "max_memory": 0,
            "aggressiveness": 0.45971758479383856,
            "harvest_percent": 0.7117743719651382,
            "x": 23.60892845246609,
            "y": 43.244826782284036
        },
        {
            "max_memory": 0,
            "aggressiveness": 0.4684888974336089,
            "harvest_percent": 0.7114267835099017,
            "x": 31.222998429323024,
            "y": 4.520954437066971
        },
        {
            "max_memory": 0,
            "aggressiveness": 0.5826346166204529,
            "harvest_percent": 0.7280226786992192,
            "x": 36.72759307487947,
            "y": 42.67295911508505
        },
        {
            "max_memory": 2,
            "aggressiveness": 0.5898748992220744,
            "harvest_percent": 0.49117217925959245,
            "x": 27.75743603648499,
            "y": 33.64858906577326
        },
        {
            "max_memory": 3,
            "aggressiveness": 0.48358515251901363,
            "harvest_percent": 0.49701043615400425,
            "x": 7.8793546719553245,
            "y": 16.057470346454334
        },
        {
            "max_memory": 1,
            "aggressiveness": 0.48728219402122,
            "harvest_percent": 0.5863225273889563,
            "x": 42.822902937565885,
            "y": 27.861791691835847
        },
        {
            "max_memory": 2,
            "aggressiveness": 0.5588170314666793,
            "harvest_percent": 0.7106116725969572,
            "x": 28.93617860226265,
            "y": 21.138933870731762
        },
        {
            "max_memory": 3,
            "aggressiveness": 0.5476536189930573,
            "harvest_percent": 0.6892814121572696,
            "x": 23.60892845246609,
            "y": 43.244826782284036
        },
        {
            "max_memory": 0,
            "aggressiveness": 0.43238244265060655,
            "harvest_percent": 0.5323629275748625,
            "x": 15.196480741650165,
            "y": 4.968793721019243
        },
        {
            "max_memory": 4,
            "aggressiveness": 0.5715753877264065,
            "harvest_percent": 0.5839708961340914,
            "x": 31.222998429323024,
            "y": 4.520954437066971
        },
        {
            "max_memory": 2,
            "aggressiveness": 0.5032896944461389,
            "harvest_percent": 0.5275607252174743,
            "x": 35.53086850725441,
            "y": 10.634573749093052
        },
        {
            "max_memory": 3,
            "aggressiveness": 0.5716789461819062,
            "harvest_percent": 0.6101603506166517,
            "x": 31.134081508246535,
            "y": 20.412192977377767
        },
        {
            "max_memory": 1,
            "aggressiveness": 0.5086920390959073,
            "harvest_percent": 0.6487857962979332,
            "x": 7.001249249179647,
            "y": 44.73833777590003
        },
        {
            "max_memory": 0,
            "aggressiveness": 0.483584557630112,
            "harvest_percent": 0.7312288028955021,
            "x": 8.471465774354254,
            "y": 38.58298096339279
        },
        {
            "max_memory": 2,
            "aggressiveness": 0.3965833718828764,
            "harvest_percent": 0.5965481941403173,
            "x": 10.358111512967765,
            "y": 31.43442765206815
        },
        {
            "max_memory": 1,
            "aggressiveness": 0.3666338497519539,
            "harvest_percent": 0.6102816749042441,
            "x": 11.126203858640038,
            "y": 25.338584989545744
        },
        {
            "max_memory": 2,
            "aggressiveness": 0.5110592947942622,
            "harvest_percent": 0.506381390649365,
            "x": 42.75320637474739,
            "y": 28.24062819533633
        },
        {
            "max_memory": 0,
            "aggressiveness": 0.4932649392517695,
            "harvest_percent": 0.41071490310304504,
            "x": 34.75202648939769,
            "y": 37.85611239151132
        },
        {
            "max_memory": 3,
            "aggressiveness": 0.5808264854093684,
            "harvest_percent": 0.3849389277148413,
            "x": 32.32638608316476,
            "y": 10.602628903357791
        },
        {
            "max_memory": 1,
            "aggressiveness": 0.512956738134113,
            "harvest_percent": 0.46360598206091863,
            "x": 10.358111512967765,
            "y": 31.43442765206815
        },
        {
            "max_memory": 0,
            "aggressiveness": 0.4451282890608367,
            "harvest_percent": 0.5887211910999512,
            "x": 29.38835814797255,
            "y": 4.8116880125533115
        },
        {
            "max_memory": 1,
            "aggressiveness": 0.4441700153629152,
            "harvest_percent": 0.5853028973471855,
            "x": 15.196480741650165,
            "y": 4.968793721019243
        },
        {
            "max_memory": 1,
            "aggressiveness": 0.565973677970088,
            "harvest_percent": 0.6337698780295373,
            "x": 23.60892845246609,
            "y": 43.244826782284036
        },
        {
            "max_memory": 4,
            "aggressiveness": 0.5915171794564548,
            "harvest_percent": 0.5047076237555645,
            "x": 11.126203858640038,
            "y": 25.338584989545744
        },
        {
            "max_memory": 4,
            "aggressiveness": 0.48387612814484465,
            "harvest_percent": 0.5374493893854433,
            "x": 31.222998429323024,
            "y": 4.520954437066971
        },
        {
            "max_memory": 4,
            "aggressiveness": 0.5247650215360162,
            "harvest_percent": 0.6925084447071015,
            "x": 27.11122243176336,
            "y": 3.275441957775038
        },
        {
            "max_memory": 2,
            "aggressiveness": 0.4726180861414506,
            "harvest_percent": 0.6232017611180707,
            "x": 4.919731584983173,
            "y": 30.764576001042627
        },
        {
            "max_memory": 1,
            "aggressiveness": 0.5199805587657726,
            "harvest_percent": 0.6837686707332109,
            "x": 26.22504542397248,
            "y": 11.013563055842447
        },
        {
            "max_memory": 5,
            "aggressiveness": 0.5787479223274701,
            "harvest_percent": 0.5614254595170876,
            "x": 14.593962589819093,
            "y": 35.45531925057801
        },
        {
            "max_memory": 1,
            "aggressiveness": 0.3992138445472009,
            "harvest_percent": 0.6424817753696656,
            "x": 11.126203858640038,
            "y": 25.338584989545744
        },
        {
            "max_memory": 2,
            "aggressiveness": 0.5158163174847542,
            "harvest_percent": 0.6526196291898241,
            "x": 11.126203858640038,
            "y": 25.338584989545744
        },
        {
            "max_memory": 1,
            "aggressiveness": 0.6387089849347383,
            "harvest_percent": 0.6817657654924046,
            "x": 28.795180096596635,
            "y": 8.286532042970245
        },
        {
            "max_memory": 2,
            "aggressiveness": 0.5651038007165506,
            "harvest_percent": 0.6414778582159928,
            "x": 46.10839365903293,
            "y": 5.43078060004526
        },
        {
            "max_memory": 2,
            "aggressiveness": 0.49960687449801494,
            "harvest_percent": 0.5648179715428747,
            "x": 11.972058567113313,
            "y": 45.75366745493359
        },
        {
            "max_memory": 4,
            "aggressiveness": 0.6212887405906078,
            "harvest_percent": 0.5974525523096667,
            "x": 45.24123960241435,
            "y": 27.81266806513528
        },
        {
            "max_memory": 0,
            "aggressiveness": 0.5907491036437009,
            "harvest_percent": 0.7072695796122593,
            "x": 34.75202648939769,
            "y": 37.85611239151132
        },
        {
            "max_memory": 1,
            "aggressiveness": 0.4652201902177226,
            "harvest_percent": 0.5509219705885224,
            "x": 43.64035184643906,
            "y": 24.261178956955693
        },
        {
            "max_memory": 2,
            "aggressiveness": 0.5441858892722714,
            "harvest_percent": 0.5033671805472207,
            "x": 12.961567794761065,
            "y": 23.326263663382896
        },
        {
            "max_memory": 0,
            "aggressiveness": 0.4333818355257004,
            "harvest_percent": 0.8068160138555047,
            "x": 42.75320637474739,
            "y": 28.24062819533633
        },
        {
            "max_memory": 1,
            "aggressiveness": 0.5899666096275046,
            "harvest_percent": 0.7770539543211838,
            "x": 7.834532508320829,
            "y": 7.066144572346106
        },
        {
            "max_memory": 0,
            "aggressiveness": 0.5464864553897946,
            "harvest_percent": 0.6483104750410503,
            "x": 14.781355581422256,
            "y": 16.718285916280205
        },
        {
            "max_memory": 3,
            "aggressiveness": 0.4980016968671951,
            "harvest_percent": 0.526672312889404,
            "x": 27.11122243176336,
            "y": 3.275441957775038
        },
        {
            "max_memory": 1,
            "aggressiveness": 0.3906874360327267,
            "harvest_percent": 0.5026370101095442,
            "x": 27.11122243176336,
            "y": 3.275441957775038
        },
        {
            "max_memory": 0,
            "aggressiveness": 0.3260369875993503,
            "harvest_percent": 0.5282572037334361,
            "x": 27.11122243176336,
            "y": 3.275441957775038
        },
        {
            "max_memory": 2,
            "aggressiveness": 0.49718442029515186,
            "harvest_percent": 0.6588412468199185,
            "x": 46.10839365903293,
            "y": 5.43078060004526
        },
        {
            "max_memory": 3,
            "aggressiveness": 0.507975697809239,
            "harvest_percent": 0.5287245257473028,
            "x": 46.10839365903293,
            "y": 5.43078060004526
        },
        {
            "max_memory": 0,
            "aggressiveness": 0.4546437661877521,
            "harvest_percent": 0.5857826564104263,
            "x": 43.64035184643906,
            "y": 24.261178956955693
        },
        {
            "max_memory": 0,
            "aggressiveness": 0.35137559064189,
            "harvest_percent": 0.5165721146240546,
            "x": 43.64035184643906,
            "y": 24.261178956955693
        },
        {
            "max_memory": 4,
            "aggressiveness": 0.41415648808632194,
            "harvest_percent": 0.5005678002766337,
            "x": 7.8793546719553245,
            "y": 16.057470346454334
        },
        {
            "max_memory": 0,
            "aggressiveness": 0.5733930611868381,
            "harvest_percent": 0.5921309762337852,
            "x": 7.8793546719553245,
            "y": 16.057470346454334
        },
        {
            "max_memory": 0,
            "aggressiveness": 0.6302368787214209,
            "harvest_percent": 0.5544421047504091,
            "x": 31.134081508246535,
            "y": 20.412192977377767
        },
        {
            "max_memory": 0,
            "aggressiveness": 0.5262793959285352,
            "harvest_percent": 0.5143093408350979,
            "x": 31.134081508246535,
            "y": 20.412192977377767
        },
        {
            "max_memory": 3,
            "aggressiveness": 0.6452967825122464,
            "harvest_percent": 0.6511385397003372,
            "x": 31.134081508246535,
            "y": 20.412192977377767
        },
        {
            "max_memory": 0,
            "aggressiveness": 0.55439413231262,
            "harvest_percent": 0.49340702666417346,
            "x": 31.134081508246535,
            "y": 20.412192977377767
        },
        {
            "max_memory": 3,
            "aggressiveness": 0.5420157633164238,
            "harvest_percent": 0.5284660024717784,
            "x": 31.134081508246535,
            "y": 20.412192977377767
        },
        {
            "max_memory": 0,
            "aggressiveness": 0.5110855713543823,
            "harvest_percent": 0.6426101446052565,
            "x": 34.9001555101773,
            "y": 2.96919266345147
        },
        {
            "max_memory": 2,
            "aggressiveness": 0.5747959046829403,
            "harvest_percent": 0.505523208167432,
            "x": 34.9001555101773,
            "y": 2.96919266345147
        },
        {
            "max_memory": 2,
            "aggressiveness": 0.4907221682959398,
            "harvest_percent": 0.45194674918670374,
            "x": 19.580204348785475,
            "y": 2.076916978738269
        },
        {
            "max_memory": 1,
            "aggressiveness": 0.48341802115207566,
            "harvest_percent": 0.605035987719365,
            "x": 19.580204348785475,
            "y": 2.076916978738269
        },
        {
            "max_memory": 1,
            "aggressiveness": 0.4710122742248017,
            "harvest_percent": 0.5905269201757453,
            "x": 19.580204348785475,
            "y": 2.076916978738269
        },
        {
            "max_memory": 1,
            "aggressiveness": 0.3755168160855065,
            "harvest_percent": 0.5765974873817747,
            "x": 19.580204348785475,
            "y": 2.076916978738269
        },
        {
            "max_memory": 0,
            "aggressiveness": 0.5784941540036267,
            "harvest_percent": 0.6293045103700139,
            "x": 34.75202648939769,
            "y": 37.85611239151132
        },
        {
            "max_memory": 1,
            "aggressiveness": 0.5190134828961812,
            "harvest_percent": 0.6441867395411933,
            "x": 34.75202648939769,
            "y": 37.85611239151132
        },
        {
            "max_memory": 0,
            "aggressiveness": 0.44936855325542235,
            "harvest_percent": 0.5880755383741514,
            "x": 34.75202648939769,
            "y": 37.85611239151132
        },
        {
            "max_memory": 1,
            "aggressiveness": 0.5127242437901792,
            "harvest_percent": 0.6584756362117383,
            "x": 34.75202648939769,
            "y": 37.85611239151132
        },
        {
            "max_memory": 0,
            "aggressiveness": 0.63318285808815,
            "harvest_percent": 0.4618142277058542,
            "x": 34.75202648939769,
            "y": 37.85611239151132
        },
        {
            "max_memory": 0,
            "aggressiveness": 0.6098445437746397,
            "harvest_percent": 0.515977046002809,
            "x": 42.822902937565885,
            "y": 27.861791691835847
        },
        {
            "max_memory": 2,
            "aggressiveness": 0.3861616761937553,
            "harvest_percent": 0.5472697410828081,
            "x": 11.126203858640038,
            "y": 25.338584989545744
        },
        {
            "max_memory": 0,
            "aggressiveness": 0.5371503772111522,
            "harvest_percent": 0.5878537381876346,
            "x": 14.781355581422256,
            "y": 16.718285916280205
        },
        {
            "max_memory": 0,
            "aggressiveness": 0.5367561741314368,
            "harvest_percent": 0.7310146449606172,
            "x": 14.781355581422256,
            "y": 16.718285916280205
        },
        {
            "max_memory": 0,
            "aggressiveness": 0.4792633552188231,
            "harvest_percent": 0.6890378381396186,
            "x": 14.781355581422256,
            "y": 16.718285916280205
        },
        {
            "max_memory": 1,
            "aggressiveness": 0.5014678964452688,
            "harvest_percent": 0.6332927373163131,
            "x": 14.781355581422256,
            "y": 16.718285916280205
        },
        {
            "max_memory": 2,
            "aggressiveness": 0.4912672963838425,
            "harvest_percent": 0.43562936985468187,
            "x": 22.07960506249138,
            "y": 8.570067701801998
        },
        {
            "max_memory": 0,
            "aggressiveness": 0.5052564746182642,
            "harvest_percent": 0.47204408489783,
            "x": 22.07960506249138,
            "y": 8.570067701801998
        },
        {
            "max_memory": 3,
            "aggressiveness": 0.3269044972185206,
            "harvest_percent": 0.38404479299986216,
            "x": 22.07960506249138,
            "y": 8.570067701801998
        },
        {
            "max_memory": 2,
            "aggressiveness": 0.44150214920620545,
            "harvest_percent": 0.4715938176771954,
            "x": 29.824392067254596,
            "y": 32.70849691454524
        },
        {
            "max_memory": 1,
            "aggressiveness": 0.42393870205414436,
            "harvest_percent": 0.4851317253872561,
            "x": 29.824392067254596,
            "y": 32.70849691454524
        },
        {
            "max_memory": 0,
            "aggressiveness": 0.3146457866610989,
            "harvest_percent": 0.4207732926485419,
            "x": 29.824392067254596,
            "y": 32.70849691454524
        },
        {
            "max_memory": 0,
            "aggressiveness": 0.44422737422783215,
            "harvest_percent": 0.5160096904672696,
            "x": 29.824392067254596,
            "y": 32.70849691454524
        },
        {
            "max_memory": 0,
            "aggressiveness": 0.3566405468490915,
            "harvest_percent": 0.5841681923832813,
            "x": 15.196480741650165,
            "y": 4.968793721019243
        },
        {
            "max_memory": 2,
            "aggressiveness": 0.5580102728727787,
            "harvest_percent": 0.6181776604818715,
            "x": 32.32638608316476,
            "y": 10.602628903357791
        },
        {
            "max_memory": 3,
            "aggressiveness": 0.5796315752163996,
            "harvest_percent": 0.5907284871486866,
            "x": 31.222998429323024,
            "y": 4.520954437066971
        },
        {
            "max_memory": 6,
            "aggressiveness": 0.5695552872728841,
            "harvest_percent": 0.6116916582098184,
            "x": 31.222998429323024,
            "y": 4.520954437066971
        },
        {
            "max_memory": 4,
            "aggressiveness": 0.4215726117216198,
            "harvest_percent": 0.5900305042089244,
            "x": 31.222998429323024,
            "y": 4.520954437066971
        },
        {
            "max_memory": 2,
            "aggressiveness": 0.4721926105563297,
            "harvest_percent": 0.6304058687445657,
            "x": 29.38835814797255,
            "y": 4.8116880125533115
        },
        {
            "max_memory": 0,
            "aggressiveness": 0.4210623986666274,
            "harvest_percent": 0.5153160061360782,
            "x": 29.38835814797255,
            "y": 4.8116880125533115
        },
        {
            "max_memory": 0,
            "aggressiveness": 0.4253953839644208,
            "harvest_percent": 0.7230395645957399,
            "x": 4.919731584983173,
            "y": 30.764576001042627
        },
        {
            "max_memory": 0,
            "aggressiveness": 0.5174060366583311,
            "harvest_percent": 0.5997184101770222,
            "x": 4.919731584983173,
            "y": 30.764576001042627
        },
        {
            "max_memory": 2,
            "aggressiveness": 0.43980749457681767,
            "harvest_percent": 0.5898083212910017,
            "x": 4.919731584983173,
            "y": 30.764576001042627
        }
    ]
}